Workbook

Sheet README
A1: SpaceX valuation — Excel companion to 'Valuing SpaceX: Cash Flows versus the Cost of Capital'
A2: Alexander F. Wagner, June 2026. Paper: ssrn.com/abstract=6918120. Code: github.com/alex-wagner-research/spacex-valuation
A4: Comments and corrections are very welcome (alexander.wagner@df.uzh.ch). This workbook was put
A5: together quickly around a live IPO; if something looks off, it may well be.
A7: Tabs:
A8: Inputs — every assumption, blue on yellow, with its source. Change these.
A9: DCF — the deterministic three-segment valuation as a classic year-by-year
A10: waterfall with a step-by-step terminal value (paper Section 4), plus the
A11: direct-to-cell underlying business.
A12: Options — the expansion claims by their closed forms, the Mars probability tree,
A13: and the imported abandonment option (paper Section 5).
A14: MonteCarlo — 1,000 live trials of the correlated segment model (paper Section 4.3):
... A28: Appendix B.

Sheet Inputs
A1: Inputs — change the blue cells; every tab updates
A2: Values in $M unless noted. Paper: ssrn.com/abstract=6918120 (Table 1, Appendix A).
A5: Segments (2025 figures from the prospectus; targets, margins, volatilities per paper Table 1)
A6: Launch: revenue 2025 | B6: 4086 | C6: Prospectus, segment results (FWP acc. 0001628280-26-041013)
A7: Launch: revenue target 2036 | B7: 40000 | C7: Damodaran, June 2026 valuation (paper Sec. 4)
A8: Launch: operating margin 2025 | B8: 0.3 | C8: Prospectus, segment results
A9: Launch: terminal margin | B9: 0.45 | C9: Comparables-disciplined (paper Sec. 4); xAI 25% is the boundary case
A10: Launch: sales-to-capital | B10: 3.5 | C10: Damodaran convention (paper Table 1)
A11: Launch: revenue volatility, initial | B11: 0.18 | C11: Calibrated so dispersion lies between the two published simulations (Table 1)
A12: Launch: revenue volatility, long run | B12: 0.08 | C12: Paper Table 1
A13: Starlink: revenue 2025 | B13: 11387 | C13: Prospectus, segment results (FWP acc. 0001628280-26-041013)
A14: Starlink: revenue target 2036 | B14: 120000 | C14: Damodaran, June 2026 valuation (paper Sec. 4)
A15: Starlink: operating margin 2025 | B15: 0.35 | C15: Prospectus, segment results
A16: Starlink: terminal margin | B16: 0.6 | C16: Comparables-disciplined (paper Sec. 4); xAI 25% is the boundary case
A17: Starlink: sales-to-capital | B17: 4 | C17: Damodaran convention (paper Table 1)
... A26: xAI: revenue volatility, long run | B26: 0.15 | C26: Paper Table 1
A28: Firm-level
A29: Cost of capital (WACC) | B29: 0.0825 | C29: Damodaran bottom-up CAPM: business-weighted relevered betas (paper Sec. 4.2)
A30: Terminal growth | B30: 0.0456 | C30: Equals the June 2026 risk-free rate (Damodaran convention)
A31: Terminal ROIC | B31: 0.15 | C31: Paper Table 1; sets perpetuity reinvestment g/ROIC
A32: Tax rate, current effective | B32: 0.1 | C32: Prospectus financials
A33: Tax rate, marginal | B33: 0.25 | C33: Paper Table 1
A34: Cash | B34: 24747 | C34: Prospectus balance sheet
A35: Debt | B35: 22896 | C35: Prospectus balance sheet
A36: IPO proceeds | B36: 75000 | C36: Offering: 555.6M shares at $135
A37: Shares outstanding (M) | B37: 13091 | C37: 12,535M pre-offering + 556M new; CEO unvested award excluded (paper fn.)
A38: Common-factor correlation rho | B38: 0.3 | C38: Paper Table 1 (segments share one demand factor)
A39: Volatility decay kappa | B39: 0.2 | C39: Paper Appendix A.1 (uncertainty resolves over time)
A41: Expansion claims (paper Sec. 5.1, Appendix A.2)
A42: DTC: 2025 revenue | B42: 500 | C42: DTC underlying segment (Appendix A.2)
A43: DTC: revenue target 2036 | B43: 15000 | C43: Between D2D forecasts of roughly $3-12B (2030) and ~$100B long-run
A44: DTC: margin 2025 | B44: -0.2 | C44: Appendix A.2
A45: DTC: terminal margin | B45: 0.55 | C45: Appendix A.2
A46: DTC: sales-to-capital | B46: 4 | C46: Appendix A.2
A47: DTC: investment I | B47: 12000 | C47: Next-generation constellation cost (paper Sec. 5.1)
A48: DTC: gate year tau | B48: 4 | C48: Appendix A.2
A49: DTC: volatility sigma | B49: 0.55 | C49: Appendix A.2
A50: Starship: underlying V | B50: 110000 | C50: Capitalized launch pool $14-41B/yr: CRS IF12900, NASA OIG (App. A.3)
A51: Starship: investment I | B51: 30000 | C51: Over $15B spent plus $10-25B infrastructure (App. A.3)
A52: Starship: gate year tau | B52: 5 | C52: Appendix A.2
A53: Starship: volatility sigma | B53: 0.5 | C53: Appendix A.2
A54: Starship: P(technical trigger) | B54: 0.6 | C54: Author judgment, varied in the inversion (paper Sec. 5.1)
A56: Mars sovereign-program tree (paper Appendix A.2; budget analogs: ISS, Artemis, Antarctica)
A57: Mars: contractor margin | B57: 0.3 | C57: HLS-style prime-contractor margin (App. A.2)
A58: Mars: program start year | B58: 10 | C58: Appendix A.2
A59: Mars: robotic revenue/yr | B59: 500 | C59: Mars budget line enacted January 2026 (App. A.3)
A60: Mars: P(robotic) | B60: 0.9 | C60: Appendix A.2
A61: Mars: crewed revenue/yr | B61: 2500 | C61: Artemis-class envelope $5-8B/yr (App. A.2)
A62: Mars: crewed co-investment | B62: 5000 | C62: HLS precedent (App. A.2)
A63: Mars: P(crewed given trigger) | B63: 0.25 | C63: Appendix A.2
A64: Mars: settlement revenue/yr | B64: 10000 | C64: Settlement-class envelope $15-30B/yr (App. A.2)
A65: Mars: settlement co-investment | B65: 15000 | C65: Appendix A.2
A66: Mars: P(settlement given crewed) | B66: 0.25 | C66: One of three crewed initiatives since 1989 survived (App. A.2)
A68: Imported from the Python model (no formula representation)
A69: xAI abandonment option | B69: 1492 | C69: Least-squares Monte Carlo (venture_option.py; paper Sec. 5.2); salvage 0
A70: xAI venture floor | B70: 22555 | C70: Venture model with optimal abandonment (paper Sec. 6 sum of parts)
A71: xAI winning-model value | B71: 288402 | C71: xAI segment at a 30% terminal margin (paper Sec. 4)
A73: Inversion
A74: Target share price ($) | B74: 135 | C74: The offer price; change to read any price's implied discount rate

Sheet DCF
A1: Deterministic DCF — paper Section 4, Appendix A.1 (all values $M)
A2: The classic waterfall, year by year: revenue, margin, EBIT, taxes, reinvestment, FCFF, discounting; then the terminal value step by step. Margins and the tax rate ramp linearly; taxes apply to positive EBIT only; reinvestment is floored at zero.
C3: 2026 | D3: 2027 | E3: 2028 | F3: 2029 | G3: 2030 | H3: 2031 | I3: 2032 | J3: 2033 | K3: 2034 | L3: 2035 | M3: 2036
A4: Year index t | C4: 1 | D4: 2 | E4: 3 | F4: 4 | G4: 5 | H4: 6 | I4: 7 | J4: 8 | K4: 9 | L4: 10 | M4: 11
A5: Tax rate (ramps to marginal) | C5: =Inputs!$B$32+(Inputs!$B$33-Inputs!$B$32)*C$4/11 -> 0.11363636 | D5: =Inputs!$B$32+(Inputs!$B$33-Inputs!$B$32)*D$4/11 -> 0.12727273 | E5: =Inputs!$B$32+(Inputs!$B$33-Inputs!$B$32)*E$4/11 -> 0.14090909 | F5: =Inputs!$B$32+(Inputs!$B$33-Inputs!$B$32)*F$4/11 -> 0.15454545 | G5: =Inputs!$B$32+(Inputs!$B$33-Inputs!$B$32)*G$4/11 -> 0.16818182 | H5: =Inputs!$B$32+(Inputs!$B$33-Inputs!$B$32)*H$4/11 -> 0.18181818 | I5: =Inputs!$B$32+(Inputs!$B$33-Inputs!$B$32)*I$4/11 -> 0.19545455 | J5: =Inputs!$B$32+(Inputs!$B$33-Inputs!$B$32)*J$4/11 -> 0.20909091 | ... M5: =Inputs!$B$32+(Inputs!$B$33-Inputs!$B$32)*M$4/11 -> 0.25
A6: Discount factor 1/(1+WACC)^t | C6: =1/(1+Inputs!$B$29)^C$4 -> 0.92378753 | D6: =1/(1+Inputs!$B$29)^D$4 -> 0.8533834 | E6: =1/(1+Inputs!$B$29)^E$4 -> 0.78834494 | F6: =1/(1+Inputs!$B$29)^F$4 -> 0.72826322 | G6: =1/(1+Inputs!$B$29)^G$4 -> 0.67276048 | H6: =1/(1+Inputs!$B$29)^H$4 -> 0.62148775 | I6: =1/(1+Inputs!$B$29)^I$4 -> 0.57412263 | J6: =1/(1+Inputs!$B$29)^J$4 -> 0.53036732 | ... M6: =1/(1+Inputs!$B$29)^M$4 -> 0.4181124
A8: Launch | D8: growth to 2036 target g: | F8: =(Inputs!$B$7/Inputs!$B$6)^(1/11)-1 -> 0.23046493
A9: Revenue | C9: =(Inputs!$B$6)*(1+DCF!$F$8) -> 5027.6797 | D9: =C9*(1+DCF!$F$8) -> 6186.3835 | E9: =D9*(1+DCF!$F$8) -> 7612.1279 | F9: =E9*(1+DCF!$F$8) -> 9366.4565 | G9: =F9*(1+DCF!$F$8) -> 11525.096 | H9: =G9*(1+DCF!$F$8) -> 14181.227 | I9: =H9*(1+DCF!$F$8) -> 17449.502 | J9: =I9*(1+DCF!$F$8) -> 21471 | K9: =J9*(1+DCF!$F$8) -> 26419.313 | ... M9: =L9*(1+DCF!$F$8) -> 40000
A10: (x) Operating margin | C10: =Inputs!$B$8+(Inputs!$B$9-Inputs!$B$8)*C$4/11 -> 0.31363636 | D10: =Inputs!$B$8+(Inputs!$B$9-Inputs!$B$8)*D$4/11 -> 0.32727273 | E10: =Inputs!$B$8+(Inputs!$B$9-Inputs!$B$8)*E$4/11 -> 0.34090909 | F10: =Inputs!$B$8+(Inputs!$B$9-Inputs!$B$8)*F$4/11 -> 0.35454545 | G10: =Inputs!$B$8+(Inputs!$B$9-Inputs!$B$8)*G$4/11 -> 0.36818182 | H10: =Inputs!$B$8+(Inputs!$B$9-Inputs!$B$8)*H$4/11 -> 0.38181818 | I10: =Inputs!$B$8+(Inputs!$B$9-Inputs!$B$8)*I$4/11 -> 0.39545455 | J10: =Inputs!$B$8+(Inputs!$B$9-Inputs!$B$8)*J$4/11 -> 0.40909091 | ... M10: =Inputs!$B$8+(Inputs!$B$9-Inputs!$B$8)*M$4/11 -> 0.45
A11: (=) EBIT | C11: =C9*C10 -> 1576.8632 | D11: =D9*D10 -> 2024.6346 | E11: =E9*E10 -> 2595.0436 | F11: =F9*F10 -> 3320.8346 | G11: =G9*G10 -> 4243.3309 | H11: =H9*H10 -> 5414.6502 | I11: =I9*I10 -> 6900.4849 | J11: =J9*J10 -> 8783.591 | ... M11: =M9*M10 -> 18000
A12: (-) Taxes (on positive EBIT) | C12: =C$5*MAX(C11,0) -> 179.189 | D12: =D$5*MAX(D11,0) -> 257.68077 | E12: =E$5*MAX(E11,0) -> 365.66524 | F12: =F$5*MAX(F11,0) -> 513.21989 | G12: =G$5*MAX(G11,0) -> 713.6511 | H12: =H$5*MAX(H11,0) -> 984.48185 | I12: =I$5*MAX(I11,0) -> 1348.7311 | J12: =J$5*MAX(J11,0) -> 1836.569 | ... M12: =M$5*MAX(M11,0) -> 4500
A13: (-) Reinvestment (chg. revenue / sales-to-capital) | C13: =MAX(C9-(Inputs!$B$6),0)/Inputs!$B$10 -> 269.05134 | D13: =MAX(D9-C9,0)/Inputs!$B$10 -> 331.05824 | E13: =MAX(E9-D9,0)/Inputs!$B$10 -> 407.35555 | F13: =MAX(F9-E9,0)/Inputs!$B$10 -> 501.23672 | G13: =MAX(G9-F9,0)/Inputs!$B$10 -> 616.7542 | H13: =MAX(H9-G9,0)/Inputs!$B$10 -> 758.89441 | I13: =MAX(I9-H9,0)/Inputs!$B$10 -> 933.79296 | J13: =MAX(J9-I9,0)/Inputs!$B$10 -> 1148.9995 | K13: =MAX(K9-J9,0)/Inputs!$B$10 -> 1413.8036 | ... M13: =MAX(M9-L9,0)/Inputs!$B$10 -> 2140.5607
A14: (=) Free cash flow (FCFF) | C14: =C11-C12-C13 -> 1128.6228 | D14: =D11-D12-D13 -> 1435.8956 | E14: =E11-E12-E13 -> 1822.0228 | F14: =F11-F12-F13 -> 2306.378 | G14: =G11-G12-G13 -> 2912.9256 | H14: =H11-H12-H13 -> 3671.2739 | I14: =I11-I12-I13 -> 4617.9608 | J14: =J11-J12-J13 -> 5798.0225 | ... M14: =M11-M12-M13 -> 11359.439
A15: (x) Discount factor | C15: =C$6 -> 0.92378753 | D15: =D$6 -> 0.8533834 | E15: =E$6 -> 0.78834494 | F15: =F$6 -> 0.72826322 | G15: =G$6 -> 0.67276048 | H15: =H$6 -> 0.62148775 | I15: =I$6 -> 0.57412263 | J15: =J$6 -> 0.53036732 | ... M15: =M$6 -> 0.4181124
A16: (=) PV of FCFF | C16: =C14*C15 -> 1042.6077 | D16: =D14*D15 -> 1225.3695 | E16: =E14*E15 -> 1436.3825 | F16: =F14*F15 -> 1679.6502 | G16: =G14*G15 -> 1959.7012 | H16: =H14*H15 -> 2281.6517 | I16: =I14*I15 -> 2651.2758 | J16: =J14*J15 -> 3075.0817 | ... M16: =M14*M15 -> 4749.5224
A18: Terminal value (2037 onward)
A19: EBIT 2037 after tax = EBIT 2036 x (1+g) x (1-marginal tax) | B19: =M11*(1+Inputs!$B$30)*(1-Inputs!$B$33) -> 14115.6
A20: (-) Perpetuity reinvestment: g / ROIC of the above | B20: =B19*Inputs!$B$30/Inputs!$B$31 -> 4291.1424
A21: (=) FCFF 2037 | B21: =B19-B20 -> 9824.4576
A22: Terminal value at 2036 = FCFF 2037 / (WACC - g) | B22: =B21/(Inputs!$B$29-Inputs!$B$30) -> 266245.46
A23: PV of terminal value = TV x discount factor 2036 | B23: =B22*M15 -> 111320.53
A24: Segment operating value = sum of PV(FCFF) + PV(TV) | B24: =SUM(C16:M16)+B23 -> 139097.63 | C24: Python check: | D24: 139098
A26: Starlink | D26: growth to 2036 target g: | F26: =(Inputs!$B$14/Inputs!$B$13)^(1/11)-1 -> 0.23873745
A27: Revenue | C27: =(Inputs!$B$13)*(1+DCF!$F$26) -> 14105.503 | D27: =C27*(1+DCF!$F$26) -> 17473.015 | E27: =D27*(1+DCF!$F$26) -> 21644.478 | F27: =E27*(1+DCF!$F$26) -> 26811.826 | G27: =F27*(1+DCF!$F$26) -> 33212.812 | H27: =G27*(1+DCF!$F$26) -> 41141.954 | I27: =H27*(1+DCF!$F$26) -> 50964.079 | J27: =I27*(1+DCF!$F$26) -> 63131.113 | K27: =J27*(1+DCF!$F$26) -> 78202.874 | ... M27: =L27*(1+DCF!$F$26) -> 120000
A28: (x) Operating margin | C28: =Inputs!$B$15+(Inputs!$B$16-Inputs!$B$15)*C$4/11 -> 0.37272727 | D28: =Inputs!$B$15+(Inputs!$B$16-Inputs!$B$15)*D$4/11 -> 0.39545455 | E28: =Inputs!$B$15+(Inputs!$B$16-Inputs!$B$15)*E$4/11 -> 0.41818182 | F28: =Inputs!$B$15+(Inputs!$B$16-Inputs!$B$15)*F$4/11 -> 0.44090909 | G28: =Inputs!$B$15+(Inputs!$B$16-Inputs!$B$15)*G$4/11 -> 0.46363636 | H28: =Inputs!$B$15+(Inputs!$B$16-Inputs!$B$15)*H$4/11 -> 0.48636364 | I28: =Inputs!$B$15+(Inputs!$B$16-Inputs!$B$15)*I$4/11 -> 0.50909091 | J28: =Inputs!$B$15+(Inputs!$B$16-Inputs!$B$15)*J$4/11 -> 0.53181818 | ... M28: =Inputs!$B$15+(Inputs!$B$16-Inputs!$B$15)*M$4/11 -> 0.6
A29: (=) EBIT | C29: =C27*C28 -> 5257.5058 | D29: =D27*D28 -> 6909.7832 | E29: =E27*E28 -> 9051.3272 | F29: =F27*F28 -> 11821.578 | G29: =G27*G28 -> 15398.667 | H29: =H27*H28 -> 20009.95 | I29: =I27*I28 -> 25945.349 | J29: =J27*J28 -> 33574.274 | ... M29: =M27*M28 -> 72000
A30: (-) Taxes (on positive EBIT) | C30: =C$5*MAX(C29,0) -> 597.44384 | D30: =D$5*MAX(D29,0) -> 879.42696 | E30: =E$5*MAX(E29,0) -> 1275.4143 | F30: =F$5*MAX(F29,0) -> 1826.9711 | G30: =G$5*MAX(G29,0) -> 2589.7759 | H30: =H$5*MAX(H29,0) -> 3638.1728 | I30: =I$5*MAX(I29,0) -> 5071.1365 | J30: =J$5*MAX(J29,0) -> 7020.0755 | ... M30: =M$5*MAX(M29,0) -> 18000
A31: (-) Reinvestment (chg. revenue / sales-to-capital) | C31: =MAX(C27-(Inputs!$B$13),0)/Inputs!$B$17 -> 679.62582 | D31: =MAX(D27-C27,0)/Inputs!$B$17 -> 841.87796 | E31: =MAX(E27-D27,0)/Inputs!$B$17 -> 1042.8657 | F31: =MAX(F27-E27,0)/Inputs!$B$17 -> 1291.8369 | G31: =MAX(G27-F27,0)/Inputs!$B$17 -> 1600.2467 | H31: =MAX(H27-G27,0)/Inputs!$B$17 -> 1982.2855 | I31: =MAX(I27-H27,0)/Inputs!$B$17 -> 2455.5313 | J31: =MAX(J27-I27,0)/Inputs!$B$17 -> 3041.7585 | K31: =MAX(K27-J27,0)/Inputs!$B$17 -> 3767.9402 | ... M31: =MAX(M27-L27,0)/Inputs!$B$17 -> 5781.7929
A32: (=) Free cash flow (FCFF) | C32: =C29-C30-C31 -> 3980.4361 | D32: =D29-D30-D31 -> 5188.4783 | E32: =E29-E30-E31 -> 6733.0472 | F32: =F29-F30-F31 -> 8702.7697 | G32: =G29-G30-G31 -> 11208.645 | H32: =H29-H30-H31 -> 14389.492 | I32: =I29-I30-I31 -> 18418.682 | J32: =J29-J30-J31 -> 23512.44 | ... M32: =M29-M30-M31 -> 48218.207
A33: (x) Discount factor | C33: =C$6 -> 0.92378753 | D33: =D$6 -> 0.8533834 | E33: =E$6 -> 0.78834494 | F33: =F$6 -> 0.72826322 | G33: =G$6 -> 0.67276048 | H33: =H$6 -> 0.62148775 | I33: =I$6 -> 0.57412263 | J33: =J$6 -> 0.53036732 | ... M33: =M$6 -> 0.4181124
A34: (=) PV of FCFF | C34: =C32*C33 -> 3677.0772 | D34: =D32*D33 -> 4427.7613 | E34: =E32*E33 -> 5307.9637 | F34: =F32*F33 -> 6337.9071 | G34: =G32*G33 -> 7540.7334 | H34: =H32*H33 -> 8942.893 | I34: =I32*I33 -> 10574.582 | J34: =J32*J33 -> 12470.23 | ... M34: =M32*M33 -> 20160.63
A36: Terminal value (2037 onward)
A37: EBIT 2037 after tax = EBIT 2036 x (1+g) x (1-marginal tax) | B37: =M29*(1+Inputs!$B$30)*(1-Inputs!$B$33) -> 56462.4
A38: (-) Perpetuity reinvestment: g / ROIC of the above | B38: =B37*Inputs!$B$30/Inputs!$B$31 -> 17164.57
A39: (=) FCFF 2037 | B39: =B37-B38 -> 39297.83
A40: Terminal value at 2036 = FCFF 2037 / (WACC - g) | B40: =B39/(Inputs!$B$29-Inputs!$B$30) -> 1064981.9
A41: PV of terminal value = TV x discount factor 2036 | B41: =B40*M33 -> 445282.12
A42: Segment operating value = sum of PV(FCFF) + PV(TV) | B42: =SUM(C34:M34)+B41 -> 556606.57 | C42: Python check: | D42: 556607
A44: xAI | D44: growth to 2036 target g: | F44: =(Inputs!$B$21/Inputs!$B$20)^(1/11)-1 -> 0.42705096
A45: Revenue | C45: =(Inputs!$B$20)*(1+DCF!$F$44) -> 4567.9901 | D45: =C45*(1+DCF!$F$44) -> 6518.7547 | E45: =D45*(1+DCF!$F$44) -> 9302.5952 | F45: =E45*(1+DCF!$F$44) -> 13275.277 | G45: =F45*(1+DCF!$F$44) -> 18944.497 | H45: =G45*(1+DCF!$F$44) -> 27034.763 | I45: =H45*(1+DCF!$F$44) -> 38579.985 | J45: =I45*(1+DCF!$F$44) -> 55055.604 | K45: =J45*(1+DCF!$F$44) -> 78567.153 | ... M45: =L45*(1+DCF!$F$44) -> 160000
A46: (x) Operating margin | C46: =Inputs!$B$22+(Inputs!$B$23-Inputs!$B$22)*C$4/11 -> -0.25 | D46: =Inputs!$B$22+(Inputs!$B$23-Inputs!$B$22)*D$4/11 -> -0.2 | E46: =Inputs!$B$22+(Inputs!$B$23-Inputs!$B$22)*E$4/11 -> -0.15 | F46: =Inputs!$B$22+(Inputs!$B$23-Inputs!$B$22)*F$4/11 -> -0.1 | G46: =Inputs!$B$22+(Inputs!$B$23-Inputs!$B$22)*G$4/11 -> -0.05 | H46: =Inputs!$B$22+(Inputs!$B$23-Inputs!$B$22)*H$4/11 -> 0 | I46: =Inputs!$B$22+(Inputs!$B$23-Inputs!$B$22)*I$4/11 -> 0.05 | J46: =Inputs!$B$22+(Inputs!$B$23-Inputs!$B$22)*J$4/11 -> 0.1 | ... M46: =Inputs!$B$22+(Inputs!$B$23-Inputs!$B$22)*M$4/11 -> 0.25
A47: (=) EBIT | C47: =C45*C46 -> -1141.9975 | D47: =D45*D46 -> -1303.7509 | E47: =E45*E46 -> -1395.3893 | F47: =F45*F46 -> -1327.5277 | G47: =G45*G46 -> -947.22487 | H47: =H45*H46 -> 0 | I47: =I45*I46 -> 1928.9992 | J47: =J45*J46 -> 5505.5604 | ... M47: =M45*M46 -> 40000
A48: (-) Taxes (on positive EBIT) | C48: =C$5*MAX(C47,0) -> 0 | D48: =D$5*MAX(D47,0) -> 0 | E48: =E$5*MAX(E47,0) -> 0 | F48: =F$5*MAX(F47,0) -> 0 | G48: =G$5*MAX(G47,0) -> 0 | H48: =H$5*MAX(H47,0) -> 0 | I48: =I$5*MAX(I47,0) -> 377.03167 | J48: =J$5*MAX(J47,0) -> 1151.1626 | ... M48: =M$5*MAX(M47,0) -> 10000
A49: (-) Reinvestment (chg. revenue / sales-to-capital) | C49: =MAX(C45-(Inputs!$B$20),0)/Inputs!$B$24 -> 683.49506 | D49: =MAX(D45-C45,0)/Inputs!$B$24 -> 975.38229 | E49: =MAX(E45-D45,0)/Inputs!$B$24 -> 1391.9202 | F49: =MAX(F45-E45,0)/Inputs!$B$24 -> 1986.3411 | G49: =MAX(G45-F45,0)/Inputs!$B$24 -> 2834.61 | H49: =MAX(H45-G45,0)/Inputs!$B$24 -> 4045.1329 | I49: =MAX(I45-H45,0)/Inputs!$B$24 -> 5772.6108 | J49: =MAX(J45-I45,0)/Inputs!$B$24 -> 8237.8098 | K49: =MAX(K45-J45,0)/Inputs!$B$24 -> 11755.774 | ... M49: =MAX(M45-L45,0)/Inputs!$B$24 -> 23940.334
A50: (=) Free cash flow (FCFF) | C50: =C47-C48-C49 -> -1825.4926 | D50: =D47-D48-D49 -> -2279.1332 | E50: =E47-E48-E49 -> -2787.3095 | F50: =F47-F48-F49 -> -3313.8688 | G50: =G47-G48-G49 -> -3781.8349 | H50: =H47-H48-H49 -> -4045.1329 | I50: =I47-I48-I49 -> -4220.6432 | J50: =J47-J48-J49 -> -3883.412 | ... M50: =M47-M48-M49 -> 6059.6658
A51: (x) Discount factor | C51: =C$6 -> 0.92378753 | D51: =D$6 -> 0.8533834 | E51: =E$6 -> 0.78834494 | F51: =F$6 -> 0.72826322 | G51: =G$6 -> 0.67276048 | H51: =H$6 -> 0.62148775 | I51: =I$6 -> 0.57412263 | J51: =J$6 -> 0.53036732 | ... M51: =M$6 -> 0.4181124
A52: (=) PV of FCFF | C52: =C50*C51 -> -1686.3673 | D52: =D50*D51 -> -1944.9745 | E52: =E50*E51 -> -2197.3614 | F52: =F50*F51 -> -2413.3688 | G52: =G50*G51 -> -2544.2691 | H52: =H50*H51 -> -2514.0005 | I52: =I50*I51 -> -2423.1668 | J52: =J50*J51 -> -2059.6348 | ... M52: =M50*M51 -> 2533.6214
A54: Terminal value (2037 onward)
A55: EBIT 2037 after tax = EBIT 2036 x (1+g) x (1-marginal tax) | B55: =M47*(1+Inputs!$B$30)*(1-Inputs!$B$33) -> 31368
A56: (-) Perpetuity reinvestment: g / ROIC of the above | B56: =B55*Inputs!$B$30/Inputs!$B$31 -> 9535.872
A57: (=) FCFF 2037 | B57: =B55-B56 -> 21832.128
A58: Terminal value at 2036 = FCFF 2037 / (WACC - g) | B58: =B57/(Inputs!$B$29-Inputs!$B$30) -> 591656.59
A59: PV of terminal value = TV x discount factor 2036 | B59: =B58*M51 -> 247378.95
A60: Segment operating value = sum of PV(FCFF) + PV(TV) | B60: =SUM(C52:M52)+B59 -> 231015.07 | C60: Python check: | D60: 231015
A62: DTC underlying | D62: growth to 2036 target g: | F62: =(Inputs!$B$43/Inputs!$B$42)^(1/11)-1 -> 0.36233449
A63: Revenue | C63: =(Inputs!$B$42)*(1+DCF!$F$62) -> 681.16724 | D63: =C63*(1+DCF!$F$62) -> 927.97763 | E63: =D63*(1+DCF!$F$62) -> 1264.2159 | F63: =E63*(1+DCF!$F$62) -> 1722.2849 | G63: =F63*(1+DCF!$F$62) -> 2346.3282 | H63: =G63*(1+DCF!$F$62) -> 3196.4838 | I63: =H63*(1+DCF!$F$62) -> 4354.6801 | J63: =I63*(1+DCF!$F$62) -> 5932.5309 | K63: =J63*(1+DCF!$F$62) -> 8082.0914 | ... M63: =L63*(1+DCF!$F$62) -> 15000
A64: (x) Operating margin | C64: =Inputs!$B$44+(Inputs!$B$45-Inputs!$B$44)*C$4/11 -> -0.13181818 | D64: =Inputs!$B$44+(Inputs!$B$45-Inputs!$B$44)*D$4/11 -> -0.063636364 | E64: =Inputs!$B$44+(Inputs!$B$45-Inputs!$B$44)*E$4/11 -> 0.0045454545 | F64: =Inputs!$B$44+(Inputs!$B$45-Inputs!$B$44)*F$4/11 -> 0.072727273 | G64: =Inputs!$B$44+(Inputs!$B$45-Inputs!$B$44)*G$4/11 -> 0.14090909 | H64: =Inputs!$B$44+(Inputs!$B$45-Inputs!$B$44)*H$4/11 -> 0.20909091 | I64: =Inputs!$B$44+(Inputs!$B$45-Inputs!$B$44)*I$4/11 -> 0.27727273 | J64: =Inputs!$B$44+(Inputs!$B$45-Inputs!$B$44)*J$4/11 -> 0.34545455 | ... M64: =Inputs!$B$44+(Inputs!$B$45-Inputs!$B$44)*M$4/11 -> 0.55
A65: (=) EBIT | C65: =C63*C64 -> -89.790227 | D65: =D63*D64 -> -59.053122 | E65: =E63*E64 -> 5.746436 | F65: =F63*F64 -> 125.25709 | G65: =G63*G64 -> 330.61897 | H65: =H63*H64 -> 668.3557 | I65: =I63*I64 -> 1207.434 | J65: =J63*J64 -> 2049.4198 | ... M65: =M63*M64 -> 8250
A66: (-) Taxes (on positive EBIT) | C66: =C$5*MAX(C65,0) -> 0 | D66: =D$5*MAX(D65,0) -> 0 | E66: =E$5*MAX(E65,0) -> 0.80972507 | F66: =F$5*MAX(F65,0) -> 19.357913 | G66: =G$5*MAX(G65,0) -> 55.6041 | H66: =H$5*MAX(H65,0) -> 121.51922 | I66: =I$5*MAX(I65,0) -> 235.99847 | J66: =J$5*MAX(J65,0) -> 428.51504 | ... M66: =M$5*MAX(M65,0) -> 2062.5
A67: (-) Reinvestment (chg. revenue / sales-to-capital) | C67: =MAX(C63-(Inputs!$B$42),0)/Inputs!$B$46 -> 45.291811 | D67: =MAX(D63-C63,0)/Inputs!$B$46 -> 61.702596 | E67: =MAX(E63-D63,0)/Inputs!$B$46 -> 84.059574 | F67: =MAX(F63-E63,0)/Inputs!$B$46 -> 114.51726 | G67: =MAX(G63-F63,0)/Inputs!$B$46 -> 156.01081 | H67: =MAX(H63-G63,0)/Inputs!$B$46 -> 212.5389 | I67: =MAX(I63-H63,0)/Inputs!$B$46 -> 289.54908 | J67: =MAX(J63-I63,0)/Inputs!$B$46 -> 394.46269 | K67: =MAX(K63-J63,0)/Inputs!$B$46 -> 537.39013 | ... M67: =MAX(M63-L63,0)/Inputs!$B$46 -> 997.37204
A68: (=) Free cash flow (FCFF) | C68: =C65-C66-C67 -> -135.08204 | D68: =D65-D66-D67 -> -120.75572 | E68: =E65-E66-E67 -> -79.122863 | F68: =F65-F66-F67 -> -8.6180829 | G68: =G65-G66-G67 -> 119.00406 | H68: =H65-H66-H67 -> 334.29758 | I68: =I65-I66-I67 -> 681.88648 | J68: =J65-J66-J67 -> 1226.442 | ... M68: =M65-M66-M67 -> 5190.128
A69: (x) Discount factor | C69: =C$6 -> 0.92378753 | D69: =D$6 -> 0.8533834 | E69: =E$6 -> 0.78834494 | F69: =F$6 -> 0.72826322 | G69: =G$6 -> 0.67276048 | H69: =H$6 -> 0.62148775 | I69: =I$6 -> 0.57412263 | J69: =J$6 -> 0.53036732 | ... M69: =M$6 -> 0.4181124
A70: (=) PV of FCFF | C70: =C68*C69 -> -124.7871 | D70: =D68*D69 -> -103.05092 | E70: =E68*E69 -> -62.376109 | F70: =F68*F69 -> -6.2762328 | G70: =G68*G69 -> 80.061231 | H70: =H68*H69 -> 207.76185 | I70: =I68*I69 -> 391.48646 | J70: =J68*J69 -> 650.46478 | ... M70: =M68*M69 -> 2170.0568
A72: Terminal value (2037 onward)
A73: EBIT 2037 after tax = EBIT 2036 x (1+g) x (1-marginal tax) | B73: =M65*(1+Inputs!$B$30)*(1-Inputs!$B$33) -> 6469.65
A74: (-) Perpetuity reinvestment: g / ROIC of the above | B74: =B73*Inputs!$B$30/Inputs!$B$31 -> 1966.7736
A75: (=) FCFF 2037 | B75: =B73-B74 -> 4502.8764
A76: Terminal value at 2036 = FCFF 2037 / (WACC - g) | B76: =B75/(Inputs!$B$29-Inputs!$B$30) -> 122029.17
A77: PV of terminal value = TV x discount factor 2036 | B77: =B76*M69 -> 51021.909
A78: Segment operating value = sum of PV(FCFF) + PV(TV) | B78: =SUM(C70:M70)+B77 -> 56737.281 | C78: Python check: | D78: 56737
A80: Equity bridge
A81: Launch operating value | B81: =DCF!$B$24 -> 139097.63
A82: Starlink operating value | B82: =DCF!$B$42 -> 556606.57
A83: xAI operating value | B83: =DCF!$B$60 -> 231015.07
A84: (+) Cash | B84: =Inputs!$B$34 -> 24747
A85: (+) IPO proceeds | B85: =Inputs!$B$36 -> 75000
A86: (-) Debt | B86: =-Inputs!$B$35 -> -22896
A87: Equity value ($M) | B87: =SUM(B81:B86) -> 1003570.3 | C87: Python check: | D87: 1003570
A88: Per share ($) | B88: =B87/Inputs!$B$37 -> 76.661085

Sheet Options
A1: Real options — paper Section 5, Appendix A.2 (values $M)
A2: Expansion claims by their standalone closed form p x [M N(d1) - I N(d2)] x (1+r)^-tau, validated against the paper's simulation in Appendix A.2. Mars as the exact probability tree. The abandonment option is imported from the Python least-squares Monte Carlo.
A4: Starlink direct-to-cell (exercise-at-gate)
A5: Underlying M | B5: =DCF!$B$78 -> 56737.281
A6: d1 = [ln(M/I) + sigma^2/2] / sigma | B6: =(LN(B5/Inputs!$B$47)+0.5*Inputs!$B$49^2)/Inputs!$B$49 -> 3.0995907
A7: d2 = d1 - sigma | B7: =B6-Inputs!$B$49 -> 2.5495907
A8: Option value | B8: =1*(B5*_xlfn.NORM.S.DIST(B6,TRUE)-Inputs!$B$47*_xlfn.NORM.S.DIST(B7,TRUE))/(1+Inputs!$B$29)^Inputs!$B$48 -> 32587.606 | C8: 32588 | D8: Python checks: closed form 32,588; the paper's simulated value 32,614 (same paths as the firm model; gap = Monte-Carlo error)
A10: Starship heavy lift (gated on the technical trigger)
A11: Underlying M | B11: =Inputs!$B$50 -> 110000
A12: d1 = [ln(M/I) + sigma^2/2] / sigma | B12: =(LN(B11/Inputs!$B$51)+0.5*Inputs!$B$53^2)/Inputs!$B$53 -> 2.848566
A13: d2 = d1 - sigma | B13: =B12-Inputs!$B$53 -> 2.348566
A14: Option value | B14: =Inputs!$B$54*(B11*_xlfn.NORM.S.DIST(B12,TRUE)-Inputs!$B$51*_xlfn.NORM.S.DIST(B13,TRUE))/(1+Inputs!$B$29)^Inputs!$B$52 -> 32309.112 | C14: 32309 | D14: Python checks: closed form 32,309; the paper's simulated value 32,304 (same paths as the firm model; gap = Monte-Carlo error)
A16: Mars sovereign-program claim (exact probability tree)
A17: State (highest realized) | B17: Value ($M) | C17: Probability
A18: Settlement | B18: =MAX(Inputs!$B$64*Inputs!$B$57*(1-Inputs!$B$33)/Inputs!$B$29-Inputs!$B$65,0) -> 12272.727 | C18: =Inputs!$B$54*Inputs!$B$63*Inputs!$B$66 -> 0.0375
A19: Crewed, not settlement | B19: =MAX(Inputs!$B$61*Inputs!$B$57*(1-Inputs!$B$33)/Inputs!$B$29-Inputs!$B$62,0) -> 1818.1818 | C19: =Inputs!$B$54*Inputs!$B$63*(1-Inputs!$B$66) -> 0.1125
A20: Robotic only | B20: =MAX(Inputs!$B$59*Inputs!$B$57*(1-Inputs!$B$33)/Inputs!$B$29-0,0) -> 1363.6364 | C20: =Inputs!$B$60*(1-Inputs!$B$54*Inputs!$B$63) -> 0.765
A21: Mars claim, discounted from the start year | B21: =SUMPRODUCT(B18:B20,C18:C20)/(1+Inputs!$B$29)^Inputs!$B$58 -> 773.03162 | C21: 772 | D21: Python check (simulated tree). Value per state = max(revenue x margin x (1-tax) / WACC - co-investment, 0), a flat perpetuity.
A23: xAI abandonment option (imported)
A24: Value at zero salvage | B24: =Inputs!$B$69 -> 1492 | D24: From the Python least-squares Monte Carlo (paper Sec. 5.2); optimal stopping has no formula representation — see venture_option.py
A26: Totals
A27: Expansion claims + Mars | B27: =Options!$B$8+Options!$B$14+Options!$B$21 -> 65669.75
A28: All options incl. abandonment | B28: =B27+Inputs!$B$69 -> 67161.75
A29: Equity + all options ($M) | B29: =DCF!$B$87+B28 -> 1070732
A30: Per share ($) | B30: =B29/Inputs!$B$37 -> 81.791461

Sheet MonteCarlo
A1: Monte Carlo — the distribution of equity value (1,000 trials; paper Sec. 4.3)
A2: Each row is one trial of the correlated three-segment model of Appendix A.1: a common demand factor per year (correlation rho), declining revenue volatility, the same cash-flow construction as the DCF tab. Press F9 to redraw. Excel's RAND() is not seeded, so figures move by Monte-Carlo error around the Python values; the paper's numbers use 200,000 fixed-seed paths.
C3: 2026 | D3: 2027 | E3: 2028 | F3: 2029 | G3: 2030 | H3: 2031 | I3: 2032 | J3: 2033 | K3: 2034 | L3: 2035 | M3: 2036
A4: Year index t | C4: 1 | D4: 2 | E4: 3 | F4: 4 | G4: 5 | H4: 6 | I4: 7 | J4: 8 | K4: 9 | L4: 10 | M4: 11 | P4: Summary of the simulated distribution | U4: Histogram ($T bins, count of trials)
A5: Launch: sigma_t | C5: =Inputs!$B$11*EXP(-Inputs!$B$39*C$4)+Inputs!$B$12*(1-EXP(-Inputs!$B$39*C$4)) -> 0.16187308 | D5: =Inputs!$B$11*EXP(-Inputs!$B$39*D$4)+Inputs!$B$12*(1-EXP(-Inputs!$B$39*D$4)) -> 0.147032 | E5: =Inputs!$B$11*EXP(-Inputs!$B$39*E$4)+Inputs!$B$12*(1-EXP(-Inputs!$B$39*E$4)) -> 0.13488116 | F5: =Inputs!$B$11*EXP(-Inputs!$B$39*F$4)+Inputs!$B$12*(1-EXP(-Inputs!$B$39*F$4)) -> 0.1249329 | G5: =Inputs!$B$11*EXP(-Inputs!$B$39*G$4)+Inputs!$B$12*(1-EXP(-Inputs!$B$39*G$4)) -> 0.11678794 | H5: =Inputs!$B$11*EXP(-Inputs!$B$39*H$4)+Inputs!$B$12*(1-EXP(-Inputs!$B$39*H$4)) -> 0.11011942 | I5: =Inputs!$B$11*EXP(-Inputs!$B$39*I$4)+Inputs!$B$12*(1-EXP(-Inputs!$B$39*I$4)) -> 0.1046597 | J5: =Inputs!$B$11*EXP(-Inputs!$B$39*J$4)+Inputs!$B$12*(1-EXP(-Inputs!$B$39*J$4)) -> 0.10018965 | ... M5: =Inputs!$B$11*EXP(-Inputs!$B$39*M$4)+Inputs!$B$12*(1-EXP(-Inputs!$B$39*M$4)) -> 0.091080316 | P5: Mean equity ($M) | R5: =AVERAGE(DM14:DM1013) -> 997221.72 | S5: Python (200k paths): 1,002,249 | U5: 0.2 | V5: 0.4 | W5: 0.6 | X5: 0.8 | Y5: 1 | Z5: 1.2 | AA5: 1.4 | AB5: 1.6 | AC5: 1.8 | AD5: 2 | AE5: 2.2 | AF5: 2.4 | AG5: 2.6 | AH5: 2.8 | AI5: 3
A6: Starlink: sigma_t | C6: =Inputs!$B$18*EXP(-Inputs!$B$39*C$4)+Inputs!$B$19*(1-EXP(-Inputs!$B$39*C$4)) -> 0.19824769 | D6: =Inputs!$B$18*EXP(-Inputs!$B$39*D$4)+Inputs!$B$19*(1-EXP(-Inputs!$B$39*D$4)) -> 0.18043841 | E6: =Inputs!$B$18*EXP(-Inputs!$B$39*E$4)+Inputs!$B$19*(1-EXP(-Inputs!$B$39*E$4)) -> 0.1658574 | F6: =Inputs!$B$18*EXP(-Inputs!$B$39*F$4)+Inputs!$B$19*(1-EXP(-Inputs!$B$39*F$4)) -> 0.15391948 | G6: =Inputs!$B$18*EXP(-Inputs!$B$39*G$4)+Inputs!$B$19*(1-EXP(-Inputs!$B$39*G$4)) -> 0.14414553 | H6: =Inputs!$B$18*EXP(-Inputs!$B$39*H$4)+Inputs!$B$19*(1-EXP(-Inputs!$B$39*H$4)) -> 0.13614331 | I6: =Inputs!$B$18*EXP(-Inputs!$B$39*I$4)+Inputs!$B$19*(1-EXP(-Inputs!$B$39*I$4)) -> 0.12959164 | J6: =Inputs!$B$18*EXP(-Inputs!$B$39*J$4)+Inputs!$B$19*(1-EXP(-Inputs!$B$39*J$4)) -> 0.12422758 | ... M6: =Inputs!$B$18*EXP(-Inputs!$B$39*M$4)+Inputs!$B$19*(1-EXP(-Inputs!$B$39*M$4)) -> 0.11329638 | P6: Std deviation | R6: =_xlfn.STDEV.S(DM14:DM1013) -> 423862.7 | U6: =COUNTIFS(DM14:DM1013,">=200000",DM14:DM1013,"<400000") -> 8 | V6: =COUNTIFS(DM14:DM1013,">=400000",DM14:DM1013,"<600000") -> 107 | W6: =COUNTIFS(DM14:DM1013,">=600000",DM14:DM1013,"<800000") -> 261 | X6: =COUNTIFS(DM14:DM1013,">=800000",DM14:DM1013,"<1000000") -> 224 | Y6: =COUNTIFS(DM14:DM1013,">=1000000",DM14:DM1013,"<1200000") -> 163 | Z6: =COUNTIFS(DM14:DM1013,">=1200000",DM14:DM1013,"<1400000") -> 102 | AA6: =COUNTIFS(DM14:DM1013,">=1400000",DM14:DM1013,"<1600000") -> 56 | AB6: =COUNTIFS(DM14:DM1013,">=1600000",DM14:DM1013,"<1800000") -> 32 | AC6: =COUNTIFS(DM14:DM1013,">=1800000",DM14:DM1013,"<2000000") -> 19 | AD6: =COUNTIFS(DM14:DM1013,">=2000000",DM14:DM1013,"<2200000") -> 10 | AE6: =COUNTIFS(DM14:DM1013,">=2200000",DM14:DM1013,"<2400000") -> 5 | AF6: =COUNTIFS(DM14:DM1013,">=2400000",DM14:DM1013,"<2600000") -> 3 | AG6: =COUNTIFS(DM14:DM1013,">=2600000",DM14:DM1013,"<2800000") -> 4 | AH6: =COUNTIFS(DM14:DM1013,">=2800000",DM14:DM1013,"<3000000") -> 3 | AI6: =COUNTIFS(DM14:DM1013,">=3000000",DM14:DM1013,"<3200000") -> 1
A7: xAI: sigma_t | C7: =Inputs!$B$25*EXP(-Inputs!$B$39*C$4)+Inputs!$B$26*(1-EXP(-Inputs!$B$39*C$4)) -> 0.35468269 | D7: =Inputs!$B$25*EXP(-Inputs!$B$39*D$4)+Inputs!$B$26*(1-EXP(-Inputs!$B$39*D$4)) -> 0.31758001 | E7: =Inputs!$B$25*EXP(-Inputs!$B$39*E$4)+Inputs!$B$26*(1-EXP(-Inputs!$B$39*E$4)) -> 0.28720291 | F7: =Inputs!$B$25*EXP(-Inputs!$B$39*F$4)+Inputs!$B$26*(1-EXP(-Inputs!$B$39*F$4)) -> 0.26233224 | G7: =Inputs!$B$25*EXP(-Inputs!$B$39*G$4)+Inputs!$B$26*(1-EXP(-Inputs!$B$39*G$4)) -> 0.24196986 | H7: =Inputs!$B$25*EXP(-Inputs!$B$39*H$4)+Inputs!$B$26*(1-EXP(-Inputs!$B$39*H$4)) -> 0.22529855 | I7: =Inputs!$B$25*EXP(-Inputs!$B$39*I$4)+Inputs!$B$26*(1-EXP(-Inputs!$B$39*I$4)) -> 0.21164924 | J7: =Inputs!$B$25*EXP(-Inputs!$B$39*J$4)+Inputs!$B$26*(1-EXP(-Inputs!$B$39*J$4)) -> 0.20047413 | ... M7: =Inputs!$B$25*EXP(-Inputs!$B$39*M$4)+Inputs!$B$26*(1-EXP(-Inputs!$B$39*M$4)) -> 0.17770079 | P7: MC std error of mean | R7: =_xlfn.STDEV.S(DM14:DM1013)/SQRT(1000) -> 13403.716
A8: Launch: drift ln(1+g) | B8: =LN(1+DCF!$F$8) -> 0.20739209 | P8: 5th percentile | R8: =_xlfn.PERCENTILE.INC(DM14:DM1013,0.05) -> 521926.18 | S8: Python: 514,826
A9: Starlink: drift ln(1+g) | B9: =LN(1+DCF!$F$26) -> 0.21409267 | P9: Median | R9: =_xlfn.PERCENTILE.INC(DM14:DM1013,0.5) -> 908876.59 | S9: Python: 915,244
A10: xAI: drift ln(1+g) | B10: =LN(1+DCF!$F$44) -> 0.35561005 | P10: 95th percentile | R10: =_xlfn.PERCENTILE.INC(DM14:DM1013,0.95) -> 1760783.6 | S10: Python: 1,777,523
P11: P(equity > $1.8T) | R11: =COUNTIF(DM14:DM1013,">1800000")/1000 -> 0.047 | S11: Python: 5%
A13: Trial | C13: f 2026 | D13: f 2027 | E13: f 2028 | F13: f 2029 | G13: f 2030 | H13: f 2031 | I13: f 2032 | J13: f 2033 | K13: f 2034 | L13: f 2035 | M13: f 2036 | N13: z La 26 | O13: z La 27 | P13: z La 28 | Q13: z La 29 | R13: z La 30 | S13: z La 31 | T13: z La 32 | U13: z La 33 | V13: z La 34 | W13: z La 35 | X13: z La 36 | Y13: z St 26 | Z13: z St 27 | AA13: z St 28 | AB13: z St 29 | AC13: z St 30 | AD13: z St 31 | AE13: z St 32 | AF13: z St 33 | AG13: z St 34 | AH13: z St 35 | AI13: z St 36 | AJ13: z xA 26 | AK13: z xA 27 | AL13: z xA 28 | AM13: z xA 29 | AN13: z xA 30 | AO13: z xA 31 | AP13: z xA 32 | AQ13: z xA 33 | AR13: z xA 34 | AS13: z xA 35 | AT13: z xA 36 | AU13: R La 26 | AV13: R La 27 | AW13: R La 28 | AX13: R La 29 | AY13: R La 30 | AZ13: R La 31 | BA13: R La 32 | BB13: R La 33 | BC13: R La 34 | BD13: R La 35 | BE13: R La 36 | BF13: R St 26 | BG13: R St 27 | BH13: R St 28 | BI13: R St 29 | BJ13: R St 30 | BK13: R St 31 | BL13: R St 32 | BM13: R St 33 | BN13: R St 34 | BO13: R St 35 | BP13: R St 36 | BQ13: R xA 26 | BR13: R xA 27 | BS13: R xA 28 | BT13: R xA 29 | BU13: R xA 30 | BV13: R xA 31 | BW13: R xA 32 | BX13: R xA 33 | BY13: R xA 34 | BZ13: R xA 35 | CA13: R xA 36 | CB13: PV La 26 | CC13: PV La 27 | CD13: PV La 28 | CE13: PV La 29 | CF13: PV La 30 | CG13: PV La 31 | CH13: PV La 32 | CI13: PV La 33 | CJ13: PV La 34 | CK13: PV La 35 | CL13: PV La 36 | CM13: PV St 26 | CN13: PV St 27 | CO13: PV St 28 | CP13: PV St 29 | CQ13: PV St 30 | CR13: PV St 31 | CS13: PV St 32 | CT13: PV St 33 | CU13: PV St 34 | CV13: PV St 35 | CW13: PV St 36 | CX13: PV xA 26 | CY13: PV xA 27 | CZ13: PV xA 28 | DA13: PV xA 29 | DB13: PV xA 30 | DC13: PV xA 31 | DD13: PV xA 32 | DE13: PV xA 33 | DF13: PV xA 34 | DG13: PV xA 35 | DH13: PV xA 36 | DI13: Launch value | DJ13: Starlink value | DK13: xAI value | DM13: Equity ($M)
A14: 1 | C14: =_xlfn.NORM.S.INV(RAND()) -> -0.30016433 | D14: =_xlfn.NORM.S.INV(RAND()) -> -1.6884345 | E14: =_xlfn.NORM.S.INV(RAND()) -> -0.68516792 | F14: =_xlfn.NORM.S.INV(RAND()) -> 1.6121494 | G14: =_xlfn.NORM.S.INV(RAND()) -> -0.76011499 | H14: =_xlfn.NORM.S.INV(RAND()) -> -0.51186066 | I14: =_xlfn.NORM.S.INV(RAND()) -> 0.70463139 | J14: =_xlfn.NORM.S.INV(RAND()) -> 0.10479499 | ... M14: =_xlfn.NORM.S.INV(RAND()) -> -1.6454338 | N14: =SQRT(Inputs!$B$38)*C14+SQRT(1-Inputs!$B$38)*_xlfn.NORM.S.INV(RAND()) -> -0.77212621 | O14: =SQRT(Inputs!$B$38)*D14+SQRT(1-Inputs!$B$38)*_xlfn.NORM.S.INV(RAND()) -> -0.56081031 | P14: =SQRT(Inputs!$B$38)*E14+SQRT(1-Inputs!$B$38)*_xlfn.NORM.S.INV(RAND()) -> 0.30254546 | Q14: =SQRT(Inputs!$B$38)*F14+SQRT(1-Inputs!$B$38)*_xlfn.NORM.S.INV(RAND()) -> 1.5800858 | R14: =SQRT(Inputs!$B$38)*G14+SQRT(1-Inputs!$B$38)*_xlfn.NORM.S.INV(RAND()) -> -0.25832461 | S14: =SQRT(Inputs!$B$38)*H14+SQRT(1-Inputs!$B$38)*_xlfn.NORM.S.INV(RAND()) -> -0.9464498 | T14: =SQRT(Inputs!$B$38)*I14+SQRT(1-Inputs!$B$38)*_xlfn.NORM.S.INV(RAND()) -> -0.014798184 | U14: =SQRT(Inputs!$B$38)*J14+SQRT(1-Inputs!$B$38)*_xlfn.NORM.S.INV(RAND()) -> 1.5267627 | ... X14: =SQRT(Inputs!$B$38)*M14+SQRT(1-Inputs!$B$38)*_xlfn.NORM.S.INV(RAND()) -> -1.1486193 | Y14: =SQRT(Inputs!$B$38)*C14+SQRT(1-Inputs!$B$38)*_xlfn.NORM.S.INV(RAND()) -> -0.26813794 | Z14: =SQRT(Inputs!$B$38)*D14+SQRT(1-Inputs!$B$38)*_xlfn.NORM.S.INV(RAND()) -> -0.37460193 | AA14: =SQRT(Inputs!$B$38)*E14+SQRT(1-Inputs!$B$38)*_xlfn.NORM.S.INV(RAND()) -> -0.84949988 | AB14: =SQRT(Inputs!$B$38)*F14+SQRT(1-Inputs!$B$38)*_xlfn.NORM.S.INV(RAND()) -> 0.053225127 | AC14: =SQRT(Inputs!$B$38)*G14+SQRT(1-Inputs!$B$38)*_xlfn.NORM.S.INV(RAND()) -> -1.4756267 | AD14: =SQRT(Inputs!$B$38)*H14+SQRT(1-Inputs!$B$38)*_xlfn.NORM.S.INV(RAND()) -> -1.1502349 | AE14: =SQRT(Inputs!$B$38)*I14+SQRT(1-Inputs!$B$38)*_xlfn.NORM.S.INV(RAND()) -> 0.9085652 | AF14: =SQRT(Inputs!$B$38)*J14+SQRT(1-Inputs!$B$38)*_xlfn.NORM.S.INV(RAND()) -> 0.56956074 | ... AI14: =SQRT(Inputs!$B$38)*M14+SQRT(1-Inputs!$B$38)*_xlfn.NORM.S.INV(RAND()) -> -1.3236524 | AJ14: =SQRT(Inputs!$B$38)*C14+SQRT(1-Inputs!$B$38)*_xlfn.NORM.S.INV(RAND()) -> 1.549427 | AK14: =SQRT(Inputs!$B$38)*D14+SQRT(1-Inputs!$B$38)*_xlfn.NORM.S.INV(RAND()) -> -1.8177563 | AL14: =SQRT(Inputs!$B$38)*E14+SQRT(1-Inputs!$B$38)*_xlfn.NORM.S.INV(RAND()) -> -0.38373319 | AM14: =SQRT(Inputs!$B$38)*F14+SQRT(1-Inputs!$B$38)*_xlfn.NORM.S.INV(RAND()) -> 0.75392933 | AN14: =SQRT(Inputs!$B$38)*G14+SQRT(1-Inputs!$B$38)*_xlfn.NORM.S.INV(RAND()) -> -0.28380304 | AO14: =SQRT(Inputs!$B$38)*H14+SQRT(1-Inputs!$B$38)*_xlfn.NORM.S.INV(RAND()) -> 0.64374081 | AP14: =SQRT(Inputs!$B$38)*I14+SQRT(1-Inputs!$B$38)*_xlfn.NORM.S.INV(RAND()) -> -0.16864156 | AQ14: =SQRT(Inputs!$B$38)*J14+SQRT(1-Inputs!$B$38)*_xlfn.NORM.S.INV(RAND()) -> -0.72434153 | ... AT14: =SQRT(Inputs!$B$38)*M14+SQRT(1-Inputs!$B$38)*_xlfn.NORM.S.INV(RAND()) -> -1.4851565 | AU14: =Inputs!$B$6*EXP($B$8-0.5*C$5^2+C$5*N14) -> 4379.2203 | AV14: =AU14*EXP($B$8-0.5*D$5^2+D$5*O14) -> 4908.638 | AW14: =AV14*EXP($B$8-0.5*E$5^2+E$5*P14) -> 6234.5089 | AX14: =AW14*EXP($B$8-0.5*F$5^2+F$5*Q14) -> 9272.8659 | AY14: =AX14*EXP($B$8-0.5*G$5^2+G$5*R14) -> 10995.605 | AZ14: =AY14*EXP($B$8-0.5*H$5^2+H$5*S14) -> 12116.911 | BA14: =AZ14*EXP($B$8-0.5*I$5^2+I$5*T14) -> 14805.054 | BB14: =BA14*EXP($B$8-0.5*J$5^2+J$5*U14) -> 21121.839 | BC14: =BB14*EXP($B$8-0.5*K$5^2+K$5*V14) -> 24051.511 | ... BE14: =BD14*EXP($B$8-0.5*M$5^2+M$5*X14) -> 32696.475 | BF14: =Inputs!$B$13*EXP($B$9-0.5*C$6^2+C$6*Y14) -> 13114.995 | BG14: =BF14*EXP($B$9-0.5*D$6^2+D$6*Z14) -> 14939.031 | BH14: =BG14*EXP($B$9-0.5*E$6^2+E$6*AA14) -> 15853.968 | BI14: =BH14*EXP($B$9-0.5*F$6^2+F$6*AB14) -> 19567.289 | BJ14: =BI14*EXP($B$9-0.5*G$6^2+G$6*AC14) -> 19391.949 | BK14: =BJ14*EXP($B$9-0.5*H$6^2+H$6*AD14) -> 20350.111 | BL14: =BK14*EXP($B$9-0.5*I$6^2+I$6*AE14) -> 28121.221 | BM14: =BL14*EXP($B$9-0.5*J$6^2+J$6*AF14) -> 37101.45 | BN14: =BM14*EXP($B$9-0.5*K$6^2+K$6*AG14) -> 36764.706 | ... BP14: =BO14*EXP($B$9-0.5*M$6^2+M$6*AI14) -> 40931.39 | BQ14: =Inputs!$B$20*EXP($B$10-0.5*C$7^2+C$7*AJ14) -> 7431.5046 | BR14: =BQ14*EXP($B$10-0.5*D$7^2+D$7*AK14) -> 5661.1485 | BS14: =BR14*EXP($B$10-0.5*E$7^2+E$7*AL14) -> 6943.353 | BT14: =BS14*EXP($B$10-0.5*F$7^2+F$7*AM14) -> 11667.016 | BU14: =BT14*EXP($B$10-0.5*G$7^2+G$7*AN14) -> 15095.992 | BV14: =BU14*EXP($B$10-0.5*H$7^2+H$7*AO14) -> 24280.984 | BW14: =BV14*EXP($B$10-0.5*I$7^2+I$7*AP14) -> 32694.7 | BX14: =BW14*EXP($B$10-0.5*J$7^2+J$7*AQ14) -> 39548.048 | BY14: =BX14*EXP($B$10-0.5*K$7^2+K$7*AR14) -> 51202.376 | ... CA14: =BZ14*EXP($B$10-0.5*M$7^2+M$7*AT14) -> 61944.983 | CB14: =(AU14*DCF!C$10-DCF!C$5*MAX(AU14*DCF!C$10,0)-MAX(AU14-Inputs!$B$6,0)/Inputs!$B$10)*DCF!C$6 -> 1047.2313 | CC14: =(AV14*DCF!D$10-DCF!D$5*MAX(AV14*DCF!D$10,0)-MAX(AV14-AU14,0)/Inputs!$B$10)*DCF!D$6 -> 1067.3626 | CD14: =(AW14*DCF!E$10-DCF!E$5*MAX(AW14*DCF!E$10,0)-MAX(AW14-AV14,0)/Inputs!$B$10)*DCF!E$6 -> 1140.8078 | CE14: =(AX14*DCF!F$10-DCF!F$5*MAX(AX14*DCF!F$10,0)-MAX(AX14-AW14,0)/Inputs!$B$10)*DCF!F$6 -> 1392.0451 | CF14: =(AY14*DCF!G$10-DCF!G$5*MAX(AY14*DCF!G$10,0)-MAX(AY14-AX14,0)/Inputs!$B$10)*DCF!G$6 -> 1934.3926 | CG14: =(AZ14*DCF!H$10-DCF!H$5*MAX(AZ14*DCF!H$10,0)-MAX(AZ14-AY14,0)/Inputs!$B$10)*DCF!H$6 -> 2153.399 | CH14: =(BA14*DCF!I$10-DCF!I$5*MAX(BA14*DCF!I$10,0)-MAX(BA14-AZ14,0)/Inputs!$B$10)*DCF!I$6 -> 2263.3937 | CI14: =(BB14*DCF!J$10-DCF!J$5*MAX(BB14*DCF!J$10,0)-MAX(BB14-BA14,0)/Inputs!$B$10)*DCF!J$6 -> 2667.3519 | CJ14: =(BC14*DCF!K$10-DCF!K$5*MAX(BC14*DCF!K$10,0)-MAX(BC14-BB14,0)/Inputs!$B$10)*DCF!K$6 -> 3461.7975 | ... CL14: =(BE14*DCF!M$10-DCF!M$5*MAX(BE14*DCF!M$10,0)-MAX(BE14-BD14,0)/Inputs!$B$10)*DCF!M$6 -> 4247.0494 | CM14: =(BF14*DCF!C$28-DCF!C$5*MAX(BF14*DCF!C$28,0)-MAX(BF14-Inputs!$B$13,0)/Inputs!$B$17)*DCF!C$6 -> 3603.5354 | CN14: =(BG14*DCF!D$28-DCF!D$5*MAX(BG14*DCF!D$28,0)-MAX(BG14-BF14,0)/Inputs!$B$17)*DCF!D$6 -> 4010.7386 | CO14: =(BH14*DCF!E$28-DCF!E$5*MAX(BH14*DCF!E$28,0)-MAX(BH14-BG14,0)/Inputs!$B$17)*DCF!E$6 -> 4309.8045 | CP14: =(BI14*DCF!F$28-DCF!F$5*MAX(BI14*DCF!F$28,0)-MAX(BI14-BH14,0)/Inputs!$B$17)*DCF!F$6 -> 4635.9348 | CQ14: =(BJ14*DCF!G$28-DCF!G$5*MAX(BJ14*DCF!G$28,0)-MAX(BJ14-BI14,0)/Inputs!$B$17)*DCF!G$6 -> 5031.3882 | CR14: =(BK14*DCF!H$28-DCF!H$5*MAX(BK14*DCF!H$28,0)-MAX(BK14-BJ14,0)/Inputs!$B$17)*DCF!H$6 -> 4883.9354 | CS14: =(BL14*DCF!I$28-DCF!I$5*MAX(BL14*DCF!I$28,0)-MAX(BL14-BK14,0)/Inputs!$B$17)*DCF!I$6 -> 5497.3979 | CT14: =(BM14*DCF!J$28-DCF!J$5*MAX(BM14*DCF!J$28,0)-MAX(BM14-BL14,0)/Inputs!$B$17)*DCF!J$6 -> 7085.9984 | CU14: =(BN14*DCF!K$28-DCF!K$5*MAX(BN14*DCF!K$28,0)-MAX(BN14-BM14,0)/Inputs!$B$17)*DCF!K$6 -> 7764.0894 | ... CW14: =(BP14*DCF!M$28-DCF!M$5*MAX(BP14*DCF!M$28,0)-MAX(BP14-BO14,0)/Inputs!$B$17)*DCF!M$6 -> 7461.3447 | CX14: =(BQ14*DCF!C$46-DCF!C$5*MAX(BQ14*DCF!C$46,0)-MAX(BQ14-Inputs!$B$20,0)/Inputs!$B$24)*DCF!C$6 -> -3670.3265 | CY14: =(BR14*DCF!D$46-DCF!D$5*MAX(BR14*DCF!D$46,0)-MAX(BR14-BQ14,0)/Inputs!$B$24)*DCF!D$6 -> -966.22603 | CZ14: =(BS14*DCF!E$46-DCF!E$5*MAX(BS14*DCF!E$46,0)-MAX(BS14-BR14,0)/Inputs!$B$24)*DCF!E$6 -> -1326.4733 | DA14: =(BT14*DCF!F$46-DCF!F$5*MAX(BT14*DCF!F$46,0)-MAX(BT14-BS14,0)/Inputs!$B$24)*DCF!F$6 -> -2569.7009 | DB14: =(BU14*DCF!G$46-DCF!G$5*MAX(BU14*DCF!G$46,0)-MAX(BU14-BT14,0)/Inputs!$B$24)*DCF!G$6 -> -1661.2391 | DC14: =(BV14*DCF!H$46-DCF!H$5*MAX(BV14*DCF!H$46,0)-MAX(BV14-BU14,0)/Inputs!$B$24)*DCF!H$6 -> -2854.1799 | DD14: =(BW14*DCF!I$46-DCF!I$5*MAX(BW14*DCF!I$46,0)-MAX(BW14-BV14,0)/Inputs!$B$24)*DCF!I$6 -> -1660.1556 | DE14: =(BX14*DCF!J$46-DCF!J$5*MAX(BX14*DCF!J$46,0)-MAX(BX14-BW14,0)/Inputs!$B$24)*DCF!J$6 -> -158.46489 | DF14: =(BY14*DCF!K$46-DCF!K$5*MAX(BY14*DCF!K$46,0)-MAX(BY14-BX14,0)/Inputs!$B$24)*DCF!K$6 -> 69.850648 | ... DH14: =(CA14*DCF!M$46-DCF!M$5*MAX(CA14*DCF!M$46,0)-MAX(CA14-BZ14,0)/Inputs!$B$24)*DCF!M$6 -> 3909.6216 | DI14: =SUM(CB14:CL14)+BE14*DCF!M$10*(1+Inputs!$B$30)*(1-Inputs!$B$33)*(1-Inputs!$B$30/Inputs!$B$31)/(Inputs!$B$29-Inputs!$B$30)*DCF!M$6 -> 116116.84 | DJ14: =SUM(CM14:CW14)+BP14*DCF!M$28*(1+Inputs!$B$30)*(1-Inputs!$B$33)*(1-Inputs!$B$30/Inputs!$B$31)/(Inputs!$B$29-Inputs!$B$30)*DCF!M$6 -> 213664.6 | DK14: =SUM(CX14:DH14)+CA14*DCF!M$46*(1+Inputs!$B$30)*(1-Inputs!$B$33)*(1-Inputs!$B$30/Inputs!$B$31)/(Inputs!$B$29-Inputs!$B$30)*DCF!M$6 -> 87449.584 | DM14: =DI14+DJ14+DK14+Inputs!$B$34+Inputs!$B$36-Inputs!$B$35 -> 494082.02
A15: 2 | C15: =_xlfn.NORM.S.INV(RAND()) -> 0.92353003 | D15: =_xlfn.NORM.S.INV(RAND()) -> 0.025953389 | E15: =_xlfn.NORM.S.INV(RAND()) -> -1.0652339 | F15: =_xlfn.NORM.S.INV(RAND()) -> -0.085847371 | G15: =_xlfn.NORM.S.INV(RAND()) -> -0.74126636 | H15: =_xlfn.NORM.S.INV(RAND()) -> -1.127027 | I15: =_xlfn.NORM.S.INV(RAND()) -> 0.40682181 | J15: =_xlfn.NORM.S.INV(RAND()) -> 1.1731958 | ... M15: =_xlfn.NORM.S.INV(RAND()) -> -0.094738983 | N15: =SQRT(Inputs!$B$38)*C15+SQRT(1-Inputs!$B$38)*_xlfn.NORM.S.INV(RAND()) -> 1.3135844 | O15: =SQRT(Inputs!$B$38)*D15+SQRT(1-Inputs!$B$38)*_xlfn.NORM.S.INV(RAND()) -> 0.076743268 | P15: =SQRT(Inputs!$B$38)*E15+SQRT(1-Inputs!$B$38)*_xlfn.NORM.S.INV(RAND()) -> -0.51846884 | Q15: =SQRT(Inputs!$B$38)*F15+SQRT(1-Inputs!$B$38)*_xlfn.NORM.S.INV(RAND()) -> 0.252472 | R15: =SQRT(Inputs!$B$38)*G15+SQRT(1-Inputs!$B$38)*_xlfn.NORM.S.INV(RAND()) -> -1.3351437 | S15: =SQRT(Inputs!$B$38)*H15+SQRT(1-Inputs!$B$38)*_xlfn.NORM.S.INV(RAND()) -> -1.7550109 | T15: =SQRT(Inputs!$B$38)*I15+SQRT(1-Inputs!$B$38)*_xlfn.NORM.S.INV(RAND()) -> 0.95404625 | U15: =SQRT(Inputs!$B$38)*J15+SQRT(1-Inputs!$B$38)*_xlfn.NORM.S.INV(RAND()) -> 0.070283655 | ... X15: =SQRT(Inputs!$B$38)*M15+SQRT(1-Inputs!$B$38)*_xlfn.NORM.S.INV(RAND()) -> 0.61546497 | Y15: =SQRT(Inputs!$B$38)*C15+SQRT(1-Inputs!$B$38)*_xlfn.NORM.S.INV(RAND()) -> 1.0145725 | Z15: =SQRT(Inputs!$B$38)*D15+SQRT(1-Inputs!$B$38)*_xlfn.NORM.S.INV(RAND()) -> -1.327462 | AA15: =SQRT(Inputs!$B$38)*E15+SQRT(1-Inputs!$B$38)*_xlfn.NORM.S.INV(RAND()) -> 0.99905022 | AB15: =SQRT(Inputs!$B$38)*F15+SQRT(1-Inputs!$B$38)*_xlfn.NORM.S.INV(RAND()) -> 1.6794097 | AC15: =SQRT(Inputs!$B$38)*G15+SQRT(1-Inputs!$B$38)*_xlfn.NORM.S.INV(RAND()) -> -0.62918751 | AD15: =SQRT(Inputs!$B$38)*H15+SQRT(1-Inputs!$B$38)*_xlfn.NORM.S.INV(RAND()) -> -1.335839 | AE15: =SQRT(Inputs!$B$38)*I15+SQRT(1-Inputs!$B$38)*_xlfn.NORM.S.INV(RAND()) -> 0.65527107 | AF15: =SQRT(Inputs!$B$38)*J15+SQRT(1-Inputs!$B$38)*_xlfn.NORM.S.INV(RAND()) -> 0.55632197 | ... AI15: =SQRT(Inputs!$B$38)*M15+SQRT(1-Inputs!$B$38)*_xlfn.NORM.S.INV(RAND()) -> 0.47669226 | AJ15: =SQRT(Inputs!$B$38)*C15+SQRT(1-Inputs!$B$38)*_xlfn.NORM.S.INV(RAND()) -> 0.31887492 | AK15: =SQRT(Inputs!$B$38)*D15+SQRT(1-Inputs!$B$38)*_xlfn.NORM.S.INV(RAND()) -> -0.36676824 | AL15: =SQRT(Inputs!$B$38)*E15+SQRT(1-Inputs!$B$38)*_xlfn.NORM.S.INV(RAND()) -> -0.82448535 | AM15: =SQRT(Inputs!$B$38)*F15+SQRT(1-Inputs!$B$38)*_xlfn.NORM.S.INV(RAND()) -> -1.2358924 | AN15: =SQRT(Inputs!$B$38)*G15+SQRT(1-Inputs!$B$38)*_xlfn.NORM.S.INV(RAND()) -> 1.1074882 | AO15: =SQRT(Inputs!$B$38)*H15+SQRT(1-Inputs!$B$38)*_xlfn.NORM.S.INV(RAND()) -> -2.0293819 | AP15: =SQRT(Inputs!$B$38)*I15+SQRT(1-Inputs!$B$38)*_xlfn.NORM.S.INV(RAND()) -> 1.7656908 | AQ15: =SQRT(Inputs!$B$38)*J15+SQRT(1-Inputs!$B$38)*_xlfn.NORM.S.INV(RAND()) -> -0.13764071 | ... AT15: =SQRT(Inputs!$B$38)*M15+SQRT(1-Inputs!$B$38)*_xlfn.NORM.S.INV(RAND()) -> 0.57391158 | AU15: =Inputs!$B$6*EXP($B$8-0.5*C$5^2+C$5*N15) -> 6137.9517 | AV15: =AU15*EXP($B$8-0.5*D$5^2+D$5*O15) -> 7556.1189 | AW15: =AV15*EXP($B$8-0.5*E$5^2+E$5*P15) -> 8591.0557 | AX15: =AW15*EXP($B$8-0.5*F$5^2+F$5*Q15) -> 10824.928 | AY15: =AX15*EXP($B$8-0.5*G$5^2+G$5*R15) -> 11319.143 | AZ15: =AY15*EXP($B$8-0.5*H$5^2+H$5*S15) -> 11410.837 | BA15: =AZ15*EXP($B$8-0.5*I$5^2+I$5*T15) -> 15430.236 | BB15: =BA15*EXP($B$8-0.5*J$5^2+J$5*U15) -> 19024.807 | BC15: =BB15*EXP($B$8-0.5*K$5^2+K$5*V15) -> 22569.268 | ... BE15: =BD15*EXP($B$8-0.5*M$5^2+M$5*X15) -> 33026.803 | BF15: =Inputs!$B$13*EXP($B$9-0.5*C$6^2+C$6*Y15) -> 16912.46 | BG15: =BF15*EXP($B$9-0.5*D$6^2+D$6*Z15) -> 16221.526 | BH15: =BG15*EXP($B$9-0.5*E$6^2+E$6*AA15) -> 23391.609 | BI15: =BH15*EXP($B$9-0.5*F$6^2+F$6*AB15) -> 37081.503 | BJ15: =BI15*EXP($B$9-0.5*G$6^2+G$6*AC15) -> 41518.014 | BK15: =BJ15*EXP($B$9-0.5*H$6^2+H$6*AD15) -> 42482.28 | BL15: =BK15*EXP($B$9-0.5*I$6^2+I$6*AE15) -> 56809.319 | BM15: =BL15*EXP($B$9-0.5*J$6^2+J$6*AF15) -> 74827.64 | BN15: =BM15*EXP($B$9-0.5*K$6^2+K$6*AG15) -> 87359.847 | ... BP15: =BO15*EXP($B$9-0.5*M$6^2+M$6*AI15) -> 141524.21 | BQ15: =Inputs!$B$20*EXP($B$10-0.5*C$7^2+C$7*AJ15) -> 4803.1542 | BR15: =BQ15*EXP($B$10-0.5*D$7^2+D$7*AK15) -> 5800.6854 | BS15: =BR15*EXP($B$10-0.5*E$7^2+E$7*AL15) -> 6268.5733 | BT15: =BS15*EXP($B$10-0.5*F$7^2+F$7*AM15) -> 6249.7116 | BU15: =BT15*EXP($B$10-0.5*G$7^2+G$7*AN15) -> 11323.151 | BV15: =BU15*EXP($B$10-0.5*H$7^2+H$7*AO15) -> 9972.8155 | BW15: =BV15*EXP($B$10-0.5*I$7^2+I$7*AP15) -> 20222.228 | BX15: =BW15*EXP($B$10-0.5*J$7^2+J$7*AQ15) -> 27514.252 | BY15: =BX15*EXP($B$10-0.5*K$7^2+K$7*AR15) -> 49902.241 | ... CA15: =BZ15*EXP($B$10-0.5*M$7^2+M$7*AT15) -> 113425.31 | CB15: =(AU15*DCF!C$10-DCF!C$5*MAX(AU15*DCF!C$10,0)-MAX(AU15-Inputs!$B$6,0)/Inputs!$B$10)*DCF!C$6 -> 1034.6913 | CC15: =(AV15*DCF!D$10-DCF!D$5*MAX(AV15*DCF!D$10,0)-MAX(AV15-AU15,0)/Inputs!$B$10)*DCF!D$6 -> 1495.9698 | CD15: =(AW15*DCF!E$10-DCF!E$5*MAX(AW15*DCF!E$10,0)-MAX(AW15-AV15,0)/Inputs!$B$10)*DCF!E$6 -> 1750.4274 | CE15: =(AX15*DCF!F$10-DCF!F$5*MAX(AX15*DCF!F$10,0)-MAX(AX15-AW15,0)/Inputs!$B$10)*DCF!F$6 -> 1898.2511 | CF15: =(AY15*DCF!G$10-DCF!G$5*MAX(AY15*DCF!G$10,0)-MAX(AY15-AX15,0)/Inputs!$B$10)*DCF!G$6 -> 2237.1979 | CG15: =(AZ15*DCF!H$10-DCF!H$5*MAX(AZ15*DCF!H$10,0)-MAX(AZ15-AY15,0)/Inputs!$B$10)*DCF!H$6 -> 2199.1402 | CH15: =(BA15*DCF!I$10-DCF!I$5*MAX(BA15*DCF!I$10,0)-MAX(BA15-AZ15,0)/Inputs!$B$10)*DCF!I$6 -> 2159.2189 | CI15: =(BB15*DCF!J$10-DCF!J$5*MAX(BB15*DCF!J$10,0)-MAX(BB15-BA15,0)/Inputs!$B$10)*DCF!J$6 -> 2720.003 | CJ15: =(BC15*DCF!K$10-DCF!K$5*MAX(BC15*DCF!K$10,0)-MAX(BC15-BB15,0)/Inputs!$B$10)*DCF!K$6 -> 3137.1191 | ... CL15: =(BE15*DCF!M$10-DCF!M$5*MAX(BE15*DCF!M$10,0)-MAX(BE15-BD15,0)/Inputs!$B$10)*DCF!M$6 -> 3759.342 | CM15: =(BF15*DCF!C$28-DCF!C$5*MAX(BF15*DCF!C$28,0)-MAX(BF15-Inputs!$B$13,0)/Inputs!$B$17)*DCF!C$6 -> 3885.4841 | CN15: =(BG15*DCF!D$28-DCF!D$5*MAX(BG15*DCF!D$28,0)-MAX(BG15-BF15,0)/Inputs!$B$17)*DCF!D$6 -> 4777.6137 | CO15: =(BH15*DCF!E$28-DCF!E$5*MAX(BH15*DCF!E$28,0)-MAX(BH15-BG15,0)/Inputs!$B$17)*DCF!E$6 -> 5211.7956 | CP15: =(BI15*DCF!F$28-DCF!F$5*MAX(BI15*DCF!F$28,0)-MAX(BI15-BH15,0)/Inputs!$B$17)*DCF!F$6 -> 7574.1897 | CQ15: =(BJ15*DCF!G$28-DCF!G$5*MAX(BJ15*DCF!G$28,0)-MAX(BJ15-BI15,0)/Inputs!$B$17)*DCF!G$6 -> 10025.986 | CR15: =(BK15*DCF!H$28-DCF!H$5*MAX(BK15*DCF!H$28,0)-MAX(BK15-BJ15,0)/Inputs!$B$17)*DCF!H$6 -> 10356.517 | CS15: =(BL15*DCF!I$28-DCF!I$5*MAX(BL15*DCF!I$28,0)-MAX(BL15-BK15,0)/Inputs!$B$17)*DCF!I$6 -> 11302.515 | CT15: =(BM15*DCF!J$28-DCF!J$5*MAX(BM15*DCF!J$28,0)-MAX(BM15-BL15,0)/Inputs!$B$17)*DCF!J$6 -> 14303.694 | CU15: =(BN15*DCF!K$28-DCF!K$5*MAX(BN15*DCF!K$28,0)-MAX(BN15-BM15,0)/Inputs!$B$17)*DCF!K$6 -> 16913.907 | ... CW15: =(BP15*DCF!M$28-DCF!M$5*MAX(BP15*DCF!M$28,0)-MAX(BP15-BO15,0)/Inputs!$B$17)*DCF!M$6 -> 23221.798 | CX15: =(BQ15*DCF!C$46-DCF!C$5*MAX(BQ15*DCF!C$46,0)-MAX(BQ15-Inputs!$B$20,0)/Inputs!$B$24)*DCF!C$6 -> -1849.2985 | CY15: =(BR15*DCF!D$46-DCF!D$5*MAX(BR15*DCF!D$46,0)-MAX(BR15-BQ15,0)/Inputs!$B$24)*DCF!D$6 -> -1415.68 | CZ15: =(BS15*DCF!E$46-DCF!E$5*MAX(BS15*DCF!E$46,0)-MAX(BS15-BR15,0)/Inputs!$B$24)*DCF!E$6 -> -925.69824 | DA15: =(BT15*DCF!F$46-DCF!F$5*MAX(BT15*DCF!F$46,0)-MAX(BT15-BS15,0)/Inputs!$B$24)*DCF!F$6 -> -455.14351 | DB15: =(BU15*DCF!G$46-DCF!G$5*MAX(BU15*DCF!G$46,0)-MAX(BU15-BT15,0)/Inputs!$B$24)*DCF!G$6 -> -2087.4933 | DC15: =(BV15*DCF!H$46-DCF!H$5*MAX(BV15*DCF!H$46,0)-MAX(BV15-BU15,0)/Inputs!$B$24)*DCF!H$6 -> 0 | DD15: =(BW15*DCF!I$46-DCF!I$5*MAX(BW15*DCF!I$46,0)-MAX(BW15-BV15,0)/Inputs!$B$24)*DCF!I$6 -> -2475.1697 | DE15: =(BX15*DCF!J$46-DCF!J$5*MAX(BX15*DCF!J$46,0)-MAX(BX15-BW15,0)/Inputs!$B$24)*DCF!J$6 -> -779.57876 | DF15: =(BY15*DCF!K$46-DCF!K$5*MAX(BY15*DCF!K$46,0)-MAX(BY15-BX15,0)/Inputs!$B$24)*DCF!K$6 -> -2633.8786 | ... DH15: =(CA15*DCF!M$46-DCF!M$5*MAX(CA15*DCF!M$46,0)-MAX(CA15-BZ15,0)/Inputs!$B$24)*DCF!M$6 -> 423.84406 | DI15: =SUM(CB15:CL15)+BE15*DCF!M$10*(1+Inputs!$B$30)*(1-Inputs!$B$33)*(1-Inputs!$B$30/Inputs!$B$31)/(Inputs!$B$29-Inputs!$B$30)*DCF!M$6 -> 117771.92 | DJ15: =SUM(CM15:CW15)+BP15*DCF!M$28*(1+Inputs!$B$30)*(1-Inputs!$B$33)*(1-Inputs!$B$30/Inputs!$B$31)/(Inputs!$B$29-Inputs!$B$30)*DCF!M$6 -> 652019.06 | DK15: =SUM(CX15:DH15)+CA15*DCF!M$46*(1+Inputs!$B$30)*(1-Inputs!$B$33)*(1-Inputs!$B$30/Inputs!$B$31)/(Inputs!$B$29-Inputs!$B$30)*DCF!M$6 -> 163002.77 | DM15: =DI15+DJ15+DK15+Inputs!$B$34+Inputs!$B$36-Inputs!$B$35 -> 1009644.8
A16: 3 | C16: =_xlfn.NORM.S.INV(RAND()) -> -1.5444695 | D16: =_xlfn.NORM.S.INV(RAND()) -> -0.2740138 | E16: =_xlfn.NORM.S.INV(RAND()) -> -0.26960314 | F16: =_xlfn.NORM.S.INV(RAND()) -> -0.92858525 | G16: =_xlfn.NORM.S.INV(RAND()) -> -0.49987716 | H16: =_xlfn.NORM.S.INV(RAND()) -> 0.12662781 | I16: =_xlfn.NORM.S.INV(RAND()) -> -1.7655709 | J16: =_xlfn.NORM.S.INV(RAND()) -> -1.567023 | ... M16: =_xlfn.NORM.S.INV(RAND()) -> -1.9434072 | N16: =SQRT(Inputs!$B$38)*C16+SQRT(1-Inputs!$B$38)*_xlfn.NORM.S.INV(RAND()) -> -0.8736558 | O16: =SQRT(Inputs!$B$38)*D16+SQRT(1-Inputs!$B$38)*_xlfn.NORM.S.INV(RAND()) -> -0.78040726 | P16: =SQRT(Inputs!$B$38)*E16+SQRT(1-Inputs!$B$38)*_xlfn.NORM.S.INV(RAND()) -> 0.56077767 | Q16: =SQRT(Inputs!$B$38)*F16+SQRT(1-Inputs!$B$38)*_xlfn.NORM.S.INV(RAND()) -> -1.365717 | R16: =SQRT(Inputs!$B$38)*G16+SQRT(1-Inputs!$B$38)*_xlfn.NORM.S.INV(RAND()) -> 0.35775847 | S16: =SQRT(Inputs!$B$38)*H16+SQRT(1-Inputs!$B$38)*_xlfn.NORM.S.INV(RAND()) -> 0.41322574 | T16: =SQRT(Inputs!$B$38)*I16+SQRT(1-Inputs!$B$38)*_xlfn.NORM.S.INV(RAND()) -> -1.5592541 | U16: =SQRT(Inputs!$B$38)*J16+SQRT(1-Inputs!$B$38)*_xlfn.NORM.S.INV(RAND()) -> -0.42419783 | ... X16: =SQRT(Inputs!$B$38)*M16+SQRT(1-Inputs!$B$38)*_xlfn.NORM.S.INV(RAND()) -> -0.67287191 | Y16: =SQRT(Inputs!$B$38)*C16+SQRT(1-Inputs!$B$38)*_xlfn.NORM.S.INV(RAND()) -> -1.6211951 | Z16: =SQRT(Inputs!$B$38)*D16+SQRT(1-Inputs!$B$38)*_xlfn.NORM.S.INV(RAND()) -> 1.662654 | AA16: =SQRT(Inputs!$B$38)*E16+SQRT(1-Inputs!$B$38)*_xlfn.NORM.S.INV(RAND()) -> -0.6676351 | AB16: =SQRT(Inputs!$B$38)*F16+SQRT(1-Inputs!$B$38)*_xlfn.NORM.S.INV(RAND()) -> 0.8920561 | AC16: =SQRT(Inputs!$B$38)*G16+SQRT(1-Inputs!$B$38)*_xlfn.NORM.S.INV(RAND()) -> -0.56228473 | AD16: =SQRT(Inputs!$B$38)*H16+SQRT(1-Inputs!$B$38)*_xlfn.NORM.S.INV(RAND()) -> -0.6614673 | AE16: =SQRT(Inputs!$B$38)*I16+SQRT(1-Inputs!$B$38)*_xlfn.NORM.S.INV(RAND()) -> -0.83280776 | AF16: =SQRT(Inputs!$B$38)*J16+SQRT(1-Inputs!$B$38)*_xlfn.NORM.S.INV(RAND()) -> 0.096398321 | ... AI16: =SQRT(Inputs!$B$38)*M16+SQRT(1-Inputs!$B$38)*_xlfn.NORM.S.INV(RAND()) -> -1.1509788 | AJ16: =SQRT(Inputs!$B$38)*C16+SQRT(1-Inputs!$B$38)*_xlfn.NORM.S.INV(RAND()) -> -0.060959674 | AK16: =SQRT(Inputs!$B$38)*D16+SQRT(1-Inputs!$B$38)*_xlfn.NORM.S.INV(RAND()) -> 0.85634138 | AL16: =SQRT(Inputs!$B$38)*E16+SQRT(1-Inputs!$B$38)*_xlfn.NORM.S.INV(RAND()) -> -0.50906469 | AM16: =SQRT(Inputs!$B$38)*F16+SQRT(1-Inputs!$B$38)*_xlfn.NORM.S.INV(RAND()) -> -1.0062763 | AN16: =SQRT(Inputs!$B$38)*G16+SQRT(1-Inputs!$B$38)*_xlfn.NORM.S.INV(RAND()) -> -0.78967937 | AO16: =SQRT(Inputs!$B$38)*H16+SQRT(1-Inputs!$B$38)*_xlfn.NORM.S.INV(RAND()) -> -0.43139989 | AP16: =SQRT(Inputs!$B$38)*I16+SQRT(1-Inputs!$B$38)*_xlfn.NORM.S.INV(RAND()) -> -0.5971008 | AQ16: =SQRT(Inputs!$B$38)*J16+SQRT(1-Inputs!$B$38)*_xlfn.NORM.S.INV(RAND()) -> -0.20181332 | ... AT16: =SQRT(Inputs!$B$38)*M16+SQRT(1-Inputs!$B$38)*_xlfn.NORM.S.INV(RAND()) -> -0.016466967 | AU16: =Inputs!$B$6*EXP($B$8-0.5*C$5^2+C$5*N16) -> 4307.8364 | AV16: =AU16*EXP($B$8-0.5*D$5^2+D$5*O16) -> 4675.2088 | AW16: =AV16*EXP($B$8-0.5*E$5^2+E$5*P16) -> 6148.4978 | AX16: =AW16*EXP($B$8-0.5*F$5^2+F$5*Q16) -> 6329.1933 | AY16: =AX16*EXP($B$8-0.5*G$5^2+G$5*R16) -> 8064.9461 | AZ16: =AY16*EXP($B$8-0.5*H$5^2+H$5*S16) -> 10322.853 | BA16: =AZ16*EXP($B$8-0.5*I$5^2+I$5*T16) -> 10730.438 | BB16: =BA16*EXP($B$8-0.5*J$5^2+J$5*U16) -> 12590.685 | BC16: =BB16*EXP($B$8-0.5*K$5^2+K$5*V16) -> 14296.394 | ... BE16: =BD16*EXP($B$8-0.5*M$5^2+M$5*X16) -> 21888.111 | BF16: =Inputs!$B$13*EXP($B$9-0.5*C$6^2+C$6*Y16) -> 10029.35 | BG16: =BF16*EXP($B$9-0.5*D$6^2+D$6*Z16) -> 16499.599 | BH16: =BG16*EXP($B$9-0.5*E$6^2+E$6*AA16) -> 18046.327 | BI16: =BH16*EXP($B$9-0.5*F$6^2+F$6*AB16) -> 25342.785 | BJ16: =BI16*EXP($B$9-0.5*G$6^2+G$6*AC16) -> 28649.813 | BK16: =BJ16*EXP($B$9-0.5*H$6^2+H$6*AD16) -> 32134.099 | BL16: =BK16*EXP($B$9-0.5*I$6^2+I$6*AE16) -> 35434.592 | BM16: =BL16*EXP($B$9-0.5*J$6^2+J$6*AF16) -> 44081.503 | BN16: =BM16*EXP($B$9-0.5*K$6^2+K$6*AG16) -> 47790.28 | ... BP16: =BO16*EXP($B$9-0.5*M$6^2+M$6*AI16) -> 66045.714 | BQ16: =Inputs!$B$20*EXP($B$10-0.5*C$7^2+C$7*AJ16) -> 4197.7643 | BR16: =BQ16*EXP($B$10-0.5*D$7^2+D$7*AK16) -> 7475.9447 | BS16: =BR16*EXP($B$10-0.5*E$7^2+E$7*AL16) -> 8845.0053 | BT16: =BS16*EXP($B$10-0.5*F$7^2+F$7*AM16) -> 9365.8975 | BU16: =BT16*EXP($B$10-0.5*G$7^2+G$7*AN16) -> 10722.367 | BV16: =BU16*EXP($B$10-0.5*H$7^2+H$7*AO16) -> 13536.212 | BW16: =BV16*EXP($B$10-0.5*I$7^2+I$7*AP16) -> 16646.581 | BX16: =BW16*EXP($B$10-0.5*J$7^2+J$7*AQ16) -> 22359.732 | BY16: =BX16*EXP($B$10-0.5*K$7^2+K$7*AR16) -> 36186.975 | ... CA16: =BZ16*EXP($B$10-0.5*M$7^2+M$7*AT16) -> 78812.871 | CB16: =(AU16*DCF!C$10-DCF!C$5*MAX(AU16*DCF!C$10,0)-MAX(AU16-Inputs!$B$6,0)/Inputs!$B$10)*DCF!C$6 -> 1047.7403 | CC16: =(AV16*DCF!D$10-DCF!D$5*MAX(AV16*DCF!D$10,0)-MAX(AV16-AU16,0)/Inputs!$B$10)*DCF!D$6 -> 1049.9763 | CD16: =(AW16*DCF!E$10-DCF!E$5*MAX(AW16*DCF!E$10,0)-MAX(AW16-AV16,0)/Inputs!$B$10)*DCF!E$6 -> 1087.7446 | CE16: =(AX16*DCF!F$10-DCF!F$5*MAX(AX16*DCF!F$10,0)-MAX(AX16-AW16,0)/Inputs!$B$10)*DCF!F$6 -> 1344.0546 | CF16: =(AY16*DCF!G$10-DCF!G$5*MAX(AY16*DCF!G$10,0)-MAX(AY16-AX16,0)/Inputs!$B$10)*DCF!G$6 -> 1328.0586 | CG16: =(AZ16*DCF!H$10-DCF!H$5*MAX(AZ16*DCF!H$10,0)-MAX(AZ16-AY16,0)/Inputs!$B$10)*DCF!H$6 -> 1603.2575 | CH16: =(BA16*DCF!I$10-DCF!I$5*MAX(BA16*DCF!I$10,0)-MAX(BA16-AZ16,0)/Inputs!$B$10)*DCF!I$6 -> 1893.2013 | CI16: =(BB16*DCF!J$10-DCF!J$5*MAX(BB16*DCF!J$10,0)-MAX(BB16-BA16,0)/Inputs!$B$10)*DCF!J$6 -> 1878.7009 | CJ16: =(BC16*DCF!K$10-DCF!K$5*MAX(BC16*DCF!K$10,0)-MAX(BC16-BB16,0)/Inputs!$B$10)*DCF!K$6 -> 2062.7165 | ... CL16: =(BE16*DCF!M$10-DCF!M$5*MAX(BE16*DCF!M$10,0)-MAX(BE16-BD16,0)/Inputs!$B$10)*DCF!M$6 -> 2742.649 | CM16: =(BF16*DCF!C$28-DCF!C$5*MAX(BF16*DCF!C$28,0)-MAX(BF16-Inputs!$B$13,0)/Inputs!$B$17)*DCF!C$6 -> 3060.8918 | CN16: =(BG16*DCF!D$28-DCF!D$5*MAX(BG16*DCF!D$28,0)-MAX(BG16-BF16,0)/Inputs!$B$17)*DCF!D$6 -> 3479.1116 | CO16: =(BH16*DCF!E$28-DCF!E$5*MAX(BH16*DCF!E$28,0)-MAX(BH16-BG16,0)/Inputs!$B$17)*DCF!E$6 -> 4806.2023 | CP16: =(BI16*DCF!F$28-DCF!F$5*MAX(BI16*DCF!F$28,0)-MAX(BI16-BH16,0)/Inputs!$B$17)*DCF!F$6 -> 5551.463 | CQ16: =(BJ16*DCF!G$28-DCF!G$5*MAX(BJ16*DCF!G$28,0)-MAX(BJ16-BI16,0)/Inputs!$B$17)*DCF!G$6 -> 6877.2019 | CR16: =(BK16*DCF!H$28-DCF!H$5*MAX(BK16*DCF!H$28,0)-MAX(BK16-BJ16,0)/Inputs!$B$17)*DCF!H$6 -> 7405.757 | CS16: =(BL16*DCF!I$28-DCF!I$5*MAX(BL16*DCF!I$28,0)-MAX(BL16-BK16,0)/Inputs!$B$17)*DCF!I$6 -> 7858.83 | CT16: =(BM16*DCF!J$28-DCF!J$5*MAX(BM16*DCF!J$28,0)-MAX(BM16-BL16,0)/Inputs!$B$17)*DCF!J$6 -> 8687.3249 | CU16: =(BN16*DCF!K$28-DCF!K$5*MAX(BN16*DCF!K$28,0)-MAX(BN16-BM16,0)/Inputs!$B$17)*DCF!K$6 -> 9638.2301 | ... CW16: =(BP16*DCF!M$28-DCF!M$5*MAX(BP16*DCF!M$28,0)-MAX(BP16-BO16,0)/Inputs!$B$17)*DCF!M$6 -> 11913.166 | CX16: =(BQ16*DCF!C$46-DCF!C$5*MAX(BQ16*DCF!C$46,0)-MAX(BQ16-Inputs!$B$20,0)/Inputs!$B$24)*DCF!C$6 -> -1429.8598 | CY16: =(BR16*DCF!D$46-DCF!D$5*MAX(BR16*DCF!D$46,0)-MAX(BR16-BQ16,0)/Inputs!$B$24)*DCF!D$6 -> -2674.7418 | CZ16: =(BS16*DCF!E$46-DCF!E$5*MAX(BS16*DCF!E$46,0)-MAX(BS16-BR16,0)/Inputs!$B$24)*DCF!E$6 -> -1585.5833 | DA16: =(BT16*DCF!F$46-DCF!F$5*MAX(BT16*DCF!F$46,0)-MAX(BT16-BS16,0)/Inputs!$B$24)*DCF!F$6 -> -871.75718 | DB16: =(BU16*DCF!G$46-DCF!G$5*MAX(BU16*DCF!G$46,0)-MAX(BU16-BT16,0)/Inputs!$B$24)*DCF!G$6 -> -816.96866 | DC16: =(BV16*DCF!H$46-DCF!H$5*MAX(BV16*DCF!H$46,0)-MAX(BV16-BU16,0)/Inputs!$B$24)*DCF!H$6 -> -874.38518 | DD16: =(BW16*DCF!I$46-DCF!I$5*MAX(BW16*DCF!I$46,0)-MAX(BW16-BV16,0)/Inputs!$B$24)*DCF!I$6 -> -508.40752 | DE16: =(BX16*DCF!J$46-DCF!J$5*MAX(BX16*DCF!J$46,0)-MAX(BX16-BW16,0)/Inputs!$B$24)*DCF!J$6 -> -577.10517 | DF16: =(BY16*DCF!K$46-DCF!K$5*MAX(BY16*DCF!K$46,0)-MAX(BY16-BX16,0)/Inputs!$B$24)*DCF!K$6 -> -1320.1856 | ... DH16: =(CA16*DCF!M$46-DCF!M$5*MAX(CA16*DCF!M$46,0)-MAX(CA16-BZ16,0)/Inputs!$B$24)*DCF!M$6 -> 1466.1247 | DI16: =SUM(CB16:CL16)+BE16*DCF!M$10*(1+Inputs!$B$30)*(1-Inputs!$B$33)*(1-Inputs!$B$30/Inputs!$B$31)/(Inputs!$B$29-Inputs!$B$30)*DCF!M$6 -> 79210.124 | DJ16: =SUM(CM16:CW16)+BP16*DCF!M$28*(1+Inputs!$B$30)*(1-Inputs!$B$33)*(1-Inputs!$B$30/Inputs!$B$31)/(Inputs!$B$29-Inputs!$B$30)*DCF!M$6 -> 325040.66 | DK16: =SUM(CX16:DH16)+CA16*DCF!M$46*(1+Inputs!$B$30)*(1-Inputs!$B$33)*(1-Inputs!$B$30/Inputs!$B$31)/(Inputs!$B$29-Inputs!$B$30)*DCF!M$6 -> 112005.82 | DM16: =DI16+DJ16+DK16+Inputs!$B$34+Inputs!$B$36-Inputs!$B$35 -> 593107.6
A17: 4 | C17: =_xlfn.NORM.S.INV(RAND()) -> 0.52642688 | D17: =_xlfn.NORM.S.INV(RAND()) -> -0.43621225 | E17: =_xlfn.NORM.S.INV(RAND()) -> 0.23700693 | F17: =_xlfn.NORM.S.INV(RAND()) -> -0.36997229 | G17: =_xlfn.NORM.S.INV(RAND()) -> 0.19689505 | H17: =_xlfn.NORM.S.INV(RAND()) -> -0.53204403 | I17: =_xlfn.NORM.S.INV(RAND()) -> 1.1039546 | J17: =_xlfn.NORM.S.INV(RAND()) -> 0.15101838 | ... M17: =_xlfn.NORM.S.INV(RAND()) -> 0.14923249 | N17: =SQRT(Inputs!$B$38)*C17+SQRT(1-Inputs!$B$38)*_xlfn.NORM.S.INV(RAND()) -> 0.47074689 | O17: =SQRT(Inputs!$B$38)*D17+SQRT(1-Inputs!$B$38)*_xlfn.NORM.S.INV(RAND()) -> 0.89908794 | P17: =SQRT(Inputs!$B$38)*E17+SQRT(1-Inputs!$B$38)*_xlfn.NORM.S.INV(RAND()) -> 0.88501621 | Q17: =SQRT(Inputs!$B$38)*F17+SQRT(1-Inputs!$B$38)*_xlfn.NORM.S.INV(RAND()) -> -0.33383682 | R17: =SQRT(Inputs!$B$38)*G17+SQRT(1-Inputs!$B$38)*_xlfn.NORM.S.INV(RAND()) -> 0.95646507 | S17: =SQRT(Inputs!$B$38)*H17+SQRT(1-Inputs!$B$38)*_xlfn.NORM.S.INV(RAND()) -> -1.4449946 | T17: =SQRT(Inputs!$B$38)*I17+SQRT(1-Inputs!$B$38)*_xlfn.NORM.S.INV(RAND()) -> 0.59709862 | U17: =SQRT(Inputs!$B$38)*J17+SQRT(1-Inputs!$B$38)*_xlfn.NORM.S.INV(RAND()) -> 0.31425183 | ... X17: =SQRT(Inputs!$B$38)*M17+SQRT(1-Inputs!$B$38)*_xlfn.NORM.S.INV(RAND()) -> -1.3259054 | Y17: =SQRT(Inputs!$B$38)*C17+SQRT(1-Inputs!$B$38)*_xlfn.NORM.S.INV(RAND()) -> 1.0875984 | Z17: =SQRT(Inputs!$B$38)*D17+SQRT(1-Inputs!$B$38)*_xlfn.NORM.S.INV(RAND()) -> 0.05843651 | AA17: =SQRT(Inputs!$B$38)*E17+SQRT(1-Inputs!$B$38)*_xlfn.NORM.S.INV(RAND()) -> 0.31934954 | AB17: =SQRT(Inputs!$B$38)*F17+SQRT(1-Inputs!$B$38)*_xlfn.NORM.S.INV(RAND()) -> -0.94623594 | AC17: =SQRT(Inputs!$B$38)*G17+SQRT(1-Inputs!$B$38)*_xlfn.NORM.S.INV(RAND()) -> -0.27796009 | AD17: =SQRT(Inputs!$B$38)*H17+SQRT(1-Inputs!$B$38)*_xlfn.NORM.S.INV(RAND()) -> -0.1950446 | AE17: =SQRT(Inputs!$B$38)*I17+SQRT(1-Inputs!$B$38)*_xlfn.NORM.S.INV(RAND()) -> 1.2227755 | AF17: =SQRT(Inputs!$B$38)*J17+SQRT(1-Inputs!$B$38)*_xlfn.NORM.S.INV(RAND()) -> 0.06072093 | ... AI17: =SQRT(Inputs!$B$38)*M17+SQRT(1-Inputs!$B$38)*_xlfn.NORM.S.INV(RAND()) -> 1.0179344 | AJ17: =SQRT(Inputs!$B$38)*C17+SQRT(1-Inputs!$B$38)*_xlfn.NORM.S.INV(RAND()) -> -0.29206539 | AK17: =SQRT(Inputs!$B$38)*D17+SQRT(1-Inputs!$B$38)*_xlfn.NORM.S.INV(RAND()) -> 0.21835061 | AL17: =SQRT(Inputs!$B$38)*E17+SQRT(1-Inputs!$B$38)*_xlfn.NORM.S.INV(RAND()) -> 1.6735184 | AM17: =SQRT(Inputs!$B$38)*F17+SQRT(1-Inputs!$B$38)*_xlfn.NORM.S.INV(RAND()) -> -0.10957886 | AN17: =SQRT(Inputs!$B$38)*G17+SQRT(1-Inputs!$B$38)*_xlfn.NORM.S.INV(RAND()) -> 0.25035469 | AO17: =SQRT(Inputs!$B$38)*H17+SQRT(1-Inputs!$B$38)*_xlfn.NORM.S.INV(RAND()) -> -1.4072554 | AP17: =SQRT(Inputs!$B$38)*I17+SQRT(1-Inputs!$B$38)*_xlfn.NORM.S.INV(RAND()) -> 2.7207749 | AQ17: =SQRT(Inputs!$B$38)*J17+SQRT(1-Inputs!$B$38)*_xlfn.NORM.S.INV(RAND()) -> 0.41230261 | ... AT17: =SQRT(Inputs!$B$38)*M17+SQRT(1-Inputs!$B$38)*_xlfn.NORM.S.INV(RAND()) -> -0.65644694 | AU17: =Inputs!$B$6*EXP($B$8-0.5*C$5^2+C$5*N17) -> 5355.1482 | AV17: =AU17*EXP($B$8-0.5*D$5^2+D$5*O17) -> 7439.7405 | AW17: =AV17*EXP($B$8-0.5*E$5^2+E$5*P17) -> 10221.605 | AX17: =AW17*EXP($B$8-0.5*F$5^2+F$5*Q17) -> 11969.771 | AY17: =AX17*EXP($B$8-0.5*G$5^2+G$5*R17) -> 16357.072 | AZ17: =AY17*EXP($B$8-0.5*H$5^2+H$5*S17) -> 17062.231 | BA17: =AZ17*EXP($B$8-0.5*I$5^2+I$5*T17) -> 22226.266 | BB17: =BA17*EXP($B$8-0.5*J$5^2+J$5*U17) -> 28082.107 | BC17: =BB17*EXP($B$8-0.5*K$5^2+K$5*V17) -> 29499.842 | ... BE17: =BD17*EXP($B$8-0.5*M$5^2+M$5*X17) -> 33146.629 | BF17: =Inputs!$B$13*EXP($B$9-0.5*C$6^2+C$6*Y17) -> 17159.086 | BG17: =BF17*EXP($B$9-0.5*D$6^2+D$6*Z17) -> 21134.054 | BH17: =BG17*EXP($B$9-0.5*E$6^2+E$6*AA17) -> 27226.493 | BI17: =BH17*EXP($B$9-0.5*F$6^2+F$6*AB17) -> 28812.042 | BJ17: =BI17*EXP($B$9-0.5*G$6^2+G$6*AC17) -> 33934.44 | BK17: =BJ17*EXP($B$9-0.5*H$6^2+H$6*AD17) -> 40556.724 | BL17: =BK17*EXP($B$9-0.5*I$6^2+I$6*AE17) -> 58373.308 | BM17: =BL17*EXP($B$9-0.5*J$6^2+J$6*AF17) -> 72296.692 | BN17: =BM17*EXP($B$9-0.5*K$6^2+K$6*AG17) -> 75596.466 | ... BP17: =BO17*EXP($B$9-0.5*M$6^2+M$6*AI17) -> 125986.15 | BQ17: =Inputs!$B$20*EXP($B$10-0.5*C$7^2+C$7*AJ17) -> 3867.4016 | BR17: =BQ17*EXP($B$10-0.5*D$7^2+D$7*AK17) -> 5624.3657 | BS17: =BR17*EXP($B$10-0.5*E$7^2+E$7*AL17) -> 12454.909 | BT17: =BS17*EXP($B$10-0.5*F$7^2+F$7*AM17) -> 16685.994 | BU17: =BT17*EXP($B$10-0.5*G$7^2+G$7*AN17) -> 24568.947 | BV17: =BU17*EXP($B$10-0.5*H$7^2+H$7*AO17) -> 24894.852 | BW17: =BV17*EXP($B$10-0.5*I$7^2+I$7*AP17) -> 61788.876 | BX17: =BW17*EXP($B$10-0.5*J$7^2+J$7*AQ17) -> 93868.463 | BY17: =BX17*EXP($B$10-0.5*K$7^2+K$7*AR17) -> 125708.43 | ... CA17: =BZ17*EXP($B$10-0.5*M$7^2+M$7*AT17) -> 167025.14 | CB17: =(AU17*DCF!C$10-DCF!C$5*MAX(AU17*DCF!C$10,0)-MAX(AU17-Inputs!$B$6,0)/Inputs!$B$10)*DCF!C$6 -> 1040.2728 | CC17: =(AV17*DCF!D$10-DCF!D$5*MAX(AV17*DCF!D$10,0)-MAX(AV17-AU17,0)/Inputs!$B$10)*DCF!D$6 -> 1305.1131 | CD17: =(AW17*DCF!E$10-DCF!E$5*MAX(AW17*DCF!E$10,0)-MAX(AW17-AV17,0)/Inputs!$B$10)*DCF!E$6 -> 1733.4148 | CE17: =(AX17*DCF!F$10-DCF!F$5*MAX(AX17*DCF!F$10,0)-MAX(AX17-AW17,0)/Inputs!$B$10)*DCF!F$6 -> 2249.2319 | CF17: =(AY17*DCF!G$10-DCF!G$5*MAX(AY17*DCF!G$10,0)-MAX(AY17-AX17,0)/Inputs!$B$10)*DCF!G$6 -> 2526.8935 | CG17: =(AZ17*DCF!H$10-DCF!H$5*MAX(AZ17*DCF!H$10,0)-MAX(AZ17-AY17,0)/Inputs!$B$10)*DCF!H$6 -> 3187.4308 | CH17: =(BA17*DCF!I$10-DCF!I$5*MAX(BA17*DCF!I$10,0)-MAX(BA17-AZ17,0)/Inputs!$B$10)*DCF!I$6 -> 3212.8454 | CI17: =(BB17*DCF!J$10-DCF!J$5*MAX(BB17*DCF!J$10,0)-MAX(BB17-BA17,0)/Inputs!$B$10)*DCF!J$6 -> 3931.5985 | CJ17: =(BC17*DCF!K$10-DCF!K$5*MAX(BC17*DCF!K$10,0)-MAX(BC17-BB17,0)/Inputs!$B$10)*DCF!K$6 -> 4550.5395 | ... CL17: =(BE17*DCF!M$10-DCF!M$5*MAX(BE17*DCF!M$10,0)-MAX(BE17-BD17,0)/Inputs!$B$10)*DCF!M$6 -> 4363.9251 | CM17: =(BF17*DCF!C$28-DCF!C$5*MAX(BF17*DCF!C$28,0)-MAX(BF17-Inputs!$B$13,0)/Inputs!$B$17)*DCF!C$6 -> 3903.7952 | CN17: =(BG17*DCF!D$28-DCF!D$5*MAX(BG17*DCF!D$28,0)-MAX(BG17-BF17,0)/Inputs!$B$17)*DCF!D$6 -> 5376.4234 | CO17: =(BH17*DCF!E$28-DCF!E$5*MAX(BH17*DCF!E$28,0)-MAX(BH17-BG17,0)/Inputs!$B$17)*DCF!E$6 -> 6510.2918 | CP17: =(BI17*DCF!F$28-DCF!F$5*MAX(BI17*DCF!F$28,0)-MAX(BI17-BH17,0)/Inputs!$B$17)*DCF!F$6 -> 7533.0362 | CQ17: =(BJ17*DCF!G$28-DCF!G$5*MAX(BJ17*DCF!G$28,0)-MAX(BJ17-BI17,0)/Inputs!$B$17)*DCF!G$6 -> 7943.0112 | CR17: =(BK17*DCF!H$28-DCF!H$5*MAX(BK17*DCF!H$28,0)-MAX(BK17-BJ17,0)/Inputs!$B$17)*DCF!H$6 -> 9001.2082 | CS17: =(BL17*DCF!I$28-DCF!I$5*MAX(BL17*DCF!I$28,0)-MAX(BL17-BK17,0)/Inputs!$B$17)*DCF!I$6 -> 11169.435 | CT17: =(BM17*DCF!J$28-DCF!J$5*MAX(BM17*DCF!J$28,0)-MAX(BM17-BL17,0)/Inputs!$B$17)*DCF!J$6 -> 14282.037 | CU17: =(BN17*DCF!K$28-DCF!K$5*MAX(BN17*DCF!K$28,0)-MAX(BN17-BM17,0)/Inputs!$B$17)*DCF!K$6 -> 15560.528 | ... CW17: =(BP17*DCF!M$28-DCF!M$5*MAX(BP17*DCF!M$28,0)-MAX(BP17-BO17,0)/Inputs!$B$17)*DCF!M$6 -> 20069.326 | CX17: =(BQ17*DCF!C$46-DCF!C$5*MAX(BQ17*DCF!C$46,0)-MAX(BQ17-Inputs!$B$20,0)/Inputs!$B$24)*DCF!C$6 -> -1200.9711 | CY17: =(BR17*DCF!D$46-DCF!D$5*MAX(BR17*DCF!D$46,0)-MAX(BR17-BQ17,0)/Inputs!$B$24)*DCF!D$6 -> -1709.63 | CZ17: =(BS17*DCF!E$46-DCF!E$5*MAX(BS17*DCF!E$46,0)-MAX(BS17-BR17,0)/Inputs!$B$24)*DCF!E$6 -> -4165.2267 | DA17: =(BT17*DCF!F$46-DCF!F$5*MAX(BT17*DCF!F$46,0)-MAX(BT17-BS17,0)/Inputs!$B$24)*DCF!F$6 -> -2755.8516 | DB17: =(BU17*DCF!G$46-DCF!G$5*MAX(BU17*DCF!G$46,0)-MAX(BU17-BT17,0)/Inputs!$B$24)*DCF!G$6 -> -3478.1204 | DC17: =(BV17*DCF!H$46-DCF!H$5*MAX(BV17*DCF!H$46,0)-MAX(BV17-BU17,0)/Inputs!$B$24)*DCF!H$6 -> -101.27307 | DD17: =(BW17*DCF!I$46-DCF!I$5*MAX(BW17*DCF!I$46,0)-MAX(BW17-BV17,0)/Inputs!$B$24)*DCF!I$6 -> -9163.8089 | DE17: =(BX17*DCF!J$46-DCF!J$5*MAX(BX17*DCF!J$46,0)-MAX(BX17-BW17,0)/Inputs!$B$24)*DCF!J$6 -> -4569.4599 | DF17: =(BY17*DCF!K$46-DCF!K$5*MAX(BY17*DCF!K$46,0)-MAX(BY17-BX17,0)/Inputs!$B$24)*DCF!K$6 -> -619.05887 | ... DH17: =(CA17*DCF!M$46-DCF!M$5*MAX(CA17*DCF!M$46,0)-MAX(CA17-BZ17,0)/Inputs!$B$24)*DCF!M$6 -> 6109.8449 | DI17: =SUM(CB17:CL17)+BE17*DCF!M$10*(1+Inputs!$B$30)*(1-Inputs!$B$33)*(1-Inputs!$B$30/Inputs!$B$31)/(Inputs!$B$29-Inputs!$B$30)*DCF!M$6 -> 124819.9 | DJ17: =SUM(CM17:CW17)+BP17*DCF!M$28*(1+Inputs!$B$30)*(1-Inputs!$B$33)*(1-Inputs!$B$30/Inputs!$B$31)/(Inputs!$B$29-Inputs!$B$30)*DCF!M$6 -> 585275.58 | DK17: =SUM(CX17:DH17)+CA17*DCF!M$46*(1+Inputs!$B$30)*(1-Inputs!$B$33)*(1-Inputs!$B$30/Inputs!$B$31)/(Inputs!$B$29-Inputs!$B$30)*DCF!M$6 -> 244033.76 | DM17: =DI17+DJ17+DK17+Inputs!$B$34+Inputs!$B$36-Inputs!$B$35 -> 1030980.2
A18: 5 | C18: =_xlfn.NORM.S.INV(RAND()) -> 0.052337302 | D18: =_xlfn.NORM.S.INV(RAND()) -> -0.12520591 | E18: =_xlfn.NORM.S.INV(RAND()) -> 0.73550444 | F18: =_xlfn.NORM.S.INV(RAND()) -> -1.3482596 | G18: =_xlfn.NORM.S.INV(RAND()) -> -0.34703253 | H18: =_xlfn.NORM.S.INV(RAND()) -> -0.22803047 | I18: =_xlfn.NORM.S.INV(RAND()) -> -1.12409 | J18: =_xlfn.NORM.S.INV(RAND()) -> -0.055244432 | ... M18: =_xlfn.NORM.S.INV(RAND()) -> 0.8556151 | N18: =SQRT(Inputs!$B$38)*C18+SQRT(1-Inputs!$B$38)*_xlfn.NORM.S.INV(RAND()) -> -0.8658438 | O18: =SQRT(Inputs!$B$38)*D18+SQRT(1-Inputs!$B$38)*_xlfn.NORM.S.INV(RAND()) -> -0.49140668 | P18: =SQRT(Inputs!$B$38)*E18+SQRT(1-Inputs!$B$38)*_xlfn.NORM.S.INV(RAND()) -> 0.60548972 | Q18: =SQRT(Inputs!$B$38)*F18+SQRT(1-Inputs!$B$38)*_xlfn.NORM.S.INV(RAND()) -> -0.27442389 | R18: =SQRT(Inputs!$B$38)*G18+SQRT(1-Inputs!$B$38)*_xlfn.NORM.S.INV(RAND()) -> 0.26555296 | S18: =SQRT(Inputs!$B$38)*H18+SQRT(1-Inputs!$B$38)*_xlfn.NORM.S.INV(RAND()) -> 0.48964042 | T18: =SQRT(Inputs!$B$38)*I18+SQRT(1-Inputs!$B$38)*_xlfn.NORM.S.INV(RAND()) -> -1.0762882 | U18: =SQRT(Inputs!$B$38)*J18+SQRT(1-Inputs!$B$38)*_xlfn.NORM.S.INV(RAND()) -> -1.1665326 | ... X18: =SQRT(Inputs!$B$38)*M18+SQRT(1-Inputs!$B$38)*_xlfn.NORM.S.INV(RAND()) -> -0.2488233 | Y18: =SQRT(Inputs!$B$38)*C18+SQRT(1-Inputs!$B$38)*_xlfn.NORM.S.INV(RAND()) -> 0.16334996 | Z18: =SQRT(Inputs!$B$38)*D18+SQRT(1-Inputs!$B$38)*_xlfn.NORM.S.INV(RAND()) -> -0.36706205 | AA18: =SQRT(Inputs!$B$38)*E18+SQRT(1-Inputs!$B$38)*_xlfn.NORM.S.INV(RAND()) -> 0.89205241 | AB18: =SQRT(Inputs!$B$38)*F18+SQRT(1-Inputs!$B$38)*_xlfn.NORM.S.INV(RAND()) -> -0.51625931 | AC18: =SQRT(Inputs!$B$38)*G18+SQRT(1-Inputs!$B$38)*_xlfn.NORM.S.INV(RAND()) -> -0.49821026 | AD18: =SQRT(Inputs!$B$38)*H18+SQRT(1-Inputs!$B$38)*_xlfn.NORM.S.INV(RAND()) -> -2.6246422 | AE18: =SQRT(Inputs!$B$38)*I18+SQRT(1-Inputs!$B$38)*_xlfn.NORM.S.INV(RAND()) -> -2.3071055 | AF18: =SQRT(Inputs!$B$38)*J18+SQRT(1-Inputs!$B$38)*_xlfn.NORM.S.INV(RAND()) -> 0.054976008 | ... AI18: =SQRT(Inputs!$B$38)*M18+SQRT(1-Inputs!$B$38)*_xlfn.NORM.S.INV(RAND()) -> 0.6421548 | AJ18: =SQRT(Inputs!$B$38)*C18+SQRT(1-Inputs!$B$38)*_xlfn.NORM.S.INV(RAND()) -> -0.48764185 | AK18: =SQRT(Inputs!$B$38)*D18+SQRT(1-Inputs!$B$38)*_xlfn.NORM.S.INV(RAND()) -> -0.22752891 | AL18: =SQRT(Inputs!$B$38)*E18+SQRT(1-Inputs!$B$38)*_xlfn.NORM.S.INV(RAND()) -> 0.77197654 | AM18: =SQRT(Inputs!$B$38)*F18+SQRT(1-Inputs!$B$38)*_xlfn.NORM.S.INV(RAND()) -> -0.33479503 | AN18: =SQRT(Inputs!$B$38)*G18+SQRT(1-Inputs!$B$38)*_xlfn.NORM.S.INV(RAND()) -> -0.11726011 | AO18: =SQRT(Inputs!$B$38)*H18+SQRT(1-Inputs!$B$38)*_xlfn.NORM.S.INV(RAND()) -> -0.32194154 | AP18: =SQRT(Inputs!$B$38)*I18+SQRT(1-Inputs!$B$38)*_xlfn.NORM.S.INV(RAND()) -> -1.7045211 | AQ18: =SQRT(Inputs!$B$38)*J18+SQRT(1-Inputs!$B$38)*_xlfn.NORM.S.INV(RAND()) -> -1.0408346 | ... AT18: =SQRT(Inputs!$B$38)*M18+SQRT(1-Inputs!$B$38)*_xlfn.NORM.S.INV(RAND()) -> 2.4710414 | AU18: =Inputs!$B$6*EXP($B$8-0.5*C$5^2+C$5*N18) -> 4313.2873 | AV18: =AU18*EXP($B$8-0.5*D$5^2+D$5*O18) -> 4884.3231 | AW18: =AV18*EXP($B$8-0.5*E$5^2+E$5*P18) -> 6462.3659 | AX18: =AW18*EXP($B$8-0.5*F$5^2+F$5*Q18) -> 7623.9827 | AY18: =AX18*EXP($B$8-0.5*G$5^2+G$5*R18) -> 9610.773 | AZ18: =AY18*EXP($B$8-0.5*H$5^2+H$5*S18) -> 12405.408 | BA18: =AZ18*EXP($B$8-0.5*I$5^2+I$5*T18) -> 13563.791 | BB18: =BA18*EXP($B$8-0.5*J$5^2+J$5*U18) -> 14774.495 | BC18: =BB18*EXP($B$8-0.5*K$5^2+K$5*V18) -> 18322.804 | ... BE18: =BD18*EXP($B$8-0.5*M$5^2+M$5*X18) -> 27872.62 | BF18: =Inputs!$B$13*EXP($B$9-0.5*C$6^2+C$6*Y18) -> 14286.252 | BG18: =BF18*EXP($B$9-0.5*D$6^2+D$6*Z18) -> 16295.342 | BH18: =BG18*EXP($B$9-0.5*E$6^2+E$6*AA18) -> 23084.724 | BI18: =BH18*EXP($B$9-0.5*F$6^2+F$6*AB18) -> 26100.535 | BJ18: =BI18*EXP($B$9-0.5*G$6^2+G$6*AC18) -> 29780.229 | BK18: =BJ18*EXP($B$9-0.5*H$6^2+H$6*AD18) -> 25568.022 | BL18: =BK18*EXP($B$9-0.5*I$6^2+I$6*AE18) -> 23290.756 | BM18: =BL18*EXP($B$9-0.5*J$6^2+J$6*AF18) -> 28825.56 | BN18: =BM18*EXP($B$9-0.5*K$6^2+K$6*AG18) -> 37106.68 | ... BP18: =BO18*EXP($B$9-0.5*M$6^2+M$6*AI18) -> 53736.4 | BQ18: =Inputs!$B$20*EXP($B$10-0.5*C$7^2+C$7*AJ18) -> 3608.2226 | BR18: =BQ18*EXP($B$10-0.5*D$7^2+D$7*AK18) -> 4554.6021 | BS18: =BR18*EXP($B$10-0.5*E$7^2+E$7*AL18) -> 7785.1601 | BT18: =BS18*EXP($B$10-0.5*F$7^2+F$7*AM18) -> 9831.5125 | BU18: =BT18*EXP($B$10-0.5*G$7^2+G$7*AN18) -> 13244.134 | BV18: =BU18*EXP($B$10-0.5*H$7^2+H$7*AO18) -> 17137.209 | BW18: =BV18*EXP($B$10-0.5*I$7^2+I$7*AP18) -> 16671.553 | BX18: =BW18*EXP($B$10-0.5*J$7^2+J$7*AQ18) -> 18926.415 | BY18: =BX18*EXP($B$10-0.5*K$7^2+K$7*AR18) -> 34432.537 | ... CA18: =BZ18*EXP($B$10-0.5*M$7^2+M$7*AT18) -> 103668.47 | CB18: =(AU18*DCF!C$10-DCF!C$5*MAX(AU18*DCF!C$10,0)-MAX(AU18-Inputs!$B$6,0)/Inputs!$B$10)*DCF!C$6 -> 1047.7014 | CC18: =(AV18*DCF!D$10-DCF!D$5*MAX(AV18*DCF!D$10,0)-MAX(AV18-AU18,0)/Inputs!$B$10)*DCF!D$6 -> 1051.2885 | CD18: =(AW18*DCF!E$10-DCF!E$5*MAX(AW18*DCF!E$10,0)-MAX(AW18-AV18,0)/Inputs!$B$10)*DCF!E$6 -> 1136.6168 | CE18: =(AX18*DCF!F$10-DCF!F$5*MAX(AX18*DCF!F$10,0)-MAX(AX18-AW18,0)/Inputs!$B$10)*DCF!F$6 -> 1422.5996 | CF18: =(AY18*DCF!G$10-DCF!G$5*MAX(AY18*DCF!G$10,0)-MAX(AY18-AX18,0)/Inputs!$B$10)*DCF!G$6 -> 1598.3068 | CG18: =(AZ18*DCF!H$10-DCF!H$5*MAX(AZ18*DCF!H$10,0)-MAX(AZ18-AY18,0)/Inputs!$B$10)*DCF!H$6 -> 1912.2813 | CH18: =(BA18*DCF!I$10-DCF!I$5*MAX(BA18*DCF!I$10,0)-MAX(BA18-AZ18,0)/Inputs!$B$10)*DCF!I$6 -> 2287.5944 | CI18: =(BB18*DCF!J$10-DCF!J$5*MAX(BB18*DCF!J$10,0)-MAX(BB18-BA18,0)/Inputs!$B$10)*DCF!J$6 -> 2351.8753 | CJ18: =(BC18*DCF!K$10-DCF!K$5*MAX(BC18*DCF!K$10,0)-MAX(BC18-BB18,0)/Inputs!$B$10)*DCF!K$6 -> 2452.968 | ... CL18: =(BE18*DCF!M$10-DCF!M$5*MAX(BE18*DCF!M$10,0)-MAX(BE18-BD18,0)/Inputs!$B$10)*DCF!M$6 -> 3383.0729 | CM18: =(BF18*DCF!C$28-DCF!C$5*MAX(BF18*DCF!C$28,0)-MAX(BF18-Inputs!$B$13,0)/Inputs!$B$17)*DCF!C$6 -> 3690.4972 | CN18: =(BG18*DCF!D$28-DCF!D$5*MAX(BG18*DCF!D$28,0)-MAX(BG18-BF18,0)/Inputs!$B$17)*DCF!D$6 -> 4370.7231 | CO18: =(BH18*DCF!E$28-DCF!E$5*MAX(BH18*DCF!E$28,0)-MAX(BH18-BG18,0)/Inputs!$B$17)*DCF!E$6 -> 5199.9111 | CP18: =(BI18*DCF!F$28-DCF!F$5*MAX(BI18*DCF!F$28,0)-MAX(BI18-BH18,0)/Inputs!$B$17)*DCF!F$6 -> 6536.5317 | CQ18: =(BJ18*DCF!G$28-DCF!G$5*MAX(BJ18*DCF!G$28,0)-MAX(BJ18-BI18,0)/Inputs!$B$17)*DCF!G$6 -> 7107.8182 | CR18: =(BK18*DCF!H$28-DCF!H$5*MAX(BK18*DCF!H$28,0)-MAX(BK18-BJ18,0)/Inputs!$B$17)*DCF!H$6 -> 6323.2539 | CS18: =(BL18*DCF!I$28-DCF!I$5*MAX(BL18*DCF!I$28,0)-MAX(BL18-BK18,0)/Inputs!$B$17)*DCF!I$6 -> 5476.8919 | CT18: =(BM18*DCF!J$28-DCF!J$5*MAX(BM18*DCF!J$28,0)-MAX(BM18-BL18,0)/Inputs!$B$17)*DCF!J$6 -> 5696.623 | CU18: =(BN18*DCF!K$28-DCF!K$5*MAX(BN18*DCF!K$28,0)-MAX(BN18-BM18,0)/Inputs!$B$17)*DCF!K$6 -> 6821.9817 | ... CW18: =(BP18*DCF!M$28-DCF!M$5*MAX(BP18*DCF!M$28,0)-MAX(BP18-BO18,0)/Inputs!$B$17)*DCF!M$6 -> 8736.9625 | CX18: =(BQ18*DCF!C$46-DCF!C$5*MAX(BQ18*DCF!C$46,0)-MAX(BQ18-Inputs!$B$20,0)/Inputs!$B$24)*DCF!C$6 -> -1021.4013 | CY18: =(BR18*DCF!D$46-DCF!D$5*MAX(BR18*DCF!D$46,0)-MAX(BR18-BQ18,0)/Inputs!$B$24)*DCF!D$6 -> -1181.1767 | CZ18: =(BS18*DCF!E$46-DCF!E$5*MAX(BS18*DCF!E$46,0)-MAX(BS18-BR18,0)/Inputs!$B$24)*DCF!E$6 -> -2194.0058 | DA18: =(BT18*DCF!F$46-DCF!F$5*MAX(BT18*DCF!F$46,0)-MAX(BT18-BS18,0)/Inputs!$B$24)*DCF!F$6 -> -1461.1345 | DB18: =(BU18*DCF!G$46-DCF!G$5*MAX(BU18*DCF!G$46,0)-MAX(BU18-BT18,0)/Inputs!$B$24)*DCF!G$6 -> -1593.4449 | DC18: =(BV18*DCF!H$46-DCF!H$5*MAX(BV18*DCF!H$46,0)-MAX(BV18-BU18,0)/Inputs!$B$24)*DCF!H$6 -> -1209.7494 | DD18: =(BW18*DCF!I$46-DCF!I$5*MAX(BW18*DCF!I$46,0)-MAX(BW18-BV18,0)/Inputs!$B$24)*DCF!I$6 -> 385.03597 | DE18: =(BX18*DCF!J$46-DCF!J$5*MAX(BX18*DCF!J$46,0)-MAX(BX18-BW18,0)/Inputs!$B$24)*DCF!J$6 -> 195.95826 | DF18: =(BY18*DCF!K$46-DCF!K$5*MAX(BY18*DCF!K$46,0)-MAX(BY18-BX18,0)/Inputs!$B$24)*DCF!K$6 -> -1831.6857 | ... DH18: =(CA18*DCF!M$46-DCF!M$5*MAX(CA18*DCF!M$46,0)-MAX(CA18-BZ18,0)/Inputs!$B$24)*DCF!M$6 -> -3599.8513 | DI18: =SUM(CB18:CL18)+BE18*DCF!M$10*(1+Inputs!$B$30)*(1-Inputs!$B$33)*(1-Inputs!$B$30/Inputs!$B$31)/(Inputs!$B$29-Inputs!$B$30)*DCF!M$6 -> 99083.931 | DJ18: =SUM(CM18:CW18)+BP18*DCF!M$28*(1+Inputs!$B$30)*(1-Inputs!$B$33)*(1-Inputs!$B$30/Inputs!$B$31)/(Inputs!$B$29-Inputs!$B$30)*DCF!M$6 -> 267064.92 | DK18: =SUM(CX18:DH18)+CA18*DCF!M$46*(1+Inputs!$B$30)*(1-Inputs!$B$33)*(1-Inputs!$B$30/Inputs!$B$31)/(Inputs!$B$29-Inputs!$B$30)*DCF!M$6 -> 147087.01 | DM18: =DI18+DJ18+DK18+Inputs!$B$34+Inputs!$B$36-Inputs!$B$35 -> 590086.86
A19: 6 | C19: =_xlfn.NORM.S.INV(RAND()) -> 0.64287601 | D19: =_xlfn.NORM.S.INV(RAND()) -> -2.1693023 | E19: =_xlfn.NORM.S.INV(RAND()) -> 0.55073369 | F19: =_xlfn.NORM.S.INV(RAND()) -> 0.20727968 | G19: =_xlfn.NORM.S.INV(RAND()) -> -0.25122523 | H19: =_xlfn.NORM.S.INV(RAND()) -> -1.136236 | I19: =_xlfn.NORM.S.INV(RAND()) -> 0.60064264 | J19: =_xlfn.NORM.S.INV(RAND()) -> 0.64621625 | ... M19: =_xlfn.NORM.S.INV(RAND()) -> -0.17000524 | N19: =SQRT(Inputs!$B$38)*C19+SQRT(1-Inputs!$B$38)*_xlfn.NORM.S.INV(RAND()) -> -2.4461804 | O19: =SQRT(Inputs!$B$38)*D19+SQRT(1-Inputs!$B$38)*_xlfn.NORM.S.INV(RAND()) -> -1.8431793 | P19: =SQRT(Inputs!$B$38)*E19+SQRT(1-Inputs!$B$38)*_xlfn.NORM.S.INV(RAND()) -> -0.90287652 | Q19: =SQRT(Inputs!$B$38)*F19+SQRT(1-Inputs!$B$38)*_xlfn.NORM.S.INV(RAND()) -> -0.68026045 | R19: =SQRT(Inputs!$B$38)*G19+SQRT(1-Inputs!$B$38)*_xlfn.NORM.S.INV(RAND()) -> -0.52044541 | S19: =SQRT(Inputs!$B$38)*H19+SQRT(1-Inputs!$B$38)*_xlfn.NORM.S.INV(RAND()) -> -0.62266944 | T19: =SQRT(Inputs!$B$38)*I19+SQRT(1-Inputs!$B$38)*_xlfn.NORM.S.INV(RAND()) -> -0.28059969 | U19: =SQRT(Inputs!$B$38)*J19+SQRT(1-Inputs!$B$38)*_xlfn.NORM.S.INV(RAND()) -> 0.22289975 | ... X19: =SQRT(Inputs!$B$38)*M19+SQRT(1-Inputs!$B$38)*_xlfn.NORM.S.INV(RAND()) -> -0.93855534 | Y19: =SQRT(Inputs!$B$38)*C19+SQRT(1-Inputs!$B$38)*_xlfn.NORM.S.INV(RAND()) -> 1.3081456 | Z19: =SQRT(Inputs!$B$38)*D19+SQRT(1-Inputs!$B$38)*_xlfn.NORM.S.INV(RAND()) -> -0.5247086 | AA19: =SQRT(Inputs!$B$38)*E19+SQRT(1-Inputs!$B$38)*_xlfn.NORM.S.INV(RAND()) -> 0.40295995 | AB19: =SQRT(Inputs!$B$38)*F19+SQRT(1-Inputs!$B$38)*_xlfn.NORM.S.INV(RAND()) -> -0.36944195 | AC19: =SQRT(Inputs!$B$38)*G19+SQRT(1-Inputs!$B$38)*_xlfn.NORM.S.INV(RAND()) -> 1.6566697 | AD19: =SQRT(Inputs!$B$38)*H19+SQRT(1-Inputs!$B$38)*_xlfn.NORM.S.INV(RAND()) -> -0.60240874 | AE19: =SQRT(Inputs!$B$38)*I19+SQRT(1-Inputs!$B$38)*_xlfn.NORM.S.INV(RAND()) -> 1.2647839 | AF19: =SQRT(Inputs!$B$38)*J19+SQRT(1-Inputs!$B$38)*_xlfn.NORM.S.INV(RAND()) -> 1.2675929 | ... AI19: =SQRT(Inputs!$B$38)*M19+SQRT(1-Inputs!$B$38)*_xlfn.NORM.S.INV(RAND()) -> 0.062926386 | AJ19: =SQRT(Inputs!$B$38)*C19+SQRT(1-Inputs!$B$38)*_xlfn.NORM.S.INV(RAND()) -> -0.016633039 | AK19: =SQRT(Inputs!$B$38)*D19+SQRT(1-Inputs!$B$38)*_xlfn.NORM.S.INV(RAND()) -> -2.5767438 | AL19: =SQRT(Inputs!$B$38)*E19+SQRT(1-Inputs!$B$38)*_xlfn.NORM.S.INV(RAND()) -> 1.1326143 | AM19: =SQRT(Inputs!$B$38)*F19+SQRT(1-Inputs!$B$38)*_xlfn.NORM.S.INV(RAND()) -> -0.044016976 | AN19: =SQRT(Inputs!$B$38)*G19+SQRT(1-Inputs!$B$38)*_xlfn.NORM.S.INV(RAND()) -> -0.059961925 | AO19: =SQRT(Inputs!$B$38)*H19+SQRT(1-Inputs!$B$38)*_xlfn.NORM.S.INV(RAND()) -> -0.72919108 | AP19: =SQRT(Inputs!$B$38)*I19+SQRT(1-Inputs!$B$38)*_xlfn.NORM.S.INV(RAND()) -> 1.5095747 | AQ19: =SQRT(Inputs!$B$38)*J19+SQRT(1-Inputs!$B$38)*_xlfn.NORM.S.INV(RAND()) -> 0.88914926 | ... AT19: =SQRT(Inputs!$B$38)*M19+SQRT(1-Inputs!$B$38)*_xlfn.NORM.S.INV(RAND()) -> -1.1864166 | AU19: =Inputs!$B$6*EXP($B$8-0.5*C$5^2+C$5*N19) -> 3339.7181 | AV19: =AU19*EXP($B$8-0.5*D$5^2+D$5*O19) -> 3100.1885 | AW19: =AV19*EXP($B$8-0.5*E$5^2+E$5*P19) -> 3346.7091 | AX19: =AW19*EXP($B$8-0.5*F$5^2+F$5*Q19) -> 3753.0865 | AY19: =AX19*EXP($B$8-0.5*G$5^2+G$5*R19) -> 4316.1733 | AZ19: =AY19*EXP($B$8-0.5*H$5^2+H$5*S19) -> 4928.9705 | BA19: =AZ19*EXP($B$8-0.5*I$5^2+I$5*T19) -> 5857.2366 | BB19: =BA19*EXP($B$8-0.5*J$5^2+J$5*U19) -> 7332.9895 | BC19: =BB19*EXP($B$8-0.5*K$5^2+K$5*V19) -> 8722.3409 | ... BE19: =BD19*EXP($B$8-0.5*M$5^2+M$5*X19) -> 14426.808 | BF19: =Inputs!$B$13*EXP($B$9-0.5*C$6^2+C$6*Y19) -> 17925.975 | BG19: =BF19*EXP($B$9-0.5*D$6^2+D$6*Z19) -> 19873.494 | BH19: =BG19*EXP($B$9-0.5*E$6^2+E$6*AA19) -> 25960.057 | BI19: =BH19*EXP($B$9-0.5*F$6^2+F$6*AB19) -> 30022.343 | BJ19: =BI19*EXP($B$9-0.5*G$6^2+G$6*AC19) -> 46732.838 | BK19: =BJ19*EXP($B$9-0.5*H$6^2+H$6*AD19) -> 52839.464 | BL19: =BK19*EXP($B$9-0.5*I$6^2+I$6*AE19) -> 76467.013 | BM19: =BL19*EXP($B$9-0.5*J$6^2+J$6*AF19) -> 110024.81 | BN19: =BM19*EXP($B$9-0.5*K$6^2+K$6*AG19) -> 114903.31 | ... BP19: =BO19*EXP($B$9-0.5*M$6^2+M$6*AI19) -> 195007.61 | BQ19: =Inputs!$B$20*EXP($B$10-0.5*C$7^2+C$7*AJ19) -> 4264.2826 | BR19: =BQ19*EXP($B$10-0.5*D$7^2+D$7*AK19) -> 2552.6528 | BS19: =BR19*EXP($B$10-0.5*E$7^2+E$7*AL19) -> 4839.3992 | BT19: =BS19*EXP($B$10-0.5*F$7^2+F$7*AM19) -> 6595.875 | BU19: =BT19*EXP($B$10-0.5*G$7^2+G$7*AN19) -> 9009.4211 | BV19: =BU19*EXP($B$10-0.5*H$7^2+H$7*AO19) -> 10635.691 | BW19: =BV19*EXP($B$10-0.5*I$7^2+I$7*AP19) -> 20428.442 | BX19: =BW19*EXP($B$10-0.5*J$7^2+J$7*AQ19) -> 34147.681 | BY19: =BX19*EXP($B$10-0.5*K$7^2+K$7*AR19) -> 35779.94 | ... CA19: =BZ19*EXP($B$10-0.5*M$7^2+M$7*AT19) -> 71213.083 | CB19: =(AU19*DCF!C$10-DCF!C$5*MAX(AU19*DCF!C$10,0)-MAX(AU19-Inputs!$B$6,0)/Inputs!$B$10)*DCF!C$6 -> 857.67004 | CC19: =(AV19*DCF!D$10-DCF!D$5*MAX(AV19*DCF!D$10,0)-MAX(AV19-AU19,0)/Inputs!$B$10)*DCF!D$6 -> 755.64995 | CD19: =(AW19*DCF!E$10-DCF!E$5*MAX(AW19*DCF!E$10,0)-MAX(AW19-AV19,0)/Inputs!$B$10)*DCF!E$6 -> 717.17522 | CE19: =(AX19*DCF!F$10-DCF!F$5*MAX(AX19*DCF!F$10,0)-MAX(AX19-AW19,0)/Inputs!$B$10)*DCF!F$6 -> 734.73575 | CF19: =(AY19*DCF!G$10-DCF!G$5*MAX(AY19*DCF!G$10,0)-MAX(AY19-AX19,0)/Inputs!$B$10)*DCF!G$6 -> 781.06869 | CG19: =(AZ19*DCF!H$10-DCF!H$5*MAX(AZ19*DCF!H$10,0)-MAX(AZ19-AY19,0)/Inputs!$B$10)*DCF!H$6 -> 848.15003 | CH19: =(BA19*DCF!I$10-DCF!I$5*MAX(BA19*DCF!I$10,0)-MAX(BA19-AZ19,0)/Inputs!$B$10)*DCF!I$6 -> 917.6353 | CI19: =(BB19*DCF!J$10-DCF!J$5*MAX(BB19*DCF!J$10,0)-MAX(BB19-BA19,0)/Inputs!$B$10)*DCF!J$6 -> 1034.732 | CJ19: =(BC19*DCF!K$10-DCF!K$5*MAX(BC19*DCF!K$10,0)-MAX(BC19-BB19,0)/Inputs!$B$10)*DCF!K$6 -> 1209.6688 | ... CL19: =(BE19*DCF!M$10-DCF!M$5*MAX(BE19*DCF!M$10,0)-MAX(BE19-BD19,0)/Inputs!$B$10)*DCF!M$6 -> 1844.351 | CM19: =(BF19*DCF!C$28-DCF!C$5*MAX(BF19*DCF!C$28,0)-MAX(BF19-Inputs!$B$13,0)/Inputs!$B$17)*DCF!C$6 -> 3960.7341 | CN19: =(BG19*DCF!D$28-DCF!D$5*MAX(BG19*DCF!D$28,0)-MAX(BG19-BF19,0)/Inputs!$B$17)*DCF!D$6 -> 5437.7073 | CO19: =(BH19*DCF!E$28-DCF!E$5*MAX(BH19*DCF!E$28,0)-MAX(BH19-BG19,0)/Inputs!$B$17)*DCF!E$6 -> 6152.7726 | CP19: =(BI19*DCF!F$28-DCF!F$5*MAX(BI19*DCF!F$28,0)-MAX(BI19-BH19,0)/Inputs!$B$17)*DCF!F$6 -> 7410.6719 | CQ19: =(BJ19*DCF!G$28-DCF!G$5*MAX(BJ19*DCF!G$28,0)-MAX(BJ19-BI19,0)/Inputs!$B$17)*DCF!G$6 -> 9314.6491 | CR19: =(BK19*DCF!H$28-DCF!H$5*MAX(BK19*DCF!H$28,0)-MAX(BK19-BJ19,0)/Inputs!$B$17)*DCF!H$6 -> 12118.984 | CS19: =(BL19*DCF!I$28-DCF!I$5*MAX(BL19*DCF!I$28,0)-MAX(BL19-BK19,0)/Inputs!$B$17)*DCF!I$6 -> 14590.173 | CT19: =(BM19*DCF!J$28-DCF!J$5*MAX(BM19*DCF!J$28,0)-MAX(BM19-BL19,0)/Inputs!$B$17)*DCF!J$6 -> 20095.176 | CU19: =(BN19*DCF!K$28-DCF!K$5*MAX(BN19*DCF!K$28,0)-MAX(BN19-BM19,0)/Inputs!$B$17)*DCF!K$6 -> 23668.101 | ... CW19: =(BP19*DCF!M$28-DCF!M$5*MAX(BP19*DCF!M$28,0)-MAX(BP19-BO19,0)/Inputs!$B$17)*DCF!M$6 -> 32750.601 | CX19: =(BQ19*DCF!C$46-DCF!C$5*MAX(BQ19*DCF!C$46,0)-MAX(BQ19-Inputs!$B$20,0)/Inputs!$B$24)*DCF!C$6 -> -1475.9464 | CY19: =(BR19*DCF!D$46-DCF!D$5*MAX(BR19*DCF!D$46,0)-MAX(BR19-BQ19,0)/Inputs!$B$24)*DCF!D$6 -> -435.67831 | CZ19: =(BS19*DCF!E$46-DCF!E$5*MAX(BS19*DCF!E$46,0)-MAX(BS19-BR19,0)/Inputs!$B$24)*DCF!E$6 -> -1473.6398 | DA19: =(BT19*DCF!F$46-DCF!F$5*MAX(BT19*DCF!F$46,0)-MAX(BT19-BS19,0)/Inputs!$B$24)*DCF!F$6 -> -1119.9417 | DB19: =(BU19*DCF!G$46-DCF!G$5*MAX(BU19*DCF!G$46,0)-MAX(BU19-BT19,0)/Inputs!$B$24)*DCF!G$6 -> -1114.9283 | DC19: =(BV19*DCF!H$46-DCF!H$5*MAX(BV19*DCF!H$46,0)-MAX(BV19-BU19,0)/Inputs!$B$24)*DCF!H$6 -> -505.35352 | DD19: =(BW19*DCF!I$46-DCF!I$5*MAX(BW19*DCF!I$46,0)-MAX(BW19-BV19,0)/Inputs!$B$24)*DCF!I$6 -> -2339.317 | DE19: =(BX19*DCF!J$46-DCF!J$5*MAX(BX19*DCF!J$46,0)-MAX(BX19-BW19,0)/Inputs!$B$24)*DCF!J$6 -> -2205.7173 | DF19: =(BY19*DCF!K$46-DCF!K$5*MAX(BY19*DCF!K$46,0)-MAX(BY19-BX19,0)/Inputs!$B$24)*DCF!K$6 -> 1644.0094 | ... DH19: =(CA19*DCF!M$46-DCF!M$5*MAX(CA19*DCF!M$46,0)-MAX(CA19-BZ19,0)/Inputs!$B$24)*DCF!M$6 -> 3781.1239 | DI19: =SUM(CB19:CL19)+BE19*DCF!M$10*(1+Inputs!$B$30)*(1-Inputs!$B$33)*(1-Inputs!$B$30/Inputs!$B$31)/(Inputs!$B$29-Inputs!$B$30)*DCF!M$6 -> 51254.529 | DJ19: =SUM(CM19:CW19)+BP19*DCF!M$28*(1+Inputs!$B$30)*(1-Inputs!$B$33)*(1-Inputs!$B$30/Inputs!$B$31)/(Inputs!$B$29-Inputs!$B$30)*DCF!M$6 -> 885699.71 | DK19: =SUM(CX19:DH19)+CA19*DCF!M$46*(1+Inputs!$B$30)*(1-Inputs!$B$33)*(1-Inputs!$B$30/Inputs!$B$31)/(Inputs!$B$29-Inputs!$B$30)*DCF!M$6 -> 103117.07 | DM19: =DI19+DJ19+DK19+Inputs!$B$34+Inputs!$B$36-Inputs!$B$35 -> 1116922.3
A20: 7 | C20: =_xlfn.NORM.S.INV(RAND()) -> 0.25476531 | D20: =_xlfn.NORM.S.INV(RAND()) -> 1.3159 | E20: =_xlfn.NORM.S.INV(RAND()) -> -0.99814153 | F20: =_xlfn.NORM.S.INV(RAND()) -> 0.40655927 | G20: =_xlfn.NORM.S.INV(RAND()) -> -0.69752029 | H20: =_xlfn.NORM.S.INV(RAND()) -> -1.6024878 | I20: =_xlfn.NORM.S.INV(RAND()) -> -0.89132709 | J20: =_xlfn.NORM.S.INV(RAND()) -> -0.54278689 | ... M20: =_xlfn.NORM.S.INV(RAND()) -> 1.519362 | N20: =SQRT(Inputs!$B$38)*C20+SQRT(1-Inputs!$B$38)*_xlfn.NORM.S.INV(RAND()) -> -0.46606735 | O20: =SQRT(Inputs!$B$38)*D20+SQRT(1-Inputs!$B$38)*_xlfn.NORM.S.INV(RAND()) -> 3.1439731 | P20: =SQRT(Inputs!$B$38)*E20+SQRT(1-Inputs!$B$38)*_xlfn.NORM.S.INV(RAND()) -> -1.6959538 | Q20: =SQRT(Inputs!$B$38)*F20+SQRT(1-Inputs!$B$38)*_xlfn.NORM.S.INV(RAND()) -> -0.4988036 | R20: =SQRT(Inputs!$B$38)*G20+SQRT(1-Inputs!$B$38)*_xlfn.NORM.S.INV(RAND()) -> -0.46100153 | S20: =SQRT(Inputs!$B$38)*H20+SQRT(1-Inputs!$B$38)*_xlfn.NORM.S.INV(RAND()) -> -1.0019473 | T20: =SQRT(Inputs!$B$38)*I20+SQRT(1-Inputs!$B$38)*_xlfn.NORM.S.INV(RAND()) -> -1.4925892 | U20: =SQRT(Inputs!$B$38)*J20+SQRT(1-Inputs!$B$38)*_xlfn.NORM.S.INV(RAND()) -> -0.26621828 | ... X20: =SQRT(Inputs!$B$38)*M20+SQRT(1-Inputs!$B$38)*_xlfn.NORM.S.INV(RAND()) -> -0.086460228 | Y20: =SQRT(Inputs!$B$38)*C20+SQRT(1-Inputs!$B$38)*_xlfn.NORM.S.INV(RAND()) -> 0.74636008 | Z20: =SQRT(Inputs!$B$38)*D20+SQRT(1-Inputs!$B$38)*_xlfn.NORM.S.INV(RAND()) -> 2.7900705 | AA20: =SQRT(Inputs!$B$38)*E20+SQRT(1-Inputs!$B$38)*_xlfn.NORM.S.INV(RAND()) -> -0.61069099 | AB20: =SQRT(Inputs!$B$38)*F20+SQRT(1-Inputs!$B$38)*_xlfn.NORM.S.INV(RAND()) -> -0.23142374 | AC20: =SQRT(Inputs!$B$38)*G20+SQRT(1-Inputs!$B$38)*_xlfn.NORM.S.INV(RAND()) -> -0.49965291 | AD20: =SQRT(Inputs!$B$38)*H20+SQRT(1-Inputs!$B$38)*_xlfn.NORM.S.INV(RAND()) -> -0.82767428 | AE20: =SQRT(Inputs!$B$38)*I20+SQRT(1-Inputs!$B$38)*_xlfn.NORM.S.INV(RAND()) -> -0.64210285 | AF20: =SQRT(Inputs!$B$38)*J20+SQRT(1-Inputs!$B$38)*_xlfn.NORM.S.INV(RAND()) -> -0.77675994 | ... AI20: =SQRT(Inputs!$B$38)*M20+SQRT(1-Inputs!$B$38)*_xlfn.NORM.S.INV(RAND()) -> 0.44823606 | AJ20: =SQRT(Inputs!$B$38)*C20+SQRT(1-Inputs!$B$38)*_xlfn.NORM.S.INV(RAND()) -> -0.12994147 | AK20: =SQRT(Inputs!$B$38)*D20+SQRT(1-Inputs!$B$38)*_xlfn.NORM.S.INV(RAND()) -> 1.2362928 | AL20: =SQRT(Inputs!$B$38)*E20+SQRT(1-Inputs!$B$38)*_xlfn.NORM.S.INV(RAND()) -> 0.79583134 | AM20: =SQRT(Inputs!$B$38)*F20+SQRT(1-Inputs!$B$38)*_xlfn.NORM.S.INV(RAND()) -> -0.02276346 | AN20: =SQRT(Inputs!$B$38)*G20+SQRT(1-Inputs!$B$38)*_xlfn.NORM.S.INV(RAND()) -> 0.33498766 | AO20: =SQRT(Inputs!$B$38)*H20+SQRT(1-Inputs!$B$38)*_xlfn.NORM.S.INV(RAND()) -> -0.95521685 | AP20: =SQRT(Inputs!$B$38)*I20+SQRT(1-Inputs!$B$38)*_xlfn.NORM.S.INV(RAND()) -> -0.24870193 | AQ20: =SQRT(Inputs!$B$38)*J20+SQRT(1-Inputs!$B$38)*_xlfn.NORM.S.INV(RAND()) -> -0.7151191 | ... AT20: =SQRT(Inputs!$B$38)*M20+SQRT(1-Inputs!$B$38)*_xlfn.NORM.S.INV(RAND()) -> 0.037460161 | AU20: =Inputs!$B$6*EXP($B$8-0.5*C$5^2+C$5*N20) -> 4601.6429 | AV20: =AU20*EXP($B$8-0.5*D$5^2+D$5*O20) -> 8892.9687 | AW20: =AV20*EXP($B$8-0.5*E$5^2+E$5*P20) -> 8626.2022 | AX20: =AW20*EXP($B$8-0.5*F$5^2+F$5*Q20) -> 9895.4528 | AY20: =AX20*EXP($B$8-0.5*G$5^2+G$5*R20) -> 11459.376 | AZ20: =AY20*EXP($B$8-0.5*H$5^2+H$5*S20) -> 12551.038 | BA20: =AZ20*EXP($B$8-0.5*I$5^2+I$5*T20) -> 13137.946 | BB20: =BA20*EXP($B$8-0.5*J$5^2+J$5*U20) -> 15661.5 | BC20: =BB20*EXP($B$8-0.5*K$5^2+K$5*V20) -> 20871.879 | ... BE20: =BD20*EXP($B$8-0.5*M$5^2+M$5*X20) -> 28220.129 | BF20: =Inputs!$B$13*EXP($B$9-0.5*C$6^2+C$6*Y20) -> 16036.672 | BG20: =BF20*EXP($B$9-0.5*D$6^2+D$6*Z20) -> 32334.27 | BH20: =BG20*EXP($B$9-0.5*E$6^2+E$6*AA20) -> 35700.988 | BI20: =BH20*EXP($B$9-0.5*F$6^2+F$6*AB20) -> 42174.038 | BJ20: =BI20*EXP($B$9-0.5*G$6^2+G$6*AC20) -> 48109.795 | BK20: =BJ20*EXP($B$9-0.5*H$6^2+H$6*AD20) -> 52753.422 | BL20: =BK20*EXP($B$9-0.5*I$6^2+I$6*AE20) -> 59627.279 | BM20: =BL20*EXP($B$9-0.5*J$6^2+J$6*AF20) -> 66552.731 | BN20: =BM20*EXP($B$9-0.5*K$6^2+K$6*AG20) -> 86618.243 | ... BP20: =BO20*EXP($B$9-0.5*M$6^2+M$6*AI20) -> 150372.55 | BQ20: =Inputs!$B$20*EXP($B$10-0.5*C$7^2+C$7*AJ20) -> 4096.3053 | BR20: =BQ20*EXP($B$10-0.5*D$7^2+D$7*AK20) -> 8230.846 | BS20: =BR20*EXP($B$10-0.5*E$7^2+E$7*AL20) -> 14165.666 | BT20: =BS20*EXP($B$10-0.5*F$7^2+F$7*AM20) -> 19415.089 | BU20: =BT20*EXP($B$10-0.5*G$7^2+G$7*AN20) -> 29178.811 | BV20: =BU20*EXP($B$10-0.5*H$7^2+H$7*AO20) -> 32735.632 | BW20: =BV20*EXP($B$10-0.5*I$7^2+I$7*AP20) -> 43338.394 | BX20: =BW20*EXP($B$10-0.5*J$7^2+J$7*AQ20) -> 52519.848 | BY20: =BX20*EXP($B$10-0.5*K$7^2+K$7*AR20) -> 96873.849 | ... CA20: =BZ20*EXP($B$10-0.5*M$7^2+M$7*AT20) -> 191977.67 | CB20: =(AU20*DCF!C$10-DCF!C$5*MAX(AU20*DCF!C$10,0)-MAX(AU20-Inputs!$B$6,0)/Inputs!$B$10)*DCF!C$6 -> 1045.6454 | CC20: =(AV20*DCF!D$10-DCF!D$5*MAX(AV20*DCF!D$10,0)-MAX(AV20-AU20,0)/Inputs!$B$10)*DCF!D$6 -> 1121.2734 | CD20: =(AW20*DCF!E$10-DCF!E$5*MAX(AW20*DCF!E$10,0)-MAX(AW20-AV20,0)/Inputs!$B$10)*DCF!E$6 -> 1991.6528 | CE20: =(AX20*DCF!F$10-DCF!F$5*MAX(AX20*DCF!F$10,0)-MAX(AX20-AW20,0)/Inputs!$B$10)*DCF!F$6 -> 1896.062 | CF20: =(AY20*DCF!G$10-DCF!G$5*MAX(AY20*DCF!G$10,0)-MAX(AY20-AX20,0)/Inputs!$B$10)*DCF!G$6 -> 2060.475 | CG20: =(AZ20*DCF!H$10-DCF!H$5*MAX(AZ20*DCF!H$10,0)-MAX(AZ20-AY20,0)/Inputs!$B$10)*DCF!H$6 -> 2242.9489 | CH20: =(BA20*DCF!I$10-DCF!I$5*MAX(BA20*DCF!I$10,0)-MAX(BA20-AZ20,0)/Inputs!$B$10)*DCF!I$6 -> 2303.55 | CI20: =(BB20*DCF!J$10-DCF!J$5*MAX(BB20*DCF!J$10,0)-MAX(BB20-BA20,0)/Inputs!$B$10)*DCF!J$6 -> 2305.1468 | CJ20: =(BC20*DCF!K$10-DCF!K$5*MAX(BC20*DCF!K$10,0)-MAX(BC20-BB20,0)/Inputs!$B$10)*DCF!K$6 -> 2630.6636 | ... CL20: =(BE20*DCF!M$10-DCF!M$5*MAX(BE20*DCF!M$10,0)-MAX(BE20-BD20,0)/Inputs!$B$10)*DCF!M$6 -> 3383.9415 | CM20: =(BF20*DCF!C$28-DCF!C$5*MAX(BF20*DCF!C$28,0)-MAX(BF20-Inputs!$B$13,0)/Inputs!$B$17)*DCF!C$6 -> 3820.4599 | CN20: =(BG20*DCF!D$28-DCF!D$5*MAX(BG20*DCF!D$28,0)-MAX(BG20-BF20,0)/Inputs!$B$17)*DCF!D$6 -> 6046.1634 | CO20: =(BH20*DCF!E$28-DCF!E$5*MAX(BH20*DCF!E$28,0)-MAX(BH20-BG20,0)/Inputs!$B$17)*DCF!E$6 -> 9447.6217 | CP20: =(BI20*DCF!F$28-DCF!F$5*MAX(BI20*DCF!F$28,0)-MAX(BI20-BH20,0)/Inputs!$B$17)*DCF!F$6 -> 10270.619 | CQ20: =(BJ20*DCF!G$28-DCF!G$5*MAX(BJ20*DCF!G$28,0)-MAX(BJ20-BI20,0)/Inputs!$B$17)*DCF!G$6 -> 11484.116 | CR20: =(BK20*DCF!H$28-DCF!H$5*MAX(BK20*DCF!H$28,0)-MAX(BK20-BJ20,0)/Inputs!$B$17)*DCF!H$6 -> 12325.014 | CS20: =(BL20*DCF!I$28-DCF!I$5*MAX(BL20*DCF!I$28,0)-MAX(BL20-BK20,0)/Inputs!$B$17)*DCF!I$6 -> 13034.927 | CT20: =(BM20*DCF!J$28-DCF!J$5*MAX(BM20*DCF!J$28,0)-MAX(BM20-BL20,0)/Inputs!$B$17)*DCF!J$6 -> 13928.526 | CU20: =(BN20*DCF!K$28-DCF!K$5*MAX(BN20*DCF!K$28,0)-MAX(BN20-BM20,0)/Inputs!$B$17)*DCF!K$6 -> 15834.563 | ... CW20: =(BP20*DCF!M$28-DCF!M$5*MAX(BP20*DCF!M$28,0)-MAX(BP20-BO20,0)/Inputs!$B$17)*DCF!M$6 -> 24712.736 | CX20: =(BQ20*DCF!C$46-DCF!C$5*MAX(BQ20*DCF!C$46,0)-MAX(BQ20-Inputs!$B$20,0)/Inputs!$B$24)*DCF!C$6 -> -1359.5649 | CY20: =(BR20*DCF!D$46-DCF!D$5*MAX(BR20*DCF!D$46,0)-MAX(BR20-BQ20,0)/Inputs!$B$24)*DCF!D$6 -> -3168.9877 | CZ20: =(BS20*DCF!E$46-DCF!E$5*MAX(BS20*DCF!E$46,0)-MAX(BS20-BR20,0)/Inputs!$B$24)*DCF!E$6 -> -4014.4575 | DA20: =(BT20*DCF!F$46-DCF!F$5*MAX(BT20*DCF!F$46,0)-MAX(BT20-BS20,0)/Inputs!$B$24)*DCF!F$6 -> -3325.4102 | DB20: =(BU20*DCF!G$46-DCF!G$5*MAX(BU20*DCF!G$46,0)-MAX(BU20-BT20,0)/Inputs!$B$24)*DCF!G$6 -> -4265.8408 | DC20: =(BV20*DCF!H$46-DCF!H$5*MAX(BV20*DCF!H$46,0)-MAX(BV20-BU20,0)/Inputs!$B$24)*DCF!H$6 -> -1105.2604 | DD20: =(BW20*DCF!I$46-DCF!I$5*MAX(BW20*DCF!I$46,0)-MAX(BW20-BV20,0)/Inputs!$B$24)*DCF!I$6 -> -2042.7256 | DE20: =(BX20*DCF!J$46-DCF!J$5*MAX(BX20*DCF!J$46,0)-MAX(BX20-BW20,0)/Inputs!$B$24)*DCF!J$6 -> -231.70946 | DF20: =(BY20*DCF!K$46-DCF!K$5*MAX(BY20*DCF!K$46,0)-MAX(BY20-BX20,0)/Inputs!$B$24)*DCF!K$6 -> -5331.7915 | ... DH20: =(CA20*DCF!M$46-DCF!M$5*MAX(CA20*DCF!M$46,0)-MAX(CA20-BZ20,0)/Inputs!$B$24)*DCF!M$6 -> 3297.9975 | DI20: =SUM(CB20:CL20)+BE20*DCF!M$10*(1+Inputs!$B$30)*(1-Inputs!$B$33)*(1-Inputs!$B$30/Inputs!$B$31)/(Inputs!$B$29-Inputs!$B$30)*DCF!M$6 -> 102716.55 | DJ20: =SUM(CM20:CW20)+BP20*DCF!M$28*(1+Inputs!$B$30)*(1-Inputs!$B$33)*(1-Inputs!$B$30/Inputs!$B$31)/(Inputs!$B$29-Inputs!$B$30)*DCF!M$6 -> 698720.35 | DK20: =SUM(CX20:DH20)+CA20*DCF!M$46*(1+Inputs!$B$30)*(1-Inputs!$B$33)*(1-Inputs!$B$30/Inputs!$B$31)/(Inputs!$B$29-Inputs!$B$30)*DCF!M$6 -> 275856.6 | DM20: =DI20+DJ20+DK20+Inputs!$B$34+Inputs!$B$36-Inputs!$B$35 -> 1154144.5
A21: 8 | C21: =_xlfn.NORM.S.INV(RAND()) -> 0.18293676 | D21: =_xlfn.NORM.S.INV(RAND()) -> 1.4662989 | E21: =_xlfn.NORM.S.INV(RAND()) -> -0.402364 | F21: =_xlfn.NORM.S.INV(RAND()) -> 0.6209387 | G21: =_xlfn.NORM.S.INV(RAND()) -> -1.1212718 | H21: =_xlfn.NORM.S.INV(RAND()) -> 0.47894463 | I21: =_xlfn.NORM.S.INV(RAND()) -> -0.32913246 | J21: =_xlfn.NORM.S.INV(RAND()) -> 0.62495599 | ... M21: =_xlfn.NORM.S.INV(RAND()) -> 0.23797075 | N21: =SQRT(Inputs!$B$38)*C21+SQRT(1-Inputs!$B$38)*_xlfn.NORM.S.INV(RAND()) -> -0.11820195 | O21: =SQRT(Inputs!$B$38)*D21+SQRT(1-Inputs!$B$38)*_xlfn.NORM.S.INV(RAND()) -> 1.6932722 | P21: =SQRT(Inputs!$B$38)*E21+SQRT(1-Inputs!$B$38)*_xlfn.NORM.S.INV(RAND()) -> -0.33744876 | Q21: =SQRT(Inputs!$B$38)*F21+SQRT(1-Inputs!$B$38)*_xlfn.NORM.S.INV(RAND()) -> 0.51516913 | R21: =SQRT(Inputs!$B$38)*G21+SQRT(1-Inputs!$B$38)*_xlfn.NORM.S.INV(RAND()) -> -0.10815832 | S21: =SQRT(Inputs!$B$38)*H21+SQRT(1-Inputs!$B$38)*_xlfn.NORM.S.INV(RAND()) -> 0.2760397 | T21: =SQRT(Inputs!$B$38)*I21+SQRT(1-Inputs!$B$38)*_xlfn.NORM.S.INV(RAND()) -> -0.43098586 | U21: =SQRT(Inputs!$B$38)*J21+SQRT(1-Inputs!$B$38)*_xlfn.NORM.S.INV(RAND()) -> 1.1048061 | ... X21: =SQRT(Inputs!$B$38)*M21+SQRT(1-Inputs!$B$38)*_xlfn.NORM.S.INV(RAND()) -> -0.17476437 | Y21: =SQRT(Inputs!$B$38)*C21+SQRT(1-Inputs!$B$38)*_xlfn.NORM.S.INV(RAND()) -> 0.41370723 | Z21: =SQRT(Inputs!$B$38)*D21+SQRT(1-Inputs!$B$38)*_xlfn.NORM.S.INV(RAND()) -> 0.83567259 | AA21: =SQRT(Inputs!$B$38)*E21+SQRT(1-Inputs!$B$38)*_xlfn.NORM.S.INV(RAND()) -> -0.93502781 | AB21: =SQRT(Inputs!$B$38)*F21+SQRT(1-Inputs!$B$38)*_xlfn.NORM.S.INV(RAND()) -> 0.30027332 | AC21: =SQRT(Inputs!$B$38)*G21+SQRT(1-Inputs!$B$38)*_xlfn.NORM.S.INV(RAND()) -> -0.77280456 | AD21: =SQRT(Inputs!$B$38)*H21+SQRT(1-Inputs!$B$38)*_xlfn.NORM.S.INV(RAND()) -> 0.15801983 | AE21: =SQRT(Inputs!$B$38)*I21+SQRT(1-Inputs!$B$38)*_xlfn.NORM.S.INV(RAND()) -> -0.28800238 | AF21: =SQRT(Inputs!$B$38)*J21+SQRT(1-Inputs!$B$38)*_xlfn.NORM.S.INV(RAND()) -> 0.31173981 | ... AI21: =SQRT(Inputs!$B$38)*M21+SQRT(1-Inputs!$B$38)*_xlfn.NORM.S.INV(RAND()) -> -0.62947034 | AJ21: =SQRT(Inputs!$B$38)*C21+SQRT(1-Inputs!$B$38)*_xlfn.NORM.S.INV(RAND()) -> 0.12337831 | AK21: =SQRT(Inputs!$B$38)*D21+SQRT(1-Inputs!$B$38)*_xlfn.NORM.S.INV(RAND()) -> 1.3485397 | AL21: =SQRT(Inputs!$B$38)*E21+SQRT(1-Inputs!$B$38)*_xlfn.NORM.S.INV(RAND()) -> -0.58916664 | AM21: =SQRT(Inputs!$B$38)*F21+SQRT(1-Inputs!$B$38)*_xlfn.NORM.S.INV(RAND()) -> 1.2180334 | AN21: =SQRT(Inputs!$B$38)*G21+SQRT(1-Inputs!$B$38)*_xlfn.NORM.S.INV(RAND()) -> -1.5647007 | AO21: =SQRT(Inputs!$B$38)*H21+SQRT(1-Inputs!$B$38)*_xlfn.NORM.S.INV(RAND()) -> 1.8336084 | AP21: =SQRT(Inputs!$B$38)*I21+SQRT(1-Inputs!$B$38)*_xlfn.NORM.S.INV(RAND()) -> -1.4166493 | AQ21: =SQRT(Inputs!$B$38)*J21+SQRT(1-Inputs!$B$38)*_xlfn.NORM.S.INV(RAND()) -> 0.50498118 | ... AT21: =SQRT(Inputs!$B$38)*M21+SQRT(1-Inputs!$B$38)*_xlfn.NORM.S.INV(RAND()) -> 1.4113515 | AU21: =Inputs!$B$6*EXP($B$8-0.5*C$5^2+C$5*N21) -> 4868.1959 | AV21: =AU21*EXP($B$8-0.5*D$5^2+D$5*O21) -> 7600.9368 | AW21: =AV21*EXP($B$8-0.5*E$5^2+E$5*P21) -> 8855.6143 | AX21: =AW21*EXP($B$8-0.5*F$5^2+F$5*Q21) -> 11530.563 | AY21: =AX21*EXP($B$8-0.5*G$5^2+G$5*R21) -> 13914.646 | AZ21: =AY21*EXP($B$8-0.5*H$5^2+H$5*S21) -> 17543.232 | BA21: =AZ21*EXP($B$8-0.5*I$5^2+I$5*T21) -> 20521.573 | BB21: =BA21*EXP($B$8-0.5*J$5^2+J$5*U21) -> 28065.468 | BC21: =BB21*EXP($B$8-0.5*K$5^2+K$5*V21) -> 39161.82 | ... BE21: =BD21*EXP($B$8-0.5*M$5^2+M$5*X21) -> 66747.567 | BF21: =Inputs!$B$13*EXP($B$9-0.5*C$6^2+C$6*Y21) -> 15013.21 | BG21: =BF21*EXP($B$9-0.5*D$6^2+D$6*Z21) -> 21274.976 | BH21: =BG21*EXP($B$9-0.5*E$6^2+E$6*AA21) -> 22259.939 | BI21: =BH21*EXP($B$9-0.5*F$6^2+F$6*AB21) -> 28538.487 | BJ21: =BI21*EXP($B$9-0.5*G$6^2+G$6*AC21) -> 31298.212 | BK21: =BJ21*EXP($B$9-0.5*H$6^2+H$6*AD21) -> 39247.96 | BL21: =BK21*EXP($B$9-0.5*I$6^2+I$6*AE21) -> 46445.169 | BM21: =BL21*EXP($B$9-0.5*J$6^2+J$6*AF21) -> 59345.456 | BN21: =BM21*EXP($B$9-0.5*K$6^2+K$6*AG21) -> 66402.047 | ... BP21: =BO21*EXP($B$9-0.5*M$6^2+M$6*AI21) -> 84397.666 | BQ21: =Inputs!$B$20*EXP($B$10-0.5*C$7^2+C$7*AJ21) -> 4481.3913 | BR21: =BQ21*EXP($B$10-0.5*D$7^2+D$7*AK21) -> 9331.3933 | BS21: =BR21*EXP($B$10-0.5*E$7^2+E$7*AL21) -> 10789.153 | BT21: =BS21*EXP($B$10-0.5*F$7^2+F$7*AM21) -> 20476.372 | BU21: =BT21*EXP($B$10-0.5*G$7^2+G$7*AN21) -> 19433.465 | BV21: =BU21*EXP($B$10-0.5*H$7^2+H$7*AO21) -> 40867.545 | BW21: =BV21*EXP($B$10-0.5*I$7^2+I$7*AP21) -> 42254.71 | BX21: =BW21*EXP($B$10-0.5*J$7^2+J$7*AQ21) -> 65396.36 | BY21: =BX21*EXP($B$10-0.5*K$7^2+K$7*AR21) -> 101949.56 | ... CA21: =BZ21*EXP($B$10-0.5*M$7^2+M$7*AT21) -> 383735.23 | CB21: =(AU21*DCF!C$10-DCF!C$5*MAX(AU21*DCF!C$10,0)-MAX(AU21-Inputs!$B$6,0)/Inputs!$B$10)*DCF!C$6 -> 1043.7449 | CC21: =(AV21*DCF!D$10-DCF!D$5*MAX(AV21*DCF!D$10,0)-MAX(AV21-AU21,0)/Inputs!$B$10)*DCF!D$6 -> 1186.3695 | CD21: =(AW21*DCF!E$10-DCF!E$5*MAX(AW21*DCF!E$10,0)-MAX(AW21-AV21,0)/Inputs!$B$10)*DCF!E$6 -> 1762.015 | CE21: =(AX21*DCF!F$10-DCF!F$5*MAX(AX21*DCF!F$10,0)-MAX(AX21-AW21,0)/Inputs!$B$10)*DCF!F$6 -> 1960.513 | CF21: =(AY21*DCF!G$10-DCF!G$5*MAX(AY21*DCF!G$10,0)-MAX(AY21-AX21,0)/Inputs!$B$10)*DCF!G$6 -> 2408.7097 | CG21: =(AZ21*DCF!H$10-DCF!H$5*MAX(AZ21*DCF!H$10,0)-MAX(AZ21-AY21,0)/Inputs!$B$10)*DCF!H$6 -> 2761.7106 | CH21: =(BA21*DCF!I$10-DCF!I$5*MAX(BA21*DCF!I$10,0)-MAX(BA21-AZ21,0)/Inputs!$B$10)*DCF!I$6 -> 3259.9905 | CI21: =(BB21*DCF!J$10-DCF!J$5*MAX(BB21*DCF!J$10,0)-MAX(BB21-BA21,0)/Inputs!$B$10)*DCF!J$6 -> 3672.9464 | CJ21: =(BC21*DCF!K$10-DCF!K$5*MAX(BC21*DCF!K$10,0)-MAX(BC21-BB21,0)/Inputs!$B$10)*DCF!K$6 -> 4751.1037 | ... CL21: =(BE21*DCF!M$10-DCF!M$5*MAX(BE21*DCF!M$10,0)-MAX(BE21-BD21,0)/Inputs!$B$10)*DCF!M$6 -> 8056.8186 | CM21: =(BF21*DCF!C$28-DCF!C$5*MAX(BF21*DCF!C$28,0)-MAX(BF21-Inputs!$B$13,0)/Inputs!$B$17)*DCF!C$6 -> 3744.4713 | CN21: =(BG21*DCF!D$28-DCF!D$5*MAX(BG21*DCF!D$28,0)-MAX(BG21-BF21,0)/Inputs!$B$17)*DCF!D$6 -> 4930.0492 | CO21: =(BH21*DCF!E$28-DCF!E$5*MAX(BH21*DCF!E$28,0)-MAX(BH21-BG21,0)/Inputs!$B$17)*DCF!E$6 -> 6110.2884 | CP21: =(BI21*DCF!F$28-DCF!F$5*MAX(BI21*DCF!F$28,0)-MAX(BI21-BH21,0)/Inputs!$B$17)*DCF!F$6 -> 6604.3385 | CQ21: =(BJ21*DCF!G$28-DCF!G$5*MAX(BJ21*DCF!G$28,0)-MAX(BJ21-BI21,0)/Inputs!$B$17)*DCF!G$6 -> 7656.4 | CR21: =(BK21*DCF!H$28-DCF!H$5*MAX(BK21*DCF!H$28,0)-MAX(BK21-BJ21,0)/Inputs!$B$17)*DCF!H$6 -> 8471.2858 | CS21: =(BL21*DCF!I$28-DCF!I$5*MAX(BL21*DCF!I$28,0)-MAX(BL21-BK21,0)/Inputs!$B$17)*DCF!I$6 -> 9888.7025 | CT21: =(BM21*DCF!J$28-DCF!J$5*MAX(BM21*DCF!J$28,0)-MAX(BM21-BL21,0)/Inputs!$B$17)*DCF!J$6 -> 11528.491 | CU21: =(BN21*DCF!K$28-DCF!K$5*MAX(BN21*DCF!K$28,0)-MAX(BN21-BM21,0)/Inputs!$B$17)*DCF!K$6 -> 13158.661 | ... CW21: =(BP21*DCF!M$28-DCF!M$5*MAX(BP21*DCF!M$28,0)-MAX(BP21-BO21,0)/Inputs!$B$17)*DCF!M$6 -> 14754.941 | CX21: =(BQ21*DCF!C$46-DCF!C$5*MAX(BQ21*DCF!C$46,0)-MAX(BQ21-Inputs!$B$20,0)/Inputs!$B$24)*DCF!C$6 -> -1626.3681 | CY21: =(BR21*DCF!D$46-DCF!D$5*MAX(BR21*DCF!D$46,0)-MAX(BR21-BQ21,0)/Inputs!$B$24)*DCF!D$6 -> -3662.1068 | CZ21: =(BS21*DCF!E$46-DCF!E$5*MAX(BS21*DCF!E$46,0)-MAX(BS21-BR21,0)/Inputs!$B$24)*DCF!E$6 -> -1850.4448 | DA21: =(BT21*DCF!F$46-DCF!F$5*MAX(BT21*DCF!F$46,0)-MAX(BT21-BS21,0)/Inputs!$B$24)*DCF!F$6 -> -5018.6416 | DB21: =(BU21*DCF!G$46-DCF!G$5*MAX(BU21*DCF!G$46,0)-MAX(BU21-BT21,0)/Inputs!$B$24)*DCF!G$6 -> -653.70336 | DC21: =(BV21*DCF!H$46-DCF!H$5*MAX(BV21*DCF!H$46,0)-MAX(BV21-BU21,0)/Inputs!$B$24)*DCF!H$6 -> -6660.5091 | DD21: =(BW21*DCF!I$46-DCF!I$5*MAX(BW21*DCF!I$46,0)-MAX(BW21-BV21,0)/Inputs!$B$24)*DCF!I$6 -> 577.68759 | DE21: =(BX21*DCF!J$46-DCF!J$5*MAX(BX21*DCF!J$46,0)-MAX(BX21-BW21,0)/Inputs!$B$24)*DCF!J$6 -> -3393.5911 | DF21: =(BY21*DCF!K$46-DCF!K$5*MAX(BY21*DCF!K$46,0)-MAX(BY21-BX21,0)/Inputs!$B$24)*DCF!K$6 -> -3130.8619 | ... DH21: =(CA21*DCF!M$46-DCF!M$5*MAX(CA21*DCF!M$46,0)-MAX(CA21-BZ21,0)/Inputs!$B$24)*DCF!M$6 -> -5697.0645 | DI21: =SUM(CB21:CL21)+BE21*DCF!M$10*(1+Inputs!$B$30)*(1-Inputs!$B$33)*(1-Inputs!$B$30/Inputs!$B$31)/(Inputs!$B$29-Inputs!$B$30)*DCF!M$6 -> 222877.62 | DJ21: =SUM(CM21:CW21)+BP21*DCF!M$28*(1+Inputs!$B$30)*(1-Inputs!$B$33)*(1-Inputs!$B$30/Inputs!$B$31)/(Inputs!$B$29-Inputs!$B$30)*DCF!M$6 -> 413894.42 | DK21: =SUM(CX21:DH21)+CA21*DCF!M$46*(1+Inputs!$B$30)*(1-Inputs!$B$33)*(1-Inputs!$B$30/Inputs!$B$31)/(Inputs!$B$29-Inputs!$B$30)*DCF!M$6 -> 551842.65 | DM21: =DI21+DJ21+DK21+Inputs!$B$34+Inputs!$B$36-Inputs!$B$35 -> 1265465.7
A22: 9 | C22: =_xlfn.NORM.S.INV(RAND()) -> 0.21247338 | D22: =_xlfn.NORM.S.INV(RAND()) -> 0.23873189 | E22: =_xlfn.NORM.S.INV(RAND()) -> -0.067991 | F22: =_xlfn.NORM.S.INV(RAND()) -> -0.037927743 | G22: =_xlfn.NORM.S.INV(RAND()) -> 0.027850075 | H22: =_xlfn.NORM.S.INV(RAND()) -> 1.2561673 | I22: =_xlfn.NORM.S.INV(RAND()) -> -0.4698366 | J22: =_xlfn.NORM.S.INV(RAND()) -> 0.021900857 | ... M22: =_xlfn.NORM.S.INV(RAND()) -> -0.79352982 | N22: =SQRT(Inputs!$B$38)*C22+SQRT(1-Inputs!$B$38)*_xlfn.NORM.S.INV(RAND()) -> 0.86473963 | O22: =SQRT(Inputs!$B$38)*D22+SQRT(1-Inputs!$B$38)*_xlfn.NORM.S.INV(RAND()) -> -0.49873389 | P22: =SQRT(Inputs!$B$38)*E22+SQRT(1-Inputs!$B$38)*_xlfn.NORM.S.INV(RAND()) -> 0.41769198 | Q22: =SQRT(Inputs!$B$38)*F22+SQRT(1-Inputs!$B$38)*_xlfn.NORM.S.INV(RAND()) -> 0.52483057 | R22: =SQRT(Inputs!$B$38)*G22+SQRT(1-Inputs!$B$38)*_xlfn.NORM.S.INV(RAND()) -> -0.40471077 | S22: =SQRT(Inputs!$B$38)*H22+SQRT(1-Inputs!$B$38)*_xlfn.NORM.S.INV(RAND()) -> -0.18809584 | T22: =SQRT(Inputs!$B$38)*I22+SQRT(1-Inputs!$B$38)*_xlfn.NORM.S.INV(RAND()) -> -0.034988125 | U22: =SQRT(Inputs!$B$38)*J22+SQRT(1-Inputs!$B$38)*_xlfn.NORM.S.INV(RAND()) -> 1.5246156 | ... X22: =SQRT(Inputs!$B$38)*M22+SQRT(1-Inputs!$B$38)*_xlfn.NORM.S.INV(RAND()) -> -1.2776054 | Y22: =SQRT(Inputs!$B$38)*C22+SQRT(1-Inputs!$B$38)*_xlfn.NORM.S.INV(RAND()) -> 1.3696018 | Z22: =SQRT(Inputs!$B$38)*D22+SQRT(1-Inputs!$B$38)*_xlfn.NORM.S.INV(RAND()) -> 1.1206567 | AA22: =SQRT(Inputs!$B$38)*E22+SQRT(1-Inputs!$B$38)*_xlfn.NORM.S.INV(RAND()) -> -0.45960554 | AB22: =SQRT(Inputs!$B$38)*F22+SQRT(1-Inputs!$B$38)*_xlfn.NORM.S.INV(RAND()) -> -1.3005652 | AC22: =SQRT(Inputs!$B$38)*G22+SQRT(1-Inputs!$B$38)*_xlfn.NORM.S.INV(RAND()) -> -0.63383076 | AD22: =SQRT(Inputs!$B$38)*H22+SQRT(1-Inputs!$B$38)*_xlfn.NORM.S.INV(RAND()) -> -0.050572607 | AE22: =SQRT(Inputs!$B$38)*I22+SQRT(1-Inputs!$B$38)*_xlfn.NORM.S.INV(RAND()) -> -0.87658475 | AF22: =SQRT(Inputs!$B$38)*J22+SQRT(1-Inputs!$B$38)*_xlfn.NORM.S.INV(RAND()) -> 0.035429206 | ... AI22: =SQRT(Inputs!$B$38)*M22+SQRT(1-Inputs!$B$38)*_xlfn.NORM.S.INV(RAND()) -> -0.77412288 | AJ22: =SQRT(Inputs!$B$38)*C22+SQRT(1-Inputs!$B$38)*_xlfn.NORM.S.INV(RAND()) -> -1.3367302 | AK22: =SQRT(Inputs!$B$38)*D22+SQRT(1-Inputs!$B$38)*_xlfn.NORM.S.INV(RAND()) -> 0.65833854 | AL22: =SQRT(Inputs!$B$38)*E22+SQRT(1-Inputs!$B$38)*_xlfn.NORM.S.INV(RAND()) -> 0.55486453 | AM22: =SQRT(Inputs!$B$38)*F22+SQRT(1-Inputs!$B$38)*_xlfn.NORM.S.INV(RAND()) -> 0.042559642 | AN22: =SQRT(Inputs!$B$38)*G22+SQRT(1-Inputs!$B$38)*_xlfn.NORM.S.INV(RAND()) -> -0.85427305 | AO22: =SQRT(Inputs!$B$38)*H22+SQRT(1-Inputs!$B$38)*_xlfn.NORM.S.INV(RAND()) -> -0.40490465 | AP22: =SQRT(Inputs!$B$38)*I22+SQRT(1-Inputs!$B$38)*_xlfn.NORM.S.INV(RAND()) -> -0.66366694 | AQ22: =SQRT(Inputs!$B$38)*J22+SQRT(1-Inputs!$B$38)*_xlfn.NORM.S.INV(RAND()) -> 0.64891539 | ... AT22: =SQRT(Inputs!$B$38)*M22+SQRT(1-Inputs!$B$38)*_xlfn.NORM.S.INV(RAND()) -> 0.39577745 | AU22: =Inputs!$B$6*EXP($B$8-0.5*C$5^2+C$5*N22) -> 5707.8088 | AV22: =AU22*EXP($B$8-0.5*D$5^2+D$5*O22) -> 6456.5056 | AW22: =AV22*EXP($B$8-0.5*E$5^2+E$5*P22) -> 8328.8271 | AX22: =AW22*EXP($B$8-0.5*F$5^2+F$5*Q22) -> 10857.751 | AY22: =AX22*EXP($B$8-0.5*G$5^2+G$5*R22) -> 12656.694 | AZ22: =AY22*EXP($B$8-0.5*H$5^2+H$5*S22) -> 15162.15 | BA22: =AZ22*EXP($B$8-0.5*I$5^2+I$5*T22) -> 18486.775 | BB22: =BA22*EXP($B$8-0.5*J$5^2+J$5*U22) -> 26368.745 | BC22: =BB22*EXP($B$8-0.5*K$5^2+K$5*V22) -> 31313.712 | ... BE22: =BD22*EXP($B$8-0.5*M$5^2+M$5*X22) -> 45160.915 | BF22: =Inputs!$B$13*EXP($B$9-0.5*C$6^2+C$6*Y22) -> 18145.713 | BG22: =BF22*EXP($B$9-0.5*D$6^2+D$6*Z22) -> 27070.85 | BH22: =BG22*EXP($B$9-0.5*E$6^2+E$6*AA22) -> 30647.983 | BI22: =BH22*EXP($B$9-0.5*F$6^2+F$6*AB22) -> 30711.329 | BJ22: =BI22*EXP($B$9-0.5*G$6^2+G$6*AC22) -> 34362.692 | BK22: =BJ22*EXP($B$9-0.5*H$6^2+H$6*AD22) -> 41884.319 | BL22: =BK22*EXP($B$9-0.5*I$6^2+I$6*AE22) -> 45924.977 | BM22: =BL22*EXP($B$9-0.5*J$6^2+J$6*AF22) -> 56700.716 | BN22: =BM22*EXP($B$9-0.5*K$6^2+K$6*AG22) -> 73732.879 | ... BP22: =BO22*EXP($B$9-0.5*M$6^2+M$6*AI22) -> 94236.931 | BQ22: =Inputs!$B$20*EXP($B$10-0.5*C$7^2+C$7*AJ22) -> 2669.9462 | BR22: =BQ22*EXP($B$10-0.5*D$7^2+D$7*AK22) -> 4465.2045 | BS22: =BR22*EXP($B$10-0.5*E$7^2+E$7*AL22) -> 7170.9707 | BT22: =BS22*EXP($B$10-0.5*F$7^2+F$7*AM22) -> 9998.2166 | BU22: =BT22*EXP($B$10-0.5*G$7^2+G$7*AN22) -> 11268.754 | BV22: =BU22*EXP($B$10-0.5*H$7^2+H$7*AO22) -> 14311.16 | BW22: =BV22*EXP($B$10-0.5*I$7^2+I$7*AP22) -> 17353.382 | BX22: =BW22*EXP($B$10-0.5*J$7^2+J$7*AQ22) -> 27643.573 | BY22: =BX22*EXP($B$10-0.5*K$7^2+K$7*AR22) -> 31999.837 | ... CA22: =BZ22*EXP($B$10-0.5*M$7^2+M$7*AT22) -> 65375.173 | CB22: =(AU22*DCF!C$10-DCF!C$5*MAX(AU22*DCF!C$10,0)-MAX(AU22-Inputs!$B$6,0)/Inputs!$B$10)*DCF!C$6 -> 1037.7583 | CC22: =(AV22*DCF!D$10-DCF!D$5*MAX(AV22*DCF!D$10,0)-MAX(AV22-AU22,0)/Inputs!$B$10)*DCF!D$6 -> 1391.1794 | CD22: =(AW22*DCF!E$10-DCF!E$5*MAX(AW22*DCF!E$10,0)-MAX(AW22-AV22,0)/Inputs!$B$10)*DCF!E$6 -> 1501.2693 | CE22: =(AX22*DCF!F$10-DCF!F$5*MAX(AX22*DCF!F$10,0)-MAX(AX22-AW22,0)/Inputs!$B$10)*DCF!F$6 -> 1844.0234 | CF22: =(AY22*DCF!G$10-DCF!G$5*MAX(AY22*DCF!G$10,0)-MAX(AY22-AX22,0)/Inputs!$B$10)*DCF!G$6 -> 2261.9954 | CG22: =(AZ22*DCF!H$10-DCF!H$5*MAX(AZ22*DCF!H$10,0)-MAX(AZ22-AY22,0)/Inputs!$B$10)*DCF!H$6 -> 2498.8537 | CH22: =(BA22*DCF!I$10-DCF!I$5*MAX(BA22*DCF!I$10,0)-MAX(BA22-AZ22,0)/Inputs!$B$10)*DCF!I$6 -> 2831.5044 | CI22: =(BB22*DCF!J$10-DCF!J$5*MAX(BB22*DCF!J$10,0)-MAX(BB22-BA22,0)/Inputs!$B$10)*DCF!J$6 -> 3330.5552 | CJ22: =(BC22*DCF!K$10-DCF!K$5*MAX(BC22*DCF!K$10,0)-MAX(BC22-BB22,0)/Inputs!$B$10)*DCF!K$6 -> 4348.7847 | ... CL22: =(BE22*DCF!M$10-DCF!M$5*MAX(BE22*DCF!M$10,0)-MAX(BE22-BD22,0)/Inputs!$B$10)*DCF!M$6 -> 5923.8616 | CM22: =(BF22*DCF!C$28-DCF!C$5*MAX(BF22*DCF!C$28,0)-MAX(BF22-Inputs!$B$13,0)/Inputs!$B$17)*DCF!C$6 -> 3977.0489 | CN22: =(BG22*DCF!D$28-DCF!D$5*MAX(BG22*DCF!D$28,0)-MAX(BG22-BF22,0)/Inputs!$B$17)*DCF!D$6 -> 6068.8488 | CO22: =(BH22*DCF!E$28-DCF!E$5*MAX(BH22*DCF!E$28,0)-MAX(BH22-BG22,0)/Inputs!$B$17)*DCF!E$6 -> 7975.0508 | CP22: =(BI22*DCF!F$28-DCF!F$5*MAX(BI22*DCF!F$28,0)-MAX(BI22-BH22,0)/Inputs!$B$17)*DCF!F$6 -> 8325.7838 | CQ22: =(BJ22*DCF!G$28-DCF!G$5*MAX(BJ22*DCF!G$28,0)-MAX(BJ22-BI22,0)/Inputs!$B$17)*DCF!G$6 -> 8301.538 | CR22: =(BK22*DCF!H$28-DCF!H$5*MAX(BK22*DCF!H$28,0)-MAX(BK22-BJ22,0)/Inputs!$B$17)*DCF!H$6 -> 9189.8045 | CS22: =(BL22*DCF!I$28-DCF!I$5*MAX(BL22*DCF!I$28,0)-MAX(BL22-BK22,0)/Inputs!$B$17)*DCF!I$6 -> 10219.439 | CT22: =(BM22*DCF!J$28-DCF!J$5*MAX(BM22*DCF!J$28,0)-MAX(BM22-BL22,0)/Inputs!$B$17)*DCF!J$6 -> 11220.192 | CU22: =(BN22*DCF!K$28-DCF!K$5*MAX(BN22*DCF!K$28,0)-MAX(BN22-BM22,0)/Inputs!$B$17)*DCF!K$6 -> 13484.935 | ... CW22: =(BP22*DCF!M$28-DCF!M$5*MAX(BP22*DCF!M$28,0)-MAX(BP22-BO22,0)/Inputs!$B$17)*DCF!M$6 -> 16617.121 | CX22: =(BQ22*DCF!C$46-DCF!C$5*MAX(BQ22*DCF!C$46,0)-MAX(BQ22-Inputs!$B$20,0)/Inputs!$B$24)*DCF!C$6 -> -616.61576 | CY22: =(BR22*DCF!D$46-DCF!D$5*MAX(BR22*DCF!D$46,0)-MAX(BR22-BQ22,0)/Inputs!$B$24)*DCF!D$6 -> -1528.1281 | CZ22: =(BS22*DCF!E$46-DCF!E$5*MAX(BS22*DCF!E$46,0)-MAX(BS22-BR22,0)/Inputs!$B$24)*DCF!E$6 -> -1914.5183 | DA22: =(BT22*DCF!F$46-DCF!F$5*MAX(BT22*DCF!F$46,0)-MAX(BT22-BS22,0)/Inputs!$B$24)*DCF!F$6 -> -1757.623 | DB22: =(BU22*DCF!G$46-DCF!G$5*MAX(BU22*DCF!G$46,0)-MAX(BU22-BT22,0)/Inputs!$B$24)*DCF!G$6 -> -806.44224 | DC22: =(BV22*DCF!H$46-DCF!H$5*MAX(BV22*DCF!H$46,0)-MAX(BV22-BU22,0)/Inputs!$B$24)*DCF!H$6 -> -945.40906 | DD22: =(BW22*DCF!I$46-DCF!I$5*MAX(BW22*DCF!I$46,0)-MAX(BW22-BV22,0)/Inputs!$B$24)*DCF!I$6 -> -472.52109 | DE22: =(BX22*DCF!J$46-DCF!J$5*MAX(BX22*DCF!J$46,0)-MAX(BX22-BW22,0)/Inputs!$B$24)*DCF!J$6 -> -1569.2192 | DF22: =(BY22*DCF!K$46-DCF!K$5*MAX(BY22*DCF!K$46,0)-MAX(BY22-BX22,0)/Inputs!$B$24)*DCF!K$6 -> 760.76875 | ... DH22: =(CA22*DCF!M$46-DCF!M$5*MAX(CA22*DCF!M$46,0)-MAX(CA22-BZ22,0)/Inputs!$B$24)*DCF!M$6 -> 526.86467 | DI22: =SUM(CB22:CL22)+BE22*DCF!M$10*(1+Inputs!$B$30)*(1-Inputs!$B$33)*(1-Inputs!$B$30/Inputs!$B$31)/(Inputs!$B$29-Inputs!$B$30)*DCF!M$6 -> 157592.86 | DJ22: =SUM(CM22:CW22)+BP22*DCF!M$28*(1+Inputs!$B$30)*(1-Inputs!$B$33)*(1-Inputs!$B$30/Inputs!$B$31)/(Inputs!$B$29-Inputs!$B$30)*DCF!M$6 -> 460625.29 | DK22: =SUM(CX22:DH22)+CA22*DCF!M$46*(1+Inputs!$B$30)*(1-Inputs!$B$33)*(1-Inputs!$B$30/Inputs!$B$31)/(Inputs!$B$29-Inputs!$B$30)*DCF!M$6 -> 93178.257 | DM22: =DI22+DJ22+DK22+Inputs!$B$34+Inputs!$B$36-Inputs!$B$35 -> 788247.4
A23: 10 | C23: =_xlfn.NORM.S.INV(RAND()) -> 0.16712098 | D23: =_xlfn.NORM.S.INV(RAND()) -> 0.075010124 | E23: =_xlfn.NORM.S.INV(RAND()) -> -0.22806949 | F23: =_xlfn.NORM.S.INV(RAND()) -> 1.812306 | G23: =_xlfn.NORM.S.INV(RAND()) -> -0.78337051 | H23: =_xlfn.NORM.S.INV(RAND()) -> 1.3047161 | I23: =_xlfn.NORM.S.INV(RAND()) -> 0.81127399 | J23: =_xlfn.NORM.S.INV(RAND()) -> -1.633533 | ... M23: =_xlfn.NORM.S.INV(RAND()) -> 0.76119792 | N23: =SQRT(Inputs!$B$38)*C23+SQRT(1-Inputs!$B$38)*_xlfn.NORM.S.INV(RAND()) -> 1.5995306 | O23: =SQRT(Inputs!$B$38)*D23+SQRT(1-Inputs!$B$38)*_xlfn.NORM.S.INV(RAND()) -> 0.75864013 | P23: =SQRT(Inputs!$B$38)*E23+SQRT(1-Inputs!$B$38)*_xlfn.NORM.S.INV(RAND()) -> -0.87479873 | Q23: =SQRT(Inputs!$B$38)*F23+SQRT(1-Inputs!$B$38)*_xlfn.NORM.S.INV(RAND()) -> -0.46029084 | R23: =SQRT(Inputs!$B$38)*G23+SQRT(1-Inputs!$B$38)*_xlfn.NORM.S.INV(RAND()) -> 0.5026048 | S23: =SQRT(Inputs!$B$38)*H23+SQRT(1-Inputs!$B$38)*_xlfn.NORM.S.INV(RAND()) -> 1.7609686 | T23: =SQRT(Inputs!$B$38)*I23+SQRT(1-Inputs!$B$38)*_xlfn.NORM.S.INV(RAND()) -> 0.1480597 | U23: =SQRT(Inputs!$B$38)*J23+SQRT(1-Inputs!$B$38)*_xlfn.NORM.S.INV(RAND()) -> -1.7660229 | ... X23: =SQRT(Inputs!$B$38)*M23+SQRT(1-Inputs!$B$38)*_xlfn.NORM.S.INV(RAND()) -> 0.91029257 | Y23: =SQRT(Inputs!$B$38)*C23+SQRT(1-Inputs!$B$38)*_xlfn.NORM.S.INV(RAND()) -> -1.1272097 | Z23: =SQRT(Inputs!$B$38)*D23+SQRT(1-Inputs!$B$38)*_xlfn.NORM.S.INV(RAND()) -> -1.3169906 | AA23: =SQRT(Inputs!$B$38)*E23+SQRT(1-Inputs!$B$38)*_xlfn.NORM.S.INV(RAND()) -> 0.3822762 | AB23: =SQRT(Inputs!$B$38)*F23+SQRT(1-Inputs!$B$38)*_xlfn.NORM.S.INV(RAND()) -> 0.40096658 | AC23: =SQRT(Inputs!$B$38)*G23+SQRT(1-Inputs!$B$38)*_xlfn.NORM.S.INV(RAND()) -> -1.3057043 | AD23: =SQRT(Inputs!$B$38)*H23+SQRT(1-Inputs!$B$38)*_xlfn.NORM.S.INV(RAND()) -> 1.4665891 | AE23: =SQRT(Inputs!$B$38)*I23+SQRT(1-Inputs!$B$38)*_xlfn.NORM.S.INV(RAND()) -> 0.93118859 | AF23: =SQRT(Inputs!$B$38)*J23+SQRT(1-Inputs!$B$38)*_xlfn.NORM.S.INV(RAND()) -> -0.82679895 | ... AI23: =SQRT(Inputs!$B$38)*M23+SQRT(1-Inputs!$B$38)*_xlfn.NORM.S.INV(RAND()) -> -0.76396484 | AJ23: =SQRT(Inputs!$B$38)*C23+SQRT(1-Inputs!$B$38)*_xlfn.NORM.S.INV(RAND()) -> 1.4441541 | AK23: =SQRT(Inputs!$B$38)*D23+SQRT(1-Inputs!$B$38)*_xlfn.NORM.S.INV(RAND()) -> -0.11457879 | AL23: =SQRT(Inputs!$B$38)*E23+SQRT(1-Inputs!$B$38)*_xlfn.NORM.S.INV(RAND()) -> 0.60847647 | AM23: =SQRT(Inputs!$B$38)*F23+SQRT(1-Inputs!$B$38)*_xlfn.NORM.S.INV(RAND()) -> 0.56807896 | AN23: =SQRT(Inputs!$B$38)*G23+SQRT(1-Inputs!$B$38)*_xlfn.NORM.S.INV(RAND()) -> 0.31150076 | AO23: =SQRT(Inputs!$B$38)*H23+SQRT(1-Inputs!$B$38)*_xlfn.NORM.S.INV(RAND()) -> 0.70770225 | AP23: =SQRT(Inputs!$B$38)*I23+SQRT(1-Inputs!$B$38)*_xlfn.NORM.S.INV(RAND()) -> -0.46945912 | AQ23: =SQRT(Inputs!$B$38)*J23+SQRT(1-Inputs!$B$38)*_xlfn.NORM.S.INV(RAND()) -> -1.5582318 | ... AT23: =SQRT(Inputs!$B$38)*M23+SQRT(1-Inputs!$B$38)*_xlfn.NORM.S.INV(RAND()) -> 0.75532345 | AU23: =Inputs!$B$6*EXP($B$8-0.5*C$5^2+C$5*N23) -> 6428.7368 | AV23: =AU23*EXP($B$8-0.5*D$5^2+D$5*O23) -> 8748.7019 | AW23: =AV23*EXP($B$8-0.5*E$5^2+E$5*P23) -> 9480.2158 | AX23: =AW23*EXP($B$8-0.5*F$5^2+F$5*Q23) -> 10927.577 | AY23: =AX23*EXP($B$8-0.5*G$5^2+G$5*R23) -> 14161.969 | AZ23: =AY23*EXP($B$8-0.5*H$5^2+H$5*S23) -> 21026.971 | BA23: =AZ23*EXP($B$8-0.5*I$5^2+I$5*T23) -> 26133.475 | BB23: =BA23*EXP($B$8-0.5*J$5^2+J$5*U23) -> 26806.73 | BC23: =BB23*EXP($B$8-0.5*K$5^2+K$5*V23) -> 36285.231 | ... BE23: =BD23*EXP($B$8-0.5*M$5^2+M$5*X23) -> 62691.306 | BF23: =Inputs!$B$13*EXP($B$9-0.5*C$6^2+C$6*Y23) -> 11061.241 | BG23: =BF23*EXP($B$9-0.5*D$6^2+D$6*Z23) -> 10629.416 | BH23: =BG23*EXP($B$9-0.5*E$6^2+E$6*AA23) -> 13837.287 | BI23: =BH23*EXP($B$9-0.5*F$6^2+F$6*AB23) -> 18017.266 | BJ23: =BI23*EXP($B$9-0.5*G$6^2+G$6*AC23) -> 18298.568 | BK23: =BJ23*EXP($B$9-0.5*H$6^2+H$6*AD23) -> 27421.14 | BL23: =BK23*EXP($B$9-0.5*I$6^2+I$6*AE23) -> 38003.725 | BM23: =BL23*EXP($B$9-0.5*J$6^2+J$6*AF23) -> 42154.834 | BN23: =BM23*EXP($B$9-0.5*K$6^2+K$6*AG23) -> 54338.731 | ... BP23: =BO23*EXP($B$9-0.5*M$6^2+M$6*AI23) -> 79535.884 | BQ23: =Inputs!$B$20*EXP($B$10-0.5*C$7^2+C$7*AJ23) -> 7159.1401 | BR23: =BQ23*EXP($B$10-0.5*D$7^2+D$7*AK23) -> 9366.9118 | BS23: =BR23*EXP($B$10-0.5*E$7^2+E$7*AL23) -> 15276.367 | BT23: =BS23*EXP($B$10-0.5*F$7^2+F$7*AM23) -> 24447.631 | BU23: =BT23*EXP($B$10-0.5*G$7^2+G$7*AN23) -> 36533.969 | BV23: =BU23*EXP($B$10-0.5*H$7^2+H$7*AO23) -> 59615.589 | BW23: =BV23*EXP($B$10-0.5*I$7^2+I$7*AP23) -> 75321.738 | BX23: =BW23*EXP($B$10-0.5*J$7^2+J$7*AQ23) -> 77084.231 | BY23: =BX23*EXP($B$10-0.5*K$7^2+K$7*AR23) -> 108558.53 | ... CA23: =BZ23*EXP($B$10-0.5*M$7^2+M$7*AT23) -> 219992.42 | CB23: =(AU23*DCF!C$10-DCF!C$5*MAX(AU23*DCF!C$10,0)-MAX(AU23-Inputs!$B$6,0)/Inputs!$B$10)*DCF!C$6 -> 1032.6179 | CC23: =(AV23*DCF!D$10-DCF!D$5*MAX(AV23*DCF!D$10,0)-MAX(AV23-AU23,0)/Inputs!$B$10)*DCF!D$6 -> 1566.7741 | CD23: =(AW23*DCF!E$10-DCF!E$5*MAX(AW23*DCF!E$10,0)-MAX(AW23-AV23,0)/Inputs!$B$10)*DCF!E$6 -> 2024.0637 | CE23: =(AX23*DCF!F$10-DCF!F$5*MAX(AX23*DCF!F$10,0)-MAX(AX23-AW23,0)/Inputs!$B$10)*DCF!F$6 -> 2084.3127 | CF23: =(AY23*DCF!G$10-DCF!G$5*MAX(AY23*DCF!G$10,0)-MAX(AY23-AX23,0)/Inputs!$B$10)*DCF!G$6 -> 2296.2239 | CG23: =(AZ23*DCF!H$10-DCF!H$5*MAX(AZ23*DCF!H$10,0)-MAX(AZ23-AY23,0)/Inputs!$B$10)*DCF!H$6 -> 2863.3974 | CH23: =(BA23*DCF!I$10-DCF!I$5*MAX(BA23*DCF!I$10,0)-MAX(BA23-AZ23,0)/Inputs!$B$10)*DCF!I$6 -> 3935.9869 | CI23: =(BB23*DCF!J$10-DCF!J$5*MAX(BB23*DCF!J$10,0)-MAX(BB23-BA23,0)/Inputs!$B$10)*DCF!J$6 -> 4498.0764 | CJ23: =(BC23*DCF!K$10-DCF!K$5*MAX(BC23*DCF!K$10,0)-MAX(BC23-BB23,0)/Inputs!$B$10)*DCF!K$6 -> 4514.4935 | ... CL23: =(BE23*DCF!M$10-DCF!M$5*MAX(BE23*DCF!M$10,0)-MAX(BE23-BD23,0)/Inputs!$B$10)*DCF!M$6 -> 6982.857 | CM23: =(BF23*DCF!C$28-DCF!C$5*MAX(BF23*DCF!C$28,0)-MAX(BF23-Inputs!$B$13,0)/Inputs!$B$17)*DCF!C$6 -> 3375.8184 | CN23: =(BG23*DCF!D$28-DCF!D$5*MAX(BG23*DCF!D$28,0)-MAX(BG23-BF23,0)/Inputs!$B$17)*DCF!D$6 -> 3130.6081 | CO23: =(BH23*DCF!E$28-DCF!E$5*MAX(BH23*DCF!E$28,0)-MAX(BH23-BG23,0)/Inputs!$B$17)*DCF!E$6 -> 3286.7388 | CP23: =(BI23*DCF!F$28-DCF!F$5*MAX(BI23*DCF!F$28,0)-MAX(BI23-BH23,0)/Inputs!$B$17)*DCF!F$6 -> 4130.1819 | CQ23: =(BJ23*DCF!G$28-DCF!G$5*MAX(BJ23*DCF!G$28,0)-MAX(BJ23-BI23,0)/Inputs!$B$17)*DCF!G$6 -> 4700.3901 | CR23: =(BK23*DCF!H$28-DCF!H$5*MAX(BK23*DCF!H$28,0)-MAX(BK23-BJ23,0)/Inputs!$B$17)*DCF!H$6 -> 5364.1587 | CS23: =(BL23*DCF!I$28-DCF!I$5*MAX(BL23*DCF!I$28,0)-MAX(BL23-BK23,0)/Inputs!$B$17)*DCF!I$6 -> 7417.766 | CT23: =(BM23*DCF!J$28-DCF!J$5*MAX(BM23*DCF!J$28,0)-MAX(BM23-BL23,0)/Inputs!$B$17)*DCF!J$6 -> 8853.6244 | CU23: =(BN23*DCF!K$28-DCF!K$5*MAX(BN23*DCF!K$28,0)-MAX(BN23-BM23,0)/Inputs!$B$17)*DCF!K$6 -> 9983.0638 | ... CW23: =(BP23*DCF!M$28-DCF!M$5*MAX(BP23*DCF!M$28,0)-MAX(BP23-BO23,0)/Inputs!$B$17)*DCF!M$6 -> 14016.354 | CX23: =(BQ23*DCF!C$46-DCF!C$5*MAX(BQ23*DCF!C$46,0)-MAX(BQ23-Inputs!$B$20,0)/Inputs!$B$24)*DCF!C$6 -> -3481.6213 | CY23: =(BR23*DCF!D$46-DCF!D$5*MAX(BR23*DCF!D$46,0)-MAX(BR23-BQ23,0)/Inputs!$B$24)*DCF!D$6 -> -2540.7513 | CZ23: =(BS23*DCF!E$46-DCF!E$5*MAX(BS23*DCF!E$46,0)-MAX(BS23-BR23,0)/Inputs!$B$24)*DCF!E$6 -> -4135.8013 | DA23: =(BT23*DCF!F$46-DCF!F$5*MAX(BT23*DCF!F$46,0)-MAX(BT23-BS23,0)/Inputs!$B$24)*DCF!F$6 -> -5119.9786 | DB23: =(BU23*DCF!G$46-DCF!G$5*MAX(BU23*DCF!G$46,0)-MAX(BU23-BT23,0)/Inputs!$B$24)*DCF!G$6 -> -5294.5356 | DC23: =(BV23*DCF!H$46-DCF!H$5*MAX(BV23*DCF!H$46,0)-MAX(BV23-BU23,0)/Inputs!$B$24)*DCF!H$6 -> -7172.4721 | DD23: =(BW23*DCF!I$46-DCF!I$5*MAX(BW23*DCF!I$46,0)-MAX(BW23-BV23,0)/Inputs!$B$24)*DCF!I$6 -> -2769.0431 | DE23: =(BX23*DCF!J$46-DCF!J$5*MAX(BX23*DCF!J$46,0)-MAX(BX23-BW23,0)/Inputs!$B$24)*DCF!J$6 -> 2766.086 | DF23: =(BY23*DCF!K$46-DCF!K$5*MAX(BY23*DCF!K$46,0)-MAX(BY23-BX23,0)/Inputs!$B$24)*DCF!K$6 -> -1509.1399 | ... DH23: =(CA23*DCF!M$46-DCF!M$5*MAX(CA23*DCF!M$46,0)-MAX(CA23-BZ23,0)/Inputs!$B$24)*DCF!M$6 -> -115.8698 | DI23: =SUM(CB23:CL23)+BE23*DCF!M$10*(1+Inputs!$B$30)*(1-Inputs!$B$33)*(1-Inputs!$B$30/Inputs!$B$31)/(Inputs!$B$29-Inputs!$B$30)*DCF!M$6 -> 211974.38 | DJ23: =SUM(CM23:CW23)+BP23*DCF!M$28*(1+Inputs!$B$30)*(1-Inputs!$B$33)*(1-Inputs!$B$30/Inputs!$B$31)/(Inputs!$B$29-Inputs!$B$30)*DCF!M$6 -> 371625.62 | DK23: =SUM(CX23:DH23)+CA23*DCF!M$46*(1+Inputs!$B$30)*(1-Inputs!$B$33)*(1-Inputs!$B$30/Inputs!$B$31)/(Inputs!$B$29-Inputs!$B$30)*DCF!M$6 -> 313804.26 | DM23: =DI23+DJ23+DK23+Inputs!$B$34+Inputs!$B$36-Inputs!$B$35 -> 974255.26
A24: 11 | C24: =_xlfn.NORM.S.INV(RAND()) -> 1.4007662 | D24: =_xlfn.NORM.S.INV(RAND()) -> 0.53601554 | E24: =_xlfn.NORM.S.INV(RAND()) -> -0.74459813 | F24: =_xlfn.NORM.S.INV(RAND()) -> -0.12620527 | G24: =_xlfn.NORM.S.INV(RAND()) -> 0.31618231 | H24: =_xlfn.NORM.S.INV(RAND()) -> 0.93587695 | I24: =_xlfn.NORM.S.INV(RAND()) -> 0.13248255 | J24: =_xlfn.NORM.S.INV(RAND()) -> -0.6510881 | ... M24: =_xlfn.NORM.S.INV(RAND()) -> -0.67868805 | N24: =SQRT(Inputs!$B$38)*C24+SQRT(1-Inputs!$B$38)*_xlfn.NORM.S.INV(RAND()) -> 0.7982095 | O24: =SQRT(Inputs!$B$38)*D24+SQRT(1-Inputs!$B$38)*_xlfn.NORM.S.INV(RAND()) -> -0.24727502 | P24: =SQRT(Inputs!$B$38)*E24+SQRT(1-Inputs!$B$38)*_xlfn.NORM.S.INV(RAND()) -> -0.81437699 | Q24: =SQRT(Inputs!$B$38)*F24+SQRT(1-Inputs!$B$38)*_xlfn.NORM.S.INV(RAND()) -> -1.0794349 | R24: =SQRT(Inputs!$B$38)*G24+SQRT(1-Inputs!$B$38)*_xlfn.NORM.S.INV(RAND()) -> -0.21787531 | S24: =SQRT(Inputs!$B$38)*H24+SQRT(1-Inputs!$B$38)*_xlfn.NORM.S.INV(RAND()) -> -0.28180833 | T24: =SQRT(Inputs!$B$38)*I24+SQRT(1-Inputs!$B$38)*_xlfn.NORM.S.INV(RAND()) -> 0.1659345 | U24: =SQRT(Inputs!$B$38)*J24+SQRT(1-Inputs!$B$38)*_xlfn.NORM.S.INV(RAND()) -> -0.59805186 | ... X24: =SQRT(Inputs!$B$38)*M24+SQRT(1-Inputs!$B$38)*_xlfn.NORM.S.INV(RAND()) -> -0.45570548 | Y24: =SQRT(Inputs!$B$38)*C24+SQRT(1-Inputs!$B$38)*_xlfn.NORM.S.INV(RAND()) -> -0.33766701 | Z24: =SQRT(Inputs!$B$38)*D24+SQRT(1-Inputs!$B$38)*_xlfn.NORM.S.INV(RAND()) -> 1.1938773 | AA24: =SQRT(Inputs!$B$38)*E24+SQRT(1-Inputs!$B$38)*_xlfn.NORM.S.INV(RAND()) -> -1.3015171 | AB24: =SQRT(Inputs!$B$38)*F24+SQRT(1-Inputs!$B$38)*_xlfn.NORM.S.INV(RAND()) -> 0.023480849 | AC24: =SQRT(Inputs!$B$38)*G24+SQRT(1-Inputs!$B$38)*_xlfn.NORM.S.INV(RAND()) -> 0.60015306 | AD24: =SQRT(Inputs!$B$38)*H24+SQRT(1-Inputs!$B$38)*_xlfn.NORM.S.INV(RAND()) -> 1.3267036 | AE24: =SQRT(Inputs!$B$38)*I24+SQRT(1-Inputs!$B$38)*_xlfn.NORM.S.INV(RAND()) -> -0.28303106 | AF24: =SQRT(Inputs!$B$38)*J24+SQRT(1-Inputs!$B$38)*_xlfn.NORM.S.INV(RAND()) -> -1.0185178 | ... AI24: =SQRT(Inputs!$B$38)*M24+SQRT(1-Inputs!$B$38)*_xlfn.NORM.S.INV(RAND()) -> 0.21781781 | AJ24: =SQRT(Inputs!$B$38)*C24+SQRT(1-Inputs!$B$38)*_xlfn.NORM.S.INV(RAND()) -> 0.52068549 | AK24: =SQRT(Inputs!$B$38)*D24+SQRT(1-Inputs!$B$38)*_xlfn.NORM.S.INV(RAND()) -> 0.75324125 | AL24: =SQRT(Inputs!$B$38)*E24+SQRT(1-Inputs!$B$38)*_xlfn.NORM.S.INV(RAND()) -> -0.3416268 | AM24: =SQRT(Inputs!$B$38)*F24+SQRT(1-Inputs!$B$38)*_xlfn.NORM.S.INV(RAND()) -> -0.27780955 | AN24: =SQRT(Inputs!$B$38)*G24+SQRT(1-Inputs!$B$38)*_xlfn.NORM.S.INV(RAND()) -> 0.52051953 | AO24: =SQRT(Inputs!$B$38)*H24+SQRT(1-Inputs!$B$38)*_xlfn.NORM.S.INV(RAND()) -> -1.9871846 | AP24: =SQRT(Inputs!$B$38)*I24+SQRT(1-Inputs!$B$38)*_xlfn.NORM.S.INV(RAND()) -> 0.31450987 | AQ24: =SQRT(Inputs!$B$38)*J24+SQRT(1-Inputs!$B$38)*_xlfn.NORM.S.INV(RAND()) -> -0.21023659 | ... AT24: =SQRT(Inputs!$B$38)*M24+SQRT(1-Inputs!$B$38)*_xlfn.NORM.S.INV(RAND()) -> 0.00471733 | AU24: =Inputs!$B$6*EXP($B$8-0.5*C$5^2+C$5*N24) -> 5646.6687 | AV24: =AU24*EXP($B$8-0.5*D$5^2+D$5*O24) -> 6627.9218 | AW24: =AV24*EXP($B$8-0.5*E$5^2+E$5*P24) -> 7240.8805 | AX24: =AW24*EXP($B$8-0.5*F$5^2+F$5*Q24) -> 7725.0929 | AY24: =AX24*EXP($B$8-0.5*G$5^2+G$5*R24) -> 9203.658 | AZ24: =AY24*EXP($B$8-0.5*H$5^2+H$5*S24) -> 10912.374 | BA24: =AZ24*EXP($B$8-0.5*I$5^2+I$5*T24) -> 13587.895 | BB24: =BA24*EXP($B$8-0.5*J$5^2+J$5*U24) -> 15668.21 | BC24: =BB24*EXP($B$8-0.5*K$5^2+K$5*V24) -> 17659.786 | ... BE24: =BD24*EXP($B$8-0.5*M$5^2+M$5*X24) -> 27104.18 | BF24: =Inputs!$B$13*EXP($B$9-0.5*C$6^2+C$6*Y24) -> 12935.458 | BG24: =BF24*EXP($B$9-0.5*D$6^2+D$6*Z24) -> 19554.535 | BH24: =BG24*EXP($B$9-0.5*E$6^2+E$6*AA24) -> 19253.239 | BI24: =BH24*EXP($B$9-0.5*F$6^2+F$6*AB24) -> 23654.197 | BJ24: =BI24*EXP($B$9-0.5*G$6^2+G$6*AC24) -> 31618.856 | BK24: =BJ24*EXP($B$9-0.5*H$6^2+H$6*AD24) -> 46488.298 | BL24: =BK24*EXP($B$9-0.5*I$6^2+I$6*AE24) -> 55048.678 | BM24: =BL24*EXP($B$9-0.5*J$6^2+J$6*AF24) -> 59624.482 | BN24: =BM24*EXP($B$9-0.5*K$6^2+K$6*AG24) -> 75080.669 | ... BP24: =BO24*EXP($B$9-0.5*M$6^2+M$6*AI24) -> 121867.34 | BQ24: =Inputs!$B$20*EXP($B$10-0.5*C$7^2+C$7*AJ24) -> 5159.5612 | BR24: =BQ24*EXP($B$10-0.5*D$7^2+D$7*AK24) -> 8892.8485 | BS24: =BR24*EXP($B$10-0.5*E$7^2+E$7*AL24) -> 11039.707 | BT24: =BS24*EXP($B$10-0.5*F$7^2+F$7*AM24) -> 14151.506 | BU24: =BT24*EXP($B$10-0.5*G$7^2+G$7*AN24) -> 22244.759 | BV24: =BU24*EXP($B$10-0.5*H$7^2+H$7*AO24) -> 19779.122 | BW24: =BV24*EXP($B$10-0.5*I$7^2+I$7*AP24) -> 29500.437 | BX24: =BW24*EXP($B$10-0.5*J$7^2+J$7*AQ24) -> 39558.207 | BY24: =BX24*EXP($B$10-0.5*K$7^2+K$7*AR24) -> 40024.488 | ... CA24: =BZ24*EXP($B$10-0.5*M$7^2+M$7*AT24) -> 102132.66 | CB24: =(AU24*DCF!C$10-DCF!C$5*MAX(AU24*DCF!C$10,0)-MAX(AU24-Inputs!$B$6,0)/Inputs!$B$10)*DCF!C$6 -> 1038.1942 | CC24: =(AV24*DCF!D$10-DCF!D$5*MAX(AV24*DCF!D$10,0)-MAX(AV24-AU24,0)/Inputs!$B$10)*DCF!D$6 -> 1376.2582 | CD24: =(AW24*DCF!E$10-DCF!E$5*MAX(AW24*DCF!E$10,0)-MAX(AW24-AV24,0)/Inputs!$B$10)*DCF!E$6 -> 1533.7404 | CE24: =(AX24*DCF!F$10-DCF!F$5*MAX(AX24*DCF!F$10,0)-MAX(AX24-AW24,0)/Inputs!$B$10)*DCF!F$6 -> 1585.6229 | CF24: =(AY24*DCF!G$10-DCF!G$5*MAX(AY24*DCF!G$10,0)-MAX(AY24-AX24,0)/Inputs!$B$10)*DCF!G$6 -> 1612.1145 | CG24: =(AZ24*DCF!H$10-DCF!H$5*MAX(AZ24*DCF!H$10,0)-MAX(AZ24-AY24,0)/Inputs!$B$10)*DCF!H$6 -> 1815.2321 | CH24: =(BA24*DCF!I$10-DCF!I$5*MAX(BA24*DCF!I$10,0)-MAX(BA24-AZ24,0)/Inputs!$B$10)*DCF!I$6 -> 2043.1336 | CI24: =(BB24*DCF!J$10-DCF!J$5*MAX(BB24*DCF!J$10,0)-MAX(BB24-BA24,0)/Inputs!$B$10)*DCF!J$6 -> 2373.4637 | CJ24: =(BC24*DCF!K$10-DCF!K$5*MAX(BC24*DCF!K$10,0)-MAX(BC24-BB24,0)/Inputs!$B$10)*DCF!K$6 -> 2564.1516 | ... CL24: =(BE24*DCF!M$10-DCF!M$5*MAX(BE24*DCF!M$10,0)-MAX(BE24-BD24,0)/Inputs!$B$10)*DCF!M$6 -> 3341.2165 | CM24: =(BF24*DCF!C$28-DCF!C$5*MAX(BF24*DCF!C$28,0)-MAX(BF24-Inputs!$B$13,0)/Inputs!$B$17)*DCF!C$6 -> 3590.2054 | CN24: =(BG24*DCF!D$28-DCF!D$5*MAX(BG24*DCF!D$28,0)-MAX(BG24-BF24,0)/Inputs!$B$17)*DCF!D$6 -> 4347.109 | CO24: =(BH24*DCF!E$28-DCF!E$5*MAX(BH24*DCF!E$28,0)-MAX(BH24-BG24,0)/Inputs!$B$17)*DCF!E$6 -> 5452.8602 | CP24: =(BI24*DCF!F$28-DCF!F$5*MAX(BI24*DCF!F$28,0)-MAX(BI24-BH24,0)/Inputs!$B$17)*DCF!F$6 -> 5620.2275 | CQ24: =(BJ24*DCF!G$28-DCF!G$5*MAX(BJ24*DCF!G$28,0)-MAX(BJ24-BI24,0)/Inputs!$B$17)*DCF!G$6 -> 6864.175 | CR24: =(BK24*DCF!H$28-DCF!H$5*MAX(BK24*DCF!H$28,0)-MAX(BK24-BJ24,0)/Inputs!$B$17)*DCF!H$6 -> 9186.7749 | CS24: =(BL24*DCF!I$28-DCF!I$5*MAX(BL24*DCF!I$28,0)-MAX(BL24-BK24,0)/Inputs!$B$17)*DCF!I$6 -> 11716.187 | CT24: =(BM24*DCF!J$28-DCF!J$5*MAX(BM24*DCF!J$28,0)-MAX(BM24-BL24,0)/Inputs!$B$17)*DCF!J$6 -> 12694.495 | CU24: =(BN24*DCF!K$28-DCF!K$5*MAX(BN24*DCF!K$28,0)-MAX(BN24-BM24,0)/Inputs!$B$17)*DCF!K$6 -> 13962.601 | ... CW24: =(BP24*DCF!M$28-DCF!M$5*MAX(BP24*DCF!M$28,0)-MAX(BP24-BO24,0)/Inputs!$B$17)*DCF!M$6 -> 20288.281 | CX24: =(BQ24*DCF!C$46-DCF!C$5*MAX(BQ24*DCF!C$46,0)-MAX(BQ24-Inputs!$B$20,0)/Inputs!$B$24)*DCF!C$6 -> -2096.2318 | CY24: =(BR24*DCF!D$46-DCF!D$5*MAX(BR24*DCF!D$46,0)-MAX(BR24-BQ24,0)/Inputs!$B$24)*DCF!D$6 -> -3110.7646 | CZ24: =(BS24*DCF!E$46-DCF!E$5*MAX(BS24*DCF!E$46,0)-MAX(BS24-BR24,0)/Inputs!$B$24)*DCF!E$6 -> -2151.6971 | DA24: =(BT24*DCF!F$46-DCF!F$5*MAX(BT24*DCF!F$46,0)-MAX(BT24-BS24,0)/Inputs!$B$24)*DCF!F$6 -> -2163.7065 | DB24: =(BU24*DCF!G$46-DCF!G$5*MAX(BU24*DCF!G$46,0)-MAX(BU24-BT24,0)/Inputs!$B$24)*DCF!G$6 -> -3470.6802 | DC24: =(BV24*DCF!H$46-DCF!H$5*MAX(BV24*DCF!H$46,0)-MAX(BV24-BU24,0)/Inputs!$B$24)*DCF!H$6 -> 0 | DD24: =(BW24*DCF!I$46-DCF!I$5*MAX(BW24*DCF!I$46,0)-MAX(BW24-BV24,0)/Inputs!$B$24)*DCF!I$6 -> -2109.2894 | DE24: =(BX24*DCF!J$46-DCF!J$5*MAX(BX24*DCF!J$46,0)-MAX(BX24-BW24,0)/Inputs!$B$24)*DCF!J$6 -> -1007.799 | DF24: =(BY24*DCF!K$46-DCF!K$5*MAX(BY24*DCF!K$46,0)-MAX(BY24-BX24,0)/Inputs!$B$24)*DCF!K$6 -> 2172.1058 | ... DH24: =(CA24*DCF!M$46-DCF!M$5*MAX(CA24*DCF!M$46,0)-MAX(CA24-BZ24,0)/Inputs!$B$24)*DCF!M$6 -> 1842.6536 | DI24: =SUM(CB24:CL24)+BE24*DCF!M$10*(1+Inputs!$B$30)*(1-Inputs!$B$33)*(1-Inputs!$B$30/Inputs!$B$31)/(Inputs!$B$29-Inputs!$B$30)*DCF!M$6 -> 97493.895 | DJ24: =SUM(CM24:CW24)+BP24*DCF!M$28*(1+Inputs!$B$30)*(1-Inputs!$B$33)*(1-Inputs!$B$30/Inputs!$B$31)/(Inputs!$B$29-Inputs!$B$30)*DCF!M$6 -> 562772.93 | DK24: =SUM(CX24:DH24)+CA24*DCF!M$46*(1+Inputs!$B$30)*(1-Inputs!$B$33)*(1-Inputs!$B$30/Inputs!$B$31)/(Inputs!$B$29-Inputs!$B$30)*DCF!M$6 -> 143452.93 | DM24: =DI24+DJ24+DK24+Inputs!$B$34+Inputs!$B$36-Inputs!$B$35 -> 880570.76
A25: 12 | C25: =_xlfn.NORM.S.INV(RAND()) -> 0.27427565 | D25: =_xlfn.NORM.S.INV(RAND()) -> -0.24280498 | E25: =_xlfn.NORM.S.INV(RAND()) -> 0.80236518 | F25: =_xlfn.NORM.S.INV(RAND()) -> 1.7497377 | G25: =_xlfn.NORM.S.INV(RAND()) -> -0.78563517 | H25: =_xlfn.NORM.S.INV(RAND()) -> -1.1906266 | I25: =_xlfn.NORM.S.INV(RAND()) -> 0.26558784 | J25: =_xlfn.NORM.S.INV(RAND()) -> 1.0434319 | ... M25: =_xlfn.NORM.S.INV(RAND()) -> 0.02502544 | N25: =SQRT(Inputs!$B$38)*C25+SQRT(1-Inputs!$B$38)*_xlfn.NORM.S.INV(RAND()) -> 0.014522288 | O25: =SQRT(Inputs!$B$38)*D25+SQRT(1-Inputs!$B$38)*_xlfn.NORM.S.INV(RAND()) -> -0.86927815 | P25: =SQRT(Inputs!$B$38)*E25+SQRT(1-Inputs!$B$38)*_xlfn.NORM.S.INV(RAND()) -> 0.44464196 | Q25: =SQRT(Inputs!$B$38)*F25+SQRT(1-Inputs!$B$38)*_xlfn.NORM.S.INV(RAND()) -> 0.27409452 | R25: =SQRT(Inputs!$B$38)*G25+SQRT(1-Inputs!$B$38)*_xlfn.NORM.S.INV(RAND()) -> -0.53623872 | S25: =SQRT(Inputs!$B$38)*H25+SQRT(1-Inputs!$B$38)*_xlfn.NORM.S.INV(RAND()) -> 0.083362588 | T25: =SQRT(Inputs!$B$38)*I25+SQRT(1-Inputs!$B$38)*_xlfn.NORM.S.INV(RAND()) -> -1.5797873 | U25: =SQRT(Inputs!$B$38)*J25+SQRT(1-Inputs!$B$38)*_xlfn.NORM.S.INV(RAND()) -> 1.225094 | ... X25: =SQRT(Inputs!$B$38)*M25+SQRT(1-Inputs!$B$38)*_xlfn.NORM.S.INV(RAND()) -> -0.51487903 | Y25: =SQRT(Inputs!$B$38)*C25+SQRT(1-Inputs!$B$38)*_xlfn.NORM.S.INV(RAND()) -> 1.8396239 | Z25: =SQRT(Inputs!$B$38)*D25+SQRT(1-Inputs!$B$38)*_xlfn.NORM.S.INV(RAND()) -> -1.434271 | AA25: =SQRT(Inputs!$B$38)*E25+SQRT(1-Inputs!$B$38)*_xlfn.NORM.S.INV(RAND()) -> 1.0106595 | AB25: =SQRT(Inputs!$B$38)*F25+SQRT(1-Inputs!$B$38)*_xlfn.NORM.S.INV(RAND()) -> 0.38956574 | AC25: =SQRT(Inputs!$B$38)*G25+SQRT(1-Inputs!$B$38)*_xlfn.NORM.S.INV(RAND()) -> -1.3324367 | AD25: =SQRT(Inputs!$B$38)*H25+SQRT(1-Inputs!$B$38)*_xlfn.NORM.S.INV(RAND()) -> 0.36363543 | AE25: =SQRT(Inputs!$B$38)*I25+SQRT(1-Inputs!$B$38)*_xlfn.NORM.S.INV(RAND()) -> 0.17473972 | AF25: =SQRT(Inputs!$B$38)*J25+SQRT(1-Inputs!$B$38)*_xlfn.NORM.S.INV(RAND()) -> 0.80206195 | ... AI25: =SQRT(Inputs!$B$38)*M25+SQRT(1-Inputs!$B$38)*_xlfn.NORM.S.INV(RAND()) -> 0.63434055 | AJ25: =SQRT(Inputs!$B$38)*C25+SQRT(1-Inputs!$B$38)*_xlfn.NORM.S.INV(RAND()) -> 0.016148265 | AK25: =SQRT(Inputs!$B$38)*D25+SQRT(1-Inputs!$B$38)*_xlfn.NORM.S.INV(RAND()) -> 0.271778 | AL25: =SQRT(Inputs!$B$38)*E25+SQRT(1-Inputs!$B$38)*_xlfn.NORM.S.INV(RAND()) -> 0.10790194 | AM25: =SQRT(Inputs!$B$38)*F25+SQRT(1-Inputs!$B$38)*_xlfn.NORM.S.INV(RAND()) -> 2.5511708 | AN25: =SQRT(Inputs!$B$38)*G25+SQRT(1-Inputs!$B$38)*_xlfn.NORM.S.INV(RAND()) -> 0.6246389 | AO25: =SQRT(Inputs!$B$38)*H25+SQRT(1-Inputs!$B$38)*_xlfn.NORM.S.INV(RAND()) -> -0.27652451 | AP25: =SQRT(Inputs!$B$38)*I25+SQRT(1-Inputs!$B$38)*_xlfn.NORM.S.INV(RAND()) -> -1.1599674 | AQ25: =SQRT(Inputs!$B$38)*J25+SQRT(1-Inputs!$B$38)*_xlfn.NORM.S.INV(RAND()) -> 0.015395046 | ... AT25: =SQRT(Inputs!$B$38)*M25+SQRT(1-Inputs!$B$38)*_xlfn.NORM.S.INV(RAND()) -> 1.2692155 | AU25: =Inputs!$B$6*EXP($B$8-0.5*C$5^2+C$5*N25) -> 4973.9182 | AV25: =AU25*EXP($B$8-0.5*D$5^2+D$5*O25) -> 5328.0168 | AW25: =AV25*EXP($B$8-0.5*E$5^2+E$5*P25) -> 6898.1173 | AX25: =AW25*EXP($B$8-0.5*F$5^2+F$5*Q25) -> 8715.2984 | AY25: =AX25*EXP($B$8-0.5*G$5^2+G$5*R25) -> 10004.411 | AZ25: =AY25*EXP($B$8-0.5*H$5^2+H$5*S25) -> 12348.503 | BA25: =AZ25*EXP($B$8-0.5*I$5^2+I$5*T25) -> 12808.513 | BB25: =BA25*EXP($B$8-0.5*J$5^2+J$5*U25) -> 17729.411 | BC25: =BB25*EXP($B$8-0.5*K$5^2+K$5*V25) -> 21908.631 | ... BE25: =BD25*EXP($B$8-0.5*M$5^2+M$5*X25) -> 33672.443 | BF25: =Inputs!$B$13*EXP($B$9-0.5*C$6^2+C$6*Y25) -> 19917.826 | BG25: =BF25*EXP($B$9-0.5*D$6^2+D$6*Z25) -> 18739.455 | BH25: =BG25*EXP($B$9-0.5*E$6^2+E$6*AA25) -> 27074.57 | BI25: =BH25*EXP($B$9-0.5*F$6^2+F$6*AB25) -> 35191.47 | BJ25: =BI25*EXP($B$9-0.5*G$6^2+G$6*AC25) -> 35603.453 | BK25: =BJ25*EXP($B$9-0.5*H$6^2+H$6*AD25) -> 45914.195 | BL25: =BK25*EXP($B$9-0.5*I$6^2+I$6*AE25) -> 57691.787 | BM25: =BL25*EXP($B$9-0.5*J$6^2+J$6*AF25) -> 78345.572 | BN25: =BM25*EXP($B$9-0.5*K$6^2+K$6*AG25) -> 86073.426 | ... BP25: =BO25*EXP($B$9-0.5*M$6^2+M$6*AI25) -> 161250.02 | BQ25: =Inputs!$B$20*EXP($B$10-0.5*C$7^2+C$7*AJ25) -> 4314.1526 | BR25: =BQ25*EXP($B$10-0.5*D$7^2+D$7*AK25) -> 6381.4395 | BS25: =BR25*EXP($B$10-0.5*E$7^2+E$7*AL25) -> 9013.7459 | BT25: =BS25*EXP($B$10-0.5*F$7^2+F$7*AM25) -> 24269.151 | BU25: =BT25*EXP($B$10-0.5*G$7^2+G$7*AN25) -> 39122.008 | BV25: =BU25*EXP($B$10-0.5*H$7^2+H$7*AO25) -> 51142.452 | BW25: =BV25*EXP($B$10-0.5*I$7^2+I$7*AP25) -> 55830.541 | BX25: =BW25*EXP($B$10-0.5*J$7^2+J$7*AQ25) -> 78329.358 | BY25: =BX25*EXP($B$10-0.5*K$7^2+K$7*AR25) -> 100826.35 | ... CA25: =BZ25*EXP($B$10-0.5*M$7^2+M$7*AT25) -> 192464.34 | CB25: =(AU25*DCF!C$10-DCF!C$5*MAX(AU25*DCF!C$10,0)-MAX(AU25-Inputs!$B$6,0)/Inputs!$B$10)*DCF!C$6 -> 1042.991 | CC25: =(AV25*DCF!D$10-DCF!D$5*MAX(AV25*DCF!D$10,0)-MAX(AV25-AU25,0)/Inputs!$B$10)*DCF!D$6 -> 1212.3303 | CD25: =(AW25*DCF!E$10-DCF!E$5*MAX(AW25*DCF!E$10,0)-MAX(AW25-AV25,0)/Inputs!$B$10)*DCF!E$6 -> 1239.0138 | CE25: =(AX25*DCF!F$10-DCF!F$5*MAX(AX25*DCF!F$10,0)-MAX(AX25-AW25,0)/Inputs!$B$10)*DCF!F$6 -> 1524.4254 | CF25: =(AY25*DCF!G$10-DCF!G$5*MAX(AY25*DCF!G$10,0)-MAX(AY25-AX25,0)/Inputs!$B$10)*DCF!G$6 -> 1813.5176 | CG25: =(AZ25*DCF!H$10-DCF!H$5*MAX(AZ25*DCF!H$10,0)-MAX(AZ25-AY25,0)/Inputs!$B$10)*DCF!H$6 -> 1981.2351 | CH25: =(BA25*DCF!I$10-DCF!I$5*MAX(BA25*DCF!I$10,0)-MAX(BA25-AZ25,0)/Inputs!$B$10)*DCF!I$6 -> 2264.1904 | CI25: =(BB25*DCF!J$10-DCF!J$5*MAX(BB25*DCF!J$10,0)-MAX(BB25-BA25,0)/Inputs!$B$10)*DCF!J$6 -> 2296.7271 | CJ25: =(BC25*DCF!K$10-DCF!K$5*MAX(BC25*DCF!K$10,0)-MAX(BC25-BB25,0)/Inputs!$B$10)*DCF!K$6 -> 2941.9106 | ... CL25: =(BE25*DCF!M$10-DCF!M$5*MAX(BE25*DCF!M$10,0)-MAX(BE25-BD25,0)/Inputs!$B$10)*DCF!M$6 -> 4169.3986 | CM25: =(BF25*DCF!C$28-DCF!C$5*MAX(BF25*DCF!C$28,0)-MAX(BF25-Inputs!$B$13,0)/Inputs!$B$17)*DCF!C$6 -> 4108.6222 | CN25: =(BG25*DCF!D$28-DCF!D$5*MAX(BG25*DCF!D$28,0)-MAX(BG25-BF25,0)/Inputs!$B$17)*DCF!D$6 -> 5519.2018 | CO25: =(BH25*DCF!E$28-DCF!E$5*MAX(BH25*DCF!E$28,0)-MAX(BH25-BG25,0)/Inputs!$B$17)*DCF!E$6 -> 6025.264 | CP25: =(BI25*DCF!F$28-DCF!F$5*MAX(BI25*DCF!F$28,0)-MAX(BI25-BH25,0)/Inputs!$B$17)*DCF!F$6 -> 8075.7472 | CQ25: =(BJ25*DCF!G$28-DCF!G$5*MAX(BJ25*DCF!G$28,0)-MAX(BJ25-BI25,0)/Inputs!$B$17)*DCF!G$6 -> 9168.2946 | CR25: =(BK25*DCF!H$28-DCF!H$5*MAX(BK25*DCF!H$28,0)-MAX(BK25-BJ25,0)/Inputs!$B$17)*DCF!H$6 -> 9753.0871 | CS25: =(BL25*DCF!I$28-DCF!I$5*MAX(BL25*DCF!I$28,0)-MAX(BL25-BK25,0)/Inputs!$B$17)*DCF!I$6 -> 11875.953 | CT25: =(BM25*DCF!J$28-DCF!J$5*MAX(BM25*DCF!J$28,0)-MAX(BM25-BL25,0)/Inputs!$B$17)*DCF!J$6 -> 14739.043 | CU25: =(BN25*DCF!K$28-DCF!K$5*MAX(BN25*DCF!K$28,0)-MAX(BN25-BM25,0)/Inputs!$B$17)*DCF!K$6 -> 17230.705 | ... CW25: =(BP25*DCF!M$28-DCF!M$5*MAX(BP25*DCF!M$28,0)-MAX(BP25-BO25,0)/Inputs!$B$17)*DCF!M$6 -> 26228.803 | CX25: =(BQ25*DCF!C$46-DCF!C$5*MAX(BQ25*DCF!C$46,0)-MAX(BQ25-Inputs!$B$20,0)/Inputs!$B$24)*DCF!C$6 -> -1510.4983 | CY25: =(BR25*DCF!D$46-DCF!D$5*MAX(BR25*DCF!D$46,0)-MAX(BR25-BQ25,0)/Inputs!$B$24)*DCF!D$6 -> -1971.2571 | CZ25: =(BS25*DCF!E$46-DCF!E$5*MAX(BS25*DCF!E$46,0)-MAX(BS25-BR25,0)/Inputs!$B$24)*DCF!E$6 -> -2103.4739 | DA25: =(BT25*DCF!F$46-DCF!F$5*MAX(BT25*DCF!F$46,0)-MAX(BT25-BS25,0)/Inputs!$B$24)*DCF!F$6 -> -7322.4082 | DB25: =(BU25*DCF!G$46-DCF!G$5*MAX(BU25*DCF!G$46,0)-MAX(BU25-BT25,0)/Inputs!$B$24)*DCF!G$6 -> -6312.1946 | DC25: =(BV25*DCF!H$46-DCF!H$5*MAX(BV25*DCF!H$46,0)-MAX(BV25-BU25,0)/Inputs!$B$24)*DCF!H$6 -> -3735.2796 | DD25: =(BW25*DCF!I$46-DCF!I$5*MAX(BW25*DCF!I$46,0)-MAX(BW25-BV25,0)/Inputs!$B$24)*DCF!I$6 -> -56.340943 | DE25: =(BX25*DCF!J$46-DCF!J$5*MAX(BX25*DCF!J$46,0)-MAX(BX25-BW25,0)/Inputs!$B$24)*DCF!J$6 -> -2680.6187 | DF25: =(BY25*DCF!K$46-DCF!K$5*MAX(BY25*DCF!K$46,0)-MAX(BY25-BX25,0)/Inputs!$B$24)*DCF!K$6 -> 248.37354 | ... DH25: =(CA25*DCF!M$46-DCF!M$5*MAX(CA25*DCF!M$46,0)-MAX(CA25-BZ25,0)/Inputs!$B$24)*DCF!M$6 -> -2287.2271 | DI25: =SUM(CB25:CL25)+BE25*DCF!M$10*(1+Inputs!$B$30)*(1-Inputs!$B$33)*(1-Inputs!$B$30/Inputs!$B$31)/(Inputs!$B$29-Inputs!$B$30)*DCF!M$6 -> 117648.99 | DJ25: =SUM(CM25:CW25)+BP25*DCF!M$28*(1+Inputs!$B$30)*(1-Inputs!$B$33)*(1-Inputs!$B$30/Inputs!$B$31)/(Inputs!$B$29-Inputs!$B$30)*DCF!M$6 -> 731342.66 | DK25: =SUM(CX25:DH25)+CA25*DCF!M$46*(1+Inputs!$B$30)*(1-Inputs!$B$33)*(1-Inputs!$B$30/Inputs!$B$31)/(Inputs!$B$29-Inputs!$B$30)*DCF!M$6 -> 275471.76 | DM25: =DI25+DJ25+DK25+Inputs!$B$34+Inputs!$B$36-Inputs!$B$35 -> 1201314.4
... A1013: 1000 | C1013: =_xlfn.NORM.S.INV(RAND()) -> 1.9928056 | D1013: =_xlfn.NORM.S.INV(RAND()) -> -0.24450079 | E1013: =_xlfn.NORM.S.INV(RAND()) -> 1.8255373 | F1013: =_xlfn.NORM.S.INV(RAND()) -> -0.07004776 | G1013: =_xlfn.NORM.S.INV(RAND()) -> -0.54212205 | H1013: =_xlfn.NORM.S.INV(RAND()) -> -0.99500061 | I1013: =_xlfn.NORM.S.INV(RAND()) -> 0.43428794 | J1013: =_xlfn.NORM.S.INV(RAND()) -> -1.5232385 | ... M1013: =_xlfn.NORM.S.INV(RAND()) -> 0.098951404 | N1013: =SQRT(Inputs!$B$38)*C1013+SQRT(1-Inputs!$B$38)*_xlfn.NORM.S.INV(RAND()) -> 0.64228228 | O1013: =SQRT(Inputs!$B$38)*D1013+SQRT(1-Inputs!$B$38)*_xlfn.NORM.S.INV(RAND()) -> -0.5188185 | P1013: =SQRT(Inputs!$B$38)*E1013+SQRT(1-Inputs!$B$38)*_xlfn.NORM.S.INV(RAND()) -> 0.80110981 | Q1013: =SQRT(Inputs!$B$38)*F1013+SQRT(1-Inputs!$B$38)*_xlfn.NORM.S.INV(RAND()) -> -1.7171829 | R1013: =SQRT(Inputs!$B$38)*G1013+SQRT(1-Inputs!$B$38)*_xlfn.NORM.S.INV(RAND()) -> 0.2026943 | S1013: =SQRT(Inputs!$B$38)*H1013+SQRT(1-Inputs!$B$38)*_xlfn.NORM.S.INV(RAND()) -> -0.94952716 | T1013: =SQRT(Inputs!$B$38)*I1013+SQRT(1-Inputs!$B$38)*_xlfn.NORM.S.INV(RAND()) -> -0.50532757 | U1013: =SQRT(Inputs!$B$38)*J1013+SQRT(1-Inputs!$B$38)*_xlfn.NORM.S.INV(RAND()) -> -2.0569961 | ... X1013: =SQRT(Inputs!$B$38)*M1013+SQRT(1-Inputs!$B$38)*_xlfn.NORM.S.INV(RAND()) -> 0.23091092 | Y1013: =SQRT(Inputs!$B$38)*C1013+SQRT(1-Inputs!$B$38)*_xlfn.NORM.S.INV(RAND()) -> 1.6343 | Z1013: =SQRT(Inputs!$B$38)*D1013+SQRT(1-Inputs!$B$38)*_xlfn.NORM.S.INV(RAND()) -> -0.93037531 | AA1013: =SQRT(Inputs!$B$38)*E1013+SQRT(1-Inputs!$B$38)*_xlfn.NORM.S.INV(RAND()) -> 0.6116583 | AB1013: =SQRT(Inputs!$B$38)*F1013+SQRT(1-Inputs!$B$38)*_xlfn.NORM.S.INV(RAND()) -> 0.060040657 | AC1013: =SQRT(Inputs!$B$38)*G1013+SQRT(1-Inputs!$B$38)*_xlfn.NORM.S.INV(RAND()) -> -0.76293362 | AD1013: =SQRT(Inputs!$B$38)*H1013+SQRT(1-Inputs!$B$38)*_xlfn.NORM.S.INV(RAND()) -> -0.60967963 | AE1013: =SQRT(Inputs!$B$38)*I1013+SQRT(1-Inputs!$B$38)*_xlfn.NORM.S.INV(RAND()) -> 0.61705921 | AF1013: =SQRT(Inputs!$B$38)*J1013+SQRT(1-Inputs!$B$38)*_xlfn.NORM.S.INV(RAND()) -> -1.4993561 | ... AI1013: =SQRT(Inputs!$B$38)*M1013+SQRT(1-Inputs!$B$38)*_xlfn.NORM.S.INV(RAND()) -> 1.2041283 | AJ1013: =SQRT(Inputs!$B$38)*C1013+SQRT(1-Inputs!$B$38)*_xlfn.NORM.S.INV(RAND()) -> 1.7575717 | AK1013: =SQRT(Inputs!$B$38)*D1013+SQRT(1-Inputs!$B$38)*_xlfn.NORM.S.INV(RAND()) -> 0.18864222 | AL1013: =SQRT(Inputs!$B$38)*E1013+SQRT(1-Inputs!$B$38)*_xlfn.NORM.S.INV(RAND()) -> 1.0310787 | AM1013: =SQRT(Inputs!$B$38)*F1013+SQRT(1-Inputs!$B$38)*_xlfn.NORM.S.INV(RAND()) -> 0.22983919 | AN1013: =SQRT(Inputs!$B$38)*G1013+SQRT(1-Inputs!$B$38)*_xlfn.NORM.S.INV(RAND()) -> 0.10714038 | AO1013: =SQRT(Inputs!$B$38)*H1013+SQRT(1-Inputs!$B$38)*_xlfn.NORM.S.INV(RAND()) -> -0.29617699 | AP1013: =SQRT(Inputs!$B$38)*I1013+SQRT(1-Inputs!$B$38)*_xlfn.NORM.S.INV(RAND()) -> 0.080799873 | AQ1013: =SQRT(Inputs!$B$38)*J1013+SQRT(1-Inputs!$B$38)*_xlfn.NORM.S.INV(RAND()) -> 0.54095073 | ... AT1013: =SQRT(Inputs!$B$38)*M1013+SQRT(1-Inputs!$B$38)*_xlfn.NORM.S.INV(RAND()) -> 0.3843909 | AU1013: =Inputs!$B$6*EXP($B$8-0.5*C$5^2+C$5*N1013) -> 5505.9281 | AV1013: =AU1013*EXP($B$8-0.5*D$5^2+D$5*O1013) -> 6209.779 | AW1013: =AV1013*EXP($B$8-0.5*E$5^2+E$5*P1013) -> 8435.724 | AX1013: =AW1013*EXP($B$8-0.5*F$5^2+F$5*Q1013) -> 8310.5923 | AY1013: =AX1013*EXP($B$8-0.5*G$5^2+G$5*R1013) -> 10399.685 | AZ1013: =AY1013*EXP($B$8-0.5*H$5^2+H$5*S1013) -> 11456.338 | BA1013: =AZ1013*EXP($B$8-0.5*I$5^2+I$5*T1013) -> 13297.432 | BB1013: =BA1013*EXP($B$8-0.5*J$5^2+J$5*U1013) -> 13248.102 | BC1013: =BB1013*EXP($B$8-0.5*K$5^2+K$5*V1013) -> 17381.298 | ... BE1013: =BD1013*EXP($B$8-0.5*M$5^2+M$5*X1013) -> 26602.961 | BF1013: =Inputs!$B$13*EXP($B$9-0.5*C$6^2+C$6*Y1013) -> 19123.351 | BG1013: =BF1013*EXP($B$9-0.5*D$6^2+D$6*Z1013) -> 19704.526 | BH1013: =BG1013*EXP($B$9-0.5*E$6^2+E$6*AA1013) -> 26645.886 | BI1013: =BH1013*EXP($B$9-0.5*F$6^2+F$6*AB1013) -> 32921.412 | BJ1013: =BI1013*EXP($B$9-0.5*G$6^2+G$6*AC1013) -> 36156.383 | BK1013: =BJ1013*EXP($B$9-0.5*H$6^2+H$6*AD1013) -> 40840.526 | BL1013: =BK1013*EXP($B$9-0.5*I$6^2+I$6*AE1013) -> 54344.111 | BM1013: =BL1013*EXP($B$9-0.5*J$6^2+J$6*AF1013) -> 55448.313 | BN1013: =BM1013*EXP($B$9-0.5*K$6^2+K$6*AG1013) -> 70280.008 | ... BP1013: =BO1013*EXP($B$9-0.5*M$6^2+M$6*AI1013) -> 127441.67 | BQ1013: =Inputs!$B$20*EXP($B$10-0.5*C$7^2+C$7*AJ1013) -> 8000.8971 | BR1013: =BQ1013*EXP($B$10-0.5*D$7^2+D$7*AK1013) -> 11526.448 | BS1013: =BR1013*EXP($B$10-0.5*E$7^2+E$7*AL1013) -> 21224.163 | BT1013: =BS1013*EXP($B$10-0.5*F$7^2+F$7*AM1013) -> 31082.204 | BU1013: =BT1013*EXP($B$10-0.5*G$7^2+G$7*AN1013) -> 44207.548 | BV1013: =BU1013*EXP($B$10-0.5*H$7^2+H$7*AO1013) -> 57535.24 | BW1013: =BV1013*EXP($B$10-0.5*I$7^2+I$7*AP1013) -> 81671.998 | BX1013: =BW1013*EXP($B$10-0.5*J$7^2+J$7*AQ1013) -> 127316.1 | BY1013: =BX1013*EXP($B$10-0.5*K$7^2+K$7*AR1013) -> 154525.52 | ... CA1013: =BZ1013*EXP($B$10-0.5*M$7^2+M$7*AT1013) -> 340805.49 | CB1013: =(AU1013*DCF!C$10-DCF!C$5*MAX(AU1013*DCF!C$10,0)-MAX(AU1013-Inputs!$B$6,0)/Inputs!$B$10)*DCF!C$6 -> 1039.1977 | CC1013: =(AV1013*DCF!D$10-DCF!D$5*MAX(AV1013*DCF!D$10,0)-MAX(AV1013-AU1013,0)/Inputs!$B$10)*DCF!D$6 -> 1341.9759 | CD1013: =(AW1013*DCF!E$10-DCF!E$5*MAX(AW1013*DCF!E$10,0)-MAX(AW1013-AV1013,0)/Inputs!$B$10)*DCF!E$6 -> 1446.2994 | CE1013: =(AX1013*DCF!F$10-DCF!F$5*MAX(AX1013*DCF!F$10,0)-MAX(AX1013-AW1013,0)/Inputs!$B$10)*DCF!F$6 -> 1814.1891 | CF1013: =(AY1013*DCF!G$10-DCF!G$5*MAX(AY1013*DCF!G$10,0)-MAX(AY1013-AX1013,0)/Inputs!$B$10)*DCF!G$6 -> 1741.1898 | CG1013: =(AZ1013*DCF!H$10-DCF!H$5*MAX(AZ1013*DCF!H$10,0)-MAX(AZ1013-AY1013,0)/Inputs!$B$10)*DCF!H$6 -> 2036.6285 | CH1013: =(BA1013*DCF!I$10-DCF!I$5*MAX(BA1013*DCF!I$10,0)-MAX(BA1013-AZ1013,0)/Inputs!$B$10)*DCF!I$6 -> 2126.9517 | CI1013: =(BB1013*DCF!J$10-DCF!J$5*MAX(BB1013*DCF!J$10,0)-MAX(BB1013-BA1013,0)/Inputs!$B$10)*DCF!J$6 -> 2273.405 | CJ1013: =(BC1013*DCF!K$10-DCF!K$5*MAX(BC1013*DCF!K$10,0)-MAX(BC1013-BB1013,0)/Inputs!$B$10)*DCF!K$6 -> 2219.5253 | ... CL1013: =(BE1013*DCF!M$10-DCF!M$5*MAX(BE1013*DCF!M$10,0)-MAX(BE1013-BD1013,0)/Inputs!$B$10)*DCF!M$6 -> 3115.5434 | CM1013: =(BF1013*DCF!C$28-DCF!C$5*MAX(BF1013*DCF!C$28,0)-MAX(BF1013-Inputs!$B$13,0)/Inputs!$B$17)*DCF!C$6 -> 4049.6352 | CN1013: =(BG1013*DCF!D$28-DCF!D$5*MAX(BG1013*DCF!D$28,0)-MAX(BG1013-BF1013,0)/Inputs!$B$17)*DCF!D$6 -> 5679.4461 | CO1013: =(BH1013*DCF!E$28-DCF!E$5*MAX(BH1013*DCF!E$28,0)-MAX(BH1013-BG1013,0)/Inputs!$B$17)*DCF!E$6 -> 6178.543 | CP1013: =(BI1013*DCF!F$28-DCF!F$5*MAX(BI1013*DCF!F$28,0)-MAX(BI1013-BH1013,0)/Inputs!$B$17)*DCF!F$6 -> 7794.7375 | CQ1013: =(BJ1013*DCF!G$28-DCF!G$5*MAX(BJ1013*DCF!G$28,0)-MAX(BJ1013-BI1013,0)/Inputs!$B$17)*DCF!G$6 -> 8836.9577 | CR1013: =(BK1013*DCF!H$28-DCF!H$5*MAX(BK1013*DCF!H$28,0)-MAX(BK1013-BJ1013,0)/Inputs!$B$17)*DCF!H$6 -> 9372.5282 | CS1013: =(BL1013*DCF!I$28-DCF!I$5*MAX(BL1013*DCF!I$28,0)-MAX(BL1013-BK1013,0)/Inputs!$B$17)*DCF!I$6 -> 10841.004 | CT1013: =(BM1013*DCF!J$28-DCF!J$5*MAX(BM1013*DCF!J$28,0)-MAX(BM1013-BL1013,0)/Inputs!$B$17)*DCF!J$6 -> 12223.169 | CU1013: =(BN1013*DCF!K$28-DCF!K$5*MAX(BN1013*DCF!K$28,0)-MAX(BN1013-BM1013,0)/Inputs!$B$17)*DCF!K$6 -> 13025.274 | ... CW1013: =(BP1013*DCF!M$28-DCF!M$5*MAX(BP1013*DCF!M$28,0)-MAX(BP1013-BO1013,0)/Inputs!$B$17)*DCF!M$6 -> 20099.873 | CX1013: =(BQ1013*DCF!C$46-DCF!C$5*MAX(BQ1013*DCF!C$46,0)-MAX(BQ1013-Inputs!$B$20,0)/Inputs!$B$24)*DCF!C$6 -> -4064.8248 | CY1013: =(BR1013*DCF!D$46-DCF!D$5*MAX(BR1013*DCF!D$46,0)-MAX(BR1013-BQ1013,0)/Inputs!$B$24)*DCF!D$6 -> -3471.619 | CZ1013: =(BS1013*DCF!E$46-DCF!E$5*MAX(BS1013*DCF!E$46,0)-MAX(BS1013-BR1013,0)/Inputs!$B$24)*DCF!E$6 -> -6332.3664 | DA1013: =(BT1013*DCF!F$46-DCF!F$5*MAX(BT1013*DCF!F$46,0)-MAX(BT1013-BS1013,0)/Inputs!$B$24)*DCF!F$6 -> -5853.2273 | DB1013: =(BU1013*DCF!G$46-DCF!G$5*MAX(BU1013*DCF!G$46,0)-MAX(BU1013-BT1013,0)/Inputs!$B$24)*DCF!G$6 -> -5902.1607 | DC1013: =(BV1013*DCF!H$46-DCF!H$5*MAX(BV1013*DCF!H$46,0)-MAX(BV1013-BU1013,0)/Inputs!$B$24)*DCF!H$6 -> -4141.4986 | DD1013: =(BW1013*DCF!I$46-DCF!I$5*MAX(BW1013*DCF!I$46,0)-MAX(BW1013-BV1013,0)/Inputs!$B$24)*DCF!I$6 -> -5042.4832 | DE1013: =(BX1013*DCF!J$46-DCF!J$5*MAX(BX1013*DCF!J$46,0)-MAX(BX1013-BW1013,0)/Inputs!$B$24)*DCF!J$6 -> -6763.5111 | DF1013: =(BY1013*DCF!K$46-DCF!K$5*MAX(BY1013*DCF!K$46,0)-MAX(BY1013-BX1013,0)/Inputs!$B$24)*DCF!K$6 -> 2161.4297 | ... DH1013: =(CA1013*DCF!M$46-DCF!M$5*MAX(CA1013*DCF!M$46,0)-MAX(CA1013-BZ1013,0)/Inputs!$B$24)*DCF!M$6 -> 2842.3391 | DI1013: =SUM(CB1013:CL1013)+BE1013*DCF!M$10*(1+Inputs!$B$30)*(1-Inputs!$B$33)*(1-Inputs!$B$30/Inputs!$B$31)/(Inputs!$B$29-Inputs!$B$30)*DCF!M$6 -> 95896.093 | DJ1013: =SUM(CM1013:CW1013)+BP1013*DCF!M$28*(1+Inputs!$B$30)*(1-Inputs!$B$33)*(1-Inputs!$B$30/Inputs!$B$31)/(Inputs!$B$29-Inputs!$B$30)*DCF!M$6 -> 586751.74 | DK1013: =SUM(CX1013:DH1013)+CA1013*DCF!M$46*(1+Inputs!$B$30)*(1-Inputs!$B$33)*(1-Inputs!$B$30/Inputs!$B$31)/(Inputs!$B$29-Inputs!$B$30)*DCF!M$6 -> 489710.93 | DM1013: =DI1013+DJ1013+DK1013+Inputs!$B$34+Inputs!$B$36-Inputs!$B$35 -> 1249209.8

Sheet Inversion
A1: Inversion — the discount rate a price implies (paper Section 6)
A2: Cash flows held fixed (they do not depend on the WACC); the option layer held at its base value, as in the paper. Each row recomputes total value at that rate; the implied rate interpolates where value crosses the target. For more digits, use Goal Seek (Data > What-If) on the Inputs WACC cell.
A4: Target price ($) | B4: =Inputs!$B$74 -> 135
A5: Target cap ($M) | B5: =B4*Inputs!$B$37 -> 1767285
A6: Option layer ($M) | B6: =Options!$B$27 -> 65669.75 | C6: held constant across rates (paper convention)
A8: WACC | B8: PV of FCFF ($M) | C8: PV of TV ($M) | D8: Equity ($M) | E8: Total value ($M) | F8: $ / share | H8: One-lever implied values (paper Table 4; reproduce with Goal Seek on the Inputs tab)
A9: 0.05 | B9: =SUMPRODUCT(DCF!$C$14:$M$14,1/(1+$A9)^DCF!$C$4:$M$4)+SUMPRODUCT(DCF!$C$32:$M$32,1/(1+$A9)^DCF!$C$4:$M$4)+SUMPRODUCT(DCF!$C$50:$M$50,1/(1+$A9)^DCF!$C$4:$M$4) -> 157358.52 | C9: =(DCF!$B$21+DCF!$B$39+DCF!$B$57)/($A9-Inputs!$B$30)/(1+$A9)^11 -> 9428540.3 | D9: =B9+C9+Inputs!$B$34+Inputs!$B$36-Inputs!$B$35 -> 9662749.9 | E9: =D9+$B$6 -> 9728419.6 | F9: =E9/Inputs!$B$37 -> 743.138 | H9: Starlink terminal margin | I9: 60% -> 137% (no feasible value)
A10: 0.0525 | B10: =SUMPRODUCT(DCF!$C$14:$M$14,1/(1+$A10)^DCF!$C$4:$M$4)+SUMPRODUCT(DCF!$C$32:$M$32,1/(1+$A10)^DCF!$C$4:$M$4)+SUMPRODUCT(DCF!$C$50:$M$50,1/(1+$A10)^DCF!$C$4:$M$4) -> 154299.7 | C10: =(DCF!$B$21+DCF!$B$39+DCF!$B$57)/($A10-Inputs!$B$30)/(1+$A10)^11 -> 5857161.4 | D10: =B10+C10+Inputs!$B$34+Inputs!$B$36-Inputs!$B$35 -> 6088312.1 | E10: =D10+$B$6 -> 6153981.8 | F10: =E10/Inputs!$B$37 -> 470.09257 | H10: xAI terminal margin | I10: 25% -> 86% (above every comparable)
A11: 0.055 | B11: =SUMPRODUCT(DCF!$C$14:$M$14,1/(1+$A11)^DCF!$C$4:$M$4)+SUMPRODUCT(DCF!$C$32:$M$32,1/(1+$A11)^DCF!$C$4:$M$4)+SUMPRODUCT(DCF!$C$50:$M$50,1/(1+$A11)^DCF!$C$4:$M$4) -> 151313.51 | C11: =(DCF!$B$21+DCF!$B$39+DCF!$B$57)/($A11-Inputs!$B$30)/(1+$A11)^11 -> 4188654.3 | D11: =B11+C11+Inputs!$B$34+Inputs!$B$36-Inputs!$B$35 -> 4416818.8 | E11: =D11+$B$6 -> 4482488.6 | F11: =E11/Inputs!$B$37 -> 342.40994 | H11: Launch 2036 revenue | I11: $40B -> $266B (the market is $14-41B/yr)
A12: 0.0575 | B12: =SUMPRODUCT(DCF!$C$14:$M$14,1/(1+$A12)^DCF!$C$4:$M$4)+SUMPRODUCT(DCF!$C$32:$M$32,1/(1+$A12)^DCF!$C$4:$M$4)+SUMPRODUCT(DCF!$C$50:$M$50,1/(1+$A12)^DCF!$C$4:$M$4) -> 148397.98 | C12: =(DCF!$B$21+DCF!$B$39+DCF!$B$57)/($A12-Inputs!$B$30)/(1+$A12)^11 -> 3223653.3 | D12: =B12+C12+Inputs!$B$34+Inputs!$B$36-Inputs!$B$35 -> 3448902.3 | E12: =D12+$B$6 -> 3514572.1 | F12: =E12/Inputs!$B$37 -> 268.47239 | H12: xAI 2036 revenue | I12: $160B -> $640B (about 30x OpenAI)
A13: 0.06 | B13: =SUMPRODUCT(DCF!$C$14:$M$14,1/(1+$A13)^DCF!$C$4:$M$4)+SUMPRODUCT(DCF!$C$32:$M$32,1/(1+$A13)^DCF!$C$4:$M$4)+SUMPRODUCT(DCF!$C$50:$M$50,1/(1+$A13)^DCF!$C$4:$M$4) -> 145551.22 | C13: =(DCF!$B$21+DCF!$B$39+DCF!$B$57)/($A13-Inputs!$B$30)/(1+$A13)^11 -> 2595687.6 | D13: =B13+C13+Inputs!$B$34+Inputs!$B$36-Inputs!$B$35 -> 2818089.8 | E13: =D13+$B$6 -> 2883759.6 | F13: =E13/Inputs!$B$37 -> 220.28566 | H13: Starlink 2036 revenue | I13: $120B -> $358B (above the supported range)
A14: 0.0625 | B14: =SUMPRODUCT(DCF!$C$14:$M$14,1/(1+$A14)^DCF!$C$4:$M$4)+SUMPRODUCT(DCF!$C$32:$M$32,1/(1+$A14)^DCF!$C$4:$M$4)+SUMPRODUCT(DCF!$C$50:$M$50,1/(1+$A14)^DCF!$C$4:$M$4) -> 142771.37 | C14: =(DCF!$B$21+DCF!$B$39+DCF!$B$57)/($A14-Inputs!$B$30)/(1+$A14)^11 -> 2155134.6 | D14: =B14+C14+Inputs!$B$34+Inputs!$B$36-Inputs!$B$35 -> 2374757 | E14: =D14+$B$6 -> 2440426.7 | F14: =E14/Inputs!$B$37 -> 186.42019 | H14: Discount rate | I14: 8.25% -> 6.86% (inside estimation error)
A15: 0.065 | B15: =SUMPRODUCT(DCF!$C$14:$M$14,1/(1+$A15)^DCF!$C$4:$M$4)+SUMPRODUCT(DCF!$C$32:$M$32,1/(1+$A15)^DCF!$C$4:$M$4)+SUMPRODUCT(DCF!$C$50:$M$50,1/(1+$A15)^DCF!$C$4:$M$4) -> 140056.66 | C15: =(DCF!$B$21+DCF!$B$39+DCF!$B$57)/($A15-Inputs!$B$30)/(1+$A15)^11 -> 1829498.3 | D15: =B15+C15+Inputs!$B$34+Inputs!$B$36-Inputs!$B$35 -> 2046406 | E15: =D15+$B$6 -> 2112075.7 | F15: =E15/Inputs!$B$37 -> 161.338
A16: 0.0675 | B16: =SUMPRODUCT(DCF!$C$14:$M$14,1/(1+$A16)^DCF!$C$4:$M$4)+SUMPRODUCT(DCF!$C$32:$M$32,1/(1+$A16)^DCF!$C$4:$M$4)+SUMPRODUCT(DCF!$C$50:$M$50,1/(1+$A16)^DCF!$C$4:$M$4) -> 137405.34 | C16: =(DCF!$B$21+DCF!$B$39+DCF!$B$57)/($A16-Inputs!$B$30)/(1+$A16)^11 -> 1579387.1 | D16: =B16+C16+Inputs!$B$34+Inputs!$B$36-Inputs!$B$35 -> 1793643.5 | E16: =D16+$B$6 -> 1859313.2 | F16: =E16/Inputs!$B$37 -> 142.02988
A17: 0.07 | B17: =SUMPRODUCT(DCF!$C$14:$M$14,1/(1+$A17)^DCF!$C$4:$M$4)+SUMPRODUCT(DCF!$C$32:$M$32,1/(1+$A17)^DCF!$C$4:$M$4)+SUMPRODUCT(DCF!$C$50:$M$50,1/(1+$A17)^DCF!$C$4:$M$4) -> 134815.73 | C17: =(DCF!$B$21+DCF!$B$39+DCF!$B$57)/($A17-Inputs!$B$30)/(1+$A17)^11 -> 1381554.6 | D17: =B17+C17+Inputs!$B$34+Inputs!$B$36-Inputs!$B$35 -> 1593221.3 | E17: =D17+$B$6 -> 1658891.1 | F17: =E17/Inputs!$B$37 -> 126.71997
A18: 0.0725 | B18: =SUMPRODUCT(DCF!$C$14:$M$14,1/(1+$A18)^DCF!$C$4:$M$4)+SUMPRODUCT(DCF!$C$32:$M$32,1/(1+$A18)^DCF!$C$4:$M$4)+SUMPRODUCT(DCF!$C$50:$M$50,1/(1+$A18)^DCF!$C$4:$M$4) -> 132286.19 | C18: =(DCF!$B$21+DCF!$B$39+DCF!$B$57)/($A18-Inputs!$B$30)/(1+$A18)^11 -> 1221397 | D18: =B18+C18+Inputs!$B$34+Inputs!$B$36-Inputs!$B$35 -> 1430534.2 | E18: =D18+$B$6 -> 1496203.9 | F18: =E18/Inputs!$B$37 -> 114.29256
A19: 0.075 | B19: =SUMPRODUCT(DCF!$C$14:$M$14,1/(1+$A19)^DCF!$C$4:$M$4)+SUMPRODUCT(DCF!$C$32:$M$32,1/(1+$A19)^DCF!$C$4:$M$4)+SUMPRODUCT(DCF!$C$50:$M$50,1/(1+$A19)^DCF!$C$4:$M$4) -> 129815.13 | C19: =(DCF!$B$21+DCF!$B$39+DCF!$B$57)/($A19-Inputs!$B$30)/(1+$A19)^11 -> 1089278.7 | D19: =B19+C19+Inputs!$B$34+Inputs!$B$36-Inputs!$B$35 -> 1295944.8 | E19: =D19+$B$6 -> 1361614.5 | F19: =E19/Inputs!$B$37 -> 104.0115
A20: 0.0775 | B20: =SUMPRODUCT(DCF!$C$14:$M$14,1/(1+$A20)^DCF!$C$4:$M$4)+SUMPRODUCT(DCF!$C$32:$M$32,1/(1+$A20)^DCF!$C$4:$M$4)+SUMPRODUCT(DCF!$C$50:$M$50,1/(1+$A20)^DCF!$C$4:$M$4) -> 127401.01 | C20: =(DCF!$B$21+DCF!$B$39+DCF!$B$57)/($A20-Inputs!$B$30)/(1+$A20)^11 -> 978585.28 | D20: =B20+C20+Inputs!$B$34+Inputs!$B$36-Inputs!$B$35 -> 1182837.3 | E20: =D20+$B$6 -> 1248507 | F20: =E20/Inputs!$B$37 -> 95.371403
A21: 0.08 | B21: =SUMPRODUCT(DCF!$C$14:$M$14,1/(1+$A21)^DCF!$C$4:$M$4)+SUMPRODUCT(DCF!$C$32:$M$32,1/(1+$A21)^DCF!$C$4:$M$4)+SUMPRODUCT(DCF!$C$50:$M$50,1/(1+$A21)^DCF!$C$4:$M$4) -> 125042.34 | C21: =(DCF!$B$21+DCF!$B$39+DCF!$B$57)/($A21-Inputs!$B$30)/(1+$A21)^11 -> 884625.95 | D21: =B21+C21+Inputs!$B$34+Inputs!$B$36-Inputs!$B$35 -> 1086519.3 | E21: =D21+$B$6 -> 1152189 | F21: =E21/Inputs!$B$37 -> 88.01383
A22: 0.0825 | B22: =SUMPRODUCT(DCF!$C$14:$M$14,1/(1+$A22)^DCF!$C$4:$M$4)+SUMPRODUCT(DCF!$C$32:$M$32,1/(1+$A22)^DCF!$C$4:$M$4)+SUMPRODUCT(DCF!$C$50:$M$50,1/(1+$A22)^DCF!$C$4:$M$4) -> 122737.66 | C22: =(DCF!$B$21+DCF!$B$39+DCF!$B$57)/($A22-Inputs!$B$30)/(1+$A22)^11 -> 803981.6 | D22: =B22+C22+Inputs!$B$34+Inputs!$B$36-Inputs!$B$35 -> 1003570.3 | E22: =D22+$B$6 -> 1069240 | F22: =E22/Inputs!$B$37 -> 81.677489
A23: 0.085 | B23: =SUMPRODUCT(DCF!$C$14:$M$14,1/(1+$A23)^DCF!$C$4:$M$4)+SUMPRODUCT(DCF!$C$32:$M$32,1/(1+$A23)^DCF!$C$4:$M$4)+SUMPRODUCT(DCF!$C$50:$M$50,1/(1+$A23)^DCF!$C$4:$M$4) -> 120485.57 | C23: =(DCF!$B$21+DCF!$B$39+DCF!$B$57)/($A23-Inputs!$B$30)/(1+$A23)^11 -> 734101.46 | D23: =B23+C23+Inputs!$B$34+Inputs!$B$36-Inputs!$B$35 -> 931438.03 | E23: =D23+$B$6 -> 997107.78 | F23: =E23/Inputs!$B$37 -> 76.167426
A24: 0.0875 | B24: =SUMPRODUCT(DCF!$C$14:$M$14,1/(1+$A24)^DCF!$C$4:$M$4)+SUMPRODUCT(DCF!$C$32:$M$32,1/(1+$A24)^DCF!$C$4:$M$4)+SUMPRODUCT(DCF!$C$50:$M$50,1/(1+$A24)^DCF!$C$4:$M$4) -> 118284.68 | C24: =(DCF!$B$21+DCF!$B$39+DCF!$B$57)/($A24-Inputs!$B$30)/(1+$A24)^11 -> 673044.04 | D24: =B24+C24+Inputs!$B$34+Inputs!$B$36-Inputs!$B$35 -> 868179.73 | E24: =D24+$B$6 -> 933849.48 | F24: =E24/Inputs!$B$37 -> 71.335229
A25: 0.09 | B25: =SUMPRODUCT(DCF!$C$14:$M$14,1/(1+$A25)^DCF!$C$4:$M$4)+SUMPRODUCT(DCF!$C$32:$M$32,1/(1+$A25)^DCF!$C$4:$M$4)+SUMPRODUCT(DCF!$C$50:$M$50,1/(1+$A25)^DCF!$C$4:$M$4) -> 116133.68 | C25: =(DCF!$B$21+DCF!$B$39+DCF!$B$57)/($A25-Inputs!$B$30)/(1+$A25)^11 -> 619305.56 | D25: =B25+C25+Inputs!$B$34+Inputs!$B$36-Inputs!$B$35 -> 812290.25 | E25: =D25+$B$6 -> 877960 | F25: =E25/Inputs!$B$37 -> 67.065923
A26: 0.0925 | B26: =SUMPRODUCT(DCF!$C$14:$M$14,1/(1+$A26)^DCF!$C$4:$M$4)+SUMPRODUCT(DCF!$C$32:$M$32,1/(1+$A26)^DCF!$C$4:$M$4)+SUMPRODUCT(DCF!$C$50:$M$50,1/(1+$A26)^DCF!$C$4:$M$4) -> 114031.27 | C26: =(DCF!$B$21+DCF!$B$39+DCF!$B$57)/($A26-Inputs!$B$30)/(1+$A26)^11 -> 571703.28 | D26: =B26+C26+Inputs!$B$34+Inputs!$B$36-Inputs!$B$35 -> 762585.55 | E26: =D26+$B$6 -> 828255.3 | F26: =E26/Inputs!$B$37 -> 63.269063
... A37: 0.12 | B37: =SUMPRODUCT(DCF!$C$14:$M$14,1/(1+$A37)^DCF!$C$4:$M$4)+SUMPRODUCT(DCF!$C$32:$M$32,1/(1+$A37)^DCF!$C$4:$M$4)+SUMPRODUCT(DCF!$C$50:$M$50,1/(1+$A37)^DCF!$C$4:$M$4) -> 93777.095 | C37: =(DCF!$B$21+DCF!$B$39+DCF!$B$57)/($A37-Inputs!$B$30)/(1+$A37)^11 -> 274162.62 | D37: =B37+C37+Inputs!$B$34+Inputs!$B$36-Inputs!$B$35 -> 444790.72 | E37: =D37+$B$6 -> 510460.47 | F37: =E37/Inputs!$B$37 -> 38.993237
A39: Implied WACC | B39: =INDEX(A9:A37,MATCH($B$5,E9:E37,-1))+(INDEX(E9:E37,MATCH($B$5,E9:E37,-1))-$B$5)/(INDEX(E9:E37,MATCH($B$5,E9:E37,-1))-INDEX(E9:E37,MATCH($B$5,E9:E37,-1)+1))*0.0025 -> 0.06864793 | C39: Python check: 6.86% at $135
A40: Equity premium | B40: =B39-Inputs!$B$30 -> 0.02304793 | C40: over the 4.56% risk-free rate

Sheet SumOfParts
A1: Sum of parts against the market — paper Section 6, Table 3 ($M)
A3: Launch + Starlink (core) | B3: =DCF!$B$24+DCF!$B$42 -> 695704.19 | C3: DCF tab
A4: xAI: venture floor | B4: =Inputs!$B$70 -> 22555 | C4: Low end: the venture model with optimal abandonment (imported; abandonment embedded)
A5: xAI: winning model | B5: =Inputs!$B$71 -> 288402 | C5: High end: the xAI segment at a 30% terminal margin (imported)
A6: Net cash incl. proceeds | B6: =Inputs!$B$34+Inputs!$B$36-Inputs!$B$35 -> 76851
A7: Expansion claims + Mars | B7: =Options!$B$27 -> 65669.75 | C7: Options tab
A8: xAI abandonment option | B8: =Inputs!$B$69 -> 1492 | C8: Added at the high end only; embedded in the venture floor at the low end
A10: Supported range: low | B10: =B3+B4+B6+B7 -> 860779.94 | C10: Python check: 860,800
A11: Supported range: high | B11: =B3+B5+B6+B7+B8 -> 1128118.9 | C11: Python check: 1,128,139
A12: IPO capitalization | B12: =Inputs!$B$74*Inputs!$B$37 -> 1767285
A13: Unexplained premium (vs. high) | B13: =B12-B11 -> 639166.06
